Workbook
Name Walmart: 'Year to Date Profitability Repo'!$1:$989

Sheet Year to Date Profitability Repo
B1: Walmart
B2: Net Margins | C2: =IFERROR(__xludf.DUMMYFUNCTION("importrange(""https://docs.google.com/spreadsheets/d/1SpIQ08zdW-3HpkzcmPmRLalvhgOSNVUg8BE8acIkxHI/edit?gid=0#gid=0"",""PeriodSynch"")"),"Year to Date") -> Year to Date | D2: =IFERROR(__xludf.DUMMYFUNCTION("""COMPUTED_VALUE"""),"Last Month") -> Last Month | E2: =IFERROR(__xludf.DUMMYFUNCTION("""COMPUTED_VALUE"""),"Month to Date") -> Month to Date | F2: =IFERROR(__xludf.DUMMYFUNCTION("""COMPUTED_VALUE"""),"This Week") -> This Week | G2: =IFERROR(__xludf.DUMMYFUNCTION("""COMPUTED_VALUE"""),"Last Week") -> Last Week
C3: =IFERROR(__xludf.DUMMYFUNCTION("""COMPUTED_VALUE"""),2025.0) -> 2025 | D3: =IFERROR(__xludf.DUMMYFUNCTION("""COMPUTED_VALUE"""),"November") -> November | E3: =IFERROR(__xludf.DUMMYFUNCTION("""COMPUTED_VALUE"""),"December") -> December | F3: =IFERROR(__xludf.DUMMYFUNCTION("""COMPUTED_VALUE"""),45999.0) -> 45999 | G3: =IFERROR(__xludf.DUMMYFUNCTION("""COMPUTED_VALUE"""),45992.0) -> 45992
B4: 20% Projection | C4: =C5*20% -> 1597.952 | D4: =D5*20% -> 236 | E4: =E5*20% -> 0 | F4: =F5*20% -> 0 | G4: =G5*20% -> 0
B5: Net Profit Walmart | C5: =C7+(C12+C18+C33) -> 7989.76 | D5: =D7+(D12+D18+D33) -> 1180 | E5: =E7+(E12+E18+E33) -> 0 | F5: =F7+(F12+F18+F33) -> 0 | G5: =G7+(G12+G18+G33) -> 0
B6: Item Profit Vs. Returned Items | C6: =C7+C12 -> 8530.01 | D6: =D7+D12 -> 1235.93 | E6: =E7+E12 -> 0 | F6: =F7+F12 -> 0 | G6: =G7+G12 -> 0
B7: Walmart Item Sales Profit | C7: =SUM(C8:C10) -> 12259.45 | D7: =SUM(D8:D10) -> 1613.47 | E7: =SUM(E8:E10) -> 0 | F7: =SUM(F8:F10) -> 0 | G7: =SUM(G8:G10) -> 0
B8: Keystone | C8: =sumifs('Statements Legacy Report '!$CB:$CB,'Statements Legacy Report '!$CE:$CE,C$3,'Statements Legacy Report '!$F:$F,"SALE",'Statements Legacy Report '!$BW:$BW,$B8) -> 12259.45 | D8: =sumifs('Statements Legacy Report '!$CB:$CB,'Statements Legacy Report '!$CF:$CF,D$3,'Statements Legacy Report '!$F:$F,"SALE",'Statements Legacy Report '!$BW:$BW,$B8) -> 1613.47 | E8: =sumifs('Statements Legacy Report '!$CB:$CB,'Statements Legacy Report '!$CF:$CF,E$3,'Statements Legacy Report '!$F:$F,"SALE",'Statements Legacy Report '!$BW:$BW,$B8) -> 0 | F8: =sumifs('Statements Legacy Report '!$CB:$CB,'Statements Legacy Report '!$CG:$CG,F$2,'Statements Legacy Report '!$F:$F,"SALE",'Statements Legacy Report '!$BW:$BW,$B8) -> 0 | G8: =sumifs('Statements Legacy Report '!$CB:$CB,'Statements Legacy Report '!$CG:$CG,G$2,'Statements Legacy Report '!$F:$F,"SALE",'Statements Legacy Report '!$BW:$BW,$B8) -> 0
B9: eBay | C9: =sumifs('Statements Legacy Report '!$CB:$CB,'Statements Legacy Report '!$CE:$CE,C$3,'Statements Legacy Report '!$F:$F,"SALE",'Statements Legacy Report '!$BW:$BW,$B9) -> 0 | D9: =sumifs('Statements Legacy Report '!$CB:$CB,'Statements Legacy Report '!$CF:$CF,D$3,'Statements Legacy Report '!$F:$F,"SALE",'Statements Legacy Report '!$BW:$BW,$B9) -> 0 | E9: =sumifs('Statements Legacy Report '!$CB:$CB,'Statements Legacy Report '!$CF:$CF,E$3,'Statements Legacy Report '!$F:$F,"SALE",'Statements Legacy Report '!$BW:$BW,$B9) -> 0 | F9: =sumifs('Statements Legacy Report '!$CB:$CB,'Statements Legacy Report '!$CG:$CG,F$2,'Statements Legacy Report '!$F:$F,"SALE",'Statements Legacy Report '!$BW:$BW,$B9) -> 0 | G9: =sumifs('Statements Legacy Report '!$CB:$CB,'Statements Legacy Report '!$CG:$CG,G$2,'Statements Legacy Report '!$F:$F,"SALE",'Statements Legacy Report '!$BW:$BW,$B9) -> 0
B10: TAAS | C10: =sumifs('Statements Legacy Report '!$CB:$CB,'Statements Legacy Report '!$CE:$CE,C$3,'Statements Legacy Report '!$F:$F,"SALE",'Statements Legacy Report '!$BW:$BW,$B10) -> 0 | D10: =sumifs('Statements Legacy Report '!$CB:$CB,'Statements Legacy Report '!$CF:$CF,D$3,'Statements Legacy Report '!$F:$F,"SALE",'Statements Legacy Report '!$BW:$BW,$B10) -> 0 | E10: =sumifs('Statements Legacy Report '!$CB:$CB,'Statements Legacy Report '!$CF:$CF,E$3,'Statements Legacy Report '!$F:$F,"SALE",'Statements Legacy Report '!$BW:$BW,$B10) -> 0 | F10: =sumifs('Statements Legacy Report '!$CB:$CB,'Statements Legacy Report '!$CG:$CG,F$2,'Statements Legacy Report '!$F:$F,"SALE",'Statements Legacy Report '!$BW:$BW,$B10) -> 0 | G10: =sumifs('Statements Legacy Report '!$CB:$CB,'Statements Legacy Report '!$CG:$CG,G$2,'Statements Legacy Report '!$F:$F,"SALE",'Statements Legacy Report '!$BW:$BW,$B10) -> 0
B12: Returns Items Cost | C12: =SUM(C13:C15) -> -3729.44 | D12: =SUM(D13:D15) -> -377.54 | E12: =SUM(E13:E15) -> 0 | F12: =SUM(F13:F15) -> 0 | G12: =SUM(G13:G15) -> 0
B13: Keystone | C13: =sumifs('Statements Legacy Report '!$CA:$CA,'Statements Legacy Report '!$F:$F,"REFUNDED",'Statements Legacy Report '!$BW:$BW,$B13,'Statements Legacy Report '!CE:CE,C$3)*-1 -> -3729.44 | D13: =sumifs('Statements Legacy Report '!$CA:$CA,'Statements Legacy Report '!$F:$F,"REFUNDED",'Statements Legacy Report '!$BW:$BW,$B13,'Statements Legacy Report '!$CF:$CF,D$3)*-1 -> -377.54 | E13: =sumifs('Statements Legacy Report '!$CA:$CA,'Statements Legacy Report '!$F:$F,"REFUNDED",'Statements Legacy Report '!$BW:$BW,$B13,'Statements Legacy Report '!$CF:$CF,E$3)*-1 -> 0 | F13: =sumifs('Statements Legacy Report '!$CA:$CA,'Statements Legacy Report '!$F:$F,"REFUNDED",'Statements Legacy Report '!$BW:$BW,$B13,'Statements Legacy Report '!$CG:$CG,F$2)*-1 -> 0 | G13: =sumifs('Statements Legacy Report '!$CA:$CA,'Statements Legacy Report '!$F:$F,"REFUNDED",'Statements Legacy Report '!$BW:$BW,$B13,'Statements Legacy Report '!$CG:$CG,G$2)*-1 -> 0
B14: eBay | C14: =sumifs('Statements Legacy Report '!$CA:$CA,'Statements Legacy Report '!$F:$F,"REFUNDED",'Statements Legacy Report '!$BW:$BW,$B14,'Statements Legacy Report '!CE:CE,C$3)*-1 -> 0 | D14: =sumifs('Statements Legacy Report '!$CA:$CA,'Statements Legacy Report '!$F:$F,"REFUNDED",'Statements Legacy Report '!$BW:$BW,$B14,'Statements Legacy Report '!$CF:$CF,D$3)*-1 -> 0 | E14: =sumifs('Statements Legacy Report '!$CA:$CA,'Statements Legacy Report '!$F:$F,"REFUNDED",'Statements Legacy Report '!$BW:$BW,$B14,'Statements Legacy Report '!$CF:$CF,E$3)*-1 -> 0 | F14: =sumifs('Statements Legacy Report '!$CA:$CA,'Statements Legacy Report '!$F:$F,"REFUNDED",'Statements Legacy Report '!$BW:$BW,$B14,'Statements Legacy Report '!$CG:$CG,F$2)*-1 -> 0 | G14: =sumifs('Statements Legacy Report '!$CA:$CA,'Statements Legacy Report '!$F:$F,"REFUNDED",'Statements Legacy Report '!$BW:$BW,$B14,'Statements Legacy Report '!$CG:$CG,G$2)*-1 -> 0
B15: TAAS | C15: =sumifs('Statements Legacy Report '!$CA:$CA,'Statements Legacy Report '!$F:$F,"REFUNDED",'Statements Legacy Report '!$BW:$BW,$B15,'Statements Legacy Report '!CE:CE,C$3)*-1 -> 0 | D15: =sumifs('Statements Legacy Report '!$CA:$CA,'Statements Legacy Report '!$F:$F,"REFUNDED",'Statements Legacy Report '!$BW:$BW,$B15,'Statements Legacy Report '!$CF:$CF,D$3)*-1 -> 0 | E15: =sumifs('Statements Legacy Report '!$CA:$CA,'Statements Legacy Report '!$F:$F,"REFUNDED",'Statements Legacy Report '!$BW:$BW,$B15,'Statements Legacy Report '!$CF:$CF,E$3)*-1 -> 0 | F15: =sumifs('Statements Legacy Report '!$CA:$CA,'Statements Legacy Report '!$F:$F,"REFUNDED",'Statements Legacy Report '!$BW:$BW,$B15,'Statements Legacy Report '!$CG:$CG,F$2)*-1 -> 0 | G15: =sumifs('Statements Legacy Report '!$CA:$CA,'Statements Legacy Report '!$F:$F,"REFUNDED",'Statements Legacy Report '!$BW:$BW,$B15,'Statements Legacy Report '!$CG:$CG,G$2)*-1 -> 0
B18: Other Fees | C18: =SUM(C19) -> -540.25 | D18: =SUM(D19) -> -55.93 | E18: =SUM(E19) -> 0 | F18: =SUM(F19) -> 0 | G18: =SUM(G19) -> 0
B19: Adjustment Charges | C19: =sumifs('Statements Legacy Report '!$V:$V,'Statements Legacy Report '!$F:$F,"ADJMNT",'Statements Legacy Report '!CE:CE,C3) -> -540.25 | D19: =sumifs('Statements Legacy Report '!$V:$V,'Statements Legacy Report '!$F:$F,"ADJMNT",'Statements Legacy Report '!CF:CF,D3) -> -55.93 | E19: =sumifs('Statements Legacy Report '!$V:$V,'Statements Legacy Report '!$F:$F,"ADJMNT",'Statements Legacy Report '!CF:CF,E3) -> 0 | F19: =sumifs('Statements Legacy Report '!$V:$V,'Statements Legacy Report '!$F:$F,"ADJMNT",'Statements Legacy Report '!CG:CG,F2) -> 0 | G19: =sumifs('Statements Legacy Report '!$V:$V,'Statements Legacy Report '!$F:$F,"ADJMNT",'Statements Legacy Report '!CG:CG,G2) -> 0
B21: Purchase Reconciliations
B22: Keystone | C22: =sumifs('Statements Legacy Report '!$CA:$CA,'Statements Legacy Report '!$CE:$CE,C$3,'Statements Legacy Report '!$F:$F,"SALE",'Statements Legacy Report '!$BW:$BW,$B22) -> 17711.51 | D22: =sumifs('Statements Legacy Report '!$CA:$CA,'Statements Legacy Report '!$CF:$CF,D$3,'Statements Legacy Report '!$F:$F,"SALE",'Statements Legacy Report '!$BW:$BW,$B22) -> 2265.59 | E22: =sumifs('Statements Legacy Report '!$CA:$CA,'Statements Legacy Report '!$CF:$CF,E$3,'Statements Legacy Report '!$F:$F,"SALE",'Statements Legacy Report '!$BW:$BW,$B22) -> 0 | F22: =sumifs('Statements Legacy Report '!$CA:$CA,'Statements Legacy Report '!$CG:$CG,F$2,'Statements Legacy Report '!$F:$F,"SALE",'Statements Legacy Report '!$BW:$BW,$B22) -> 0 | G22: =sumifs('Statements Legacy Report '!$CA:$CA,'Statements Legacy Report '!$CG:$CG,G$2,'Statements Legacy Report '!$F:$F,"SALE",'Statements Legacy Report '!$BW:$BW,$B22) -> 0
B23: TAAS | C23: =sumifs('Statements Legacy Report '!$CA:$CA,'Statements Legacy Report '!$CE:$CE,C$3,'Statements Legacy Report '!$F:$F,"SALE",'Statements Legacy Report '!$BW:$BW,$B23) -> 0 | D23: =sumifs('Statements Legacy Report '!$CA:$CA,'Statements Legacy Report '!$CF:$CF,D$3,'Statements Legacy Report '!$F:$F,"SALE",'Statements Legacy Report '!$BW:$BW,$B23) -> 0 | E23: =sumifs('Statements Legacy Report '!$CA:$CA,'Statements Legacy Report '!$CF:$CF,E$3,'Statements Legacy Report '!$F:$F,"SALE",'Statements Legacy Report '!$BW:$BW,$B23) -> 0 | F23: =sumifs('Statements Legacy Report '!$CA:$CA,'Statements Legacy Report '!$CG:$CG,F$2,'Statements Legacy Report '!$F:$F,"SALE",'Statements Legacy Report '!$BW:$BW,$B23) -> 0 | G23: =sumifs('Statements Legacy Report '!$CA:$CA,'Statements Legacy Report '!$CG:$CG,G$2,'Statements Legacy Report '!$F:$F,"SALE",'Statements Legacy Report '!$BW:$BW,$B23) -> 0
B24: eBay | C24: =sumifs('Statements Legacy Report '!$CA:$CA,'Statements Legacy Report '!$CE:$CE,C$3,'Statements Legacy Report '!$F:$F,"SALE",'Statements Legacy Report '!$BW:$BW,$B24) -> 0 | D24: =sumifs('Statements Legacy Report '!$CA:$CA,'Statements Legacy Report '!$CF:$CF,D$3,'Statements Legacy Report '!$F:$F,"SALE",'Statements Legacy Report '!$BW:$BW,$B24) -> 0 | E24: =sumifs('Statements Legacy Report '!$CA:$CA,'Statements Legacy Report '!$CF:$CF,E$3,'Statements Legacy Report '!$F:$F,"SALE",'Statements Legacy Report '!$BW:$BW,$B24) -> 0 | F24: =sumifs('Statements Legacy Report '!$CA:$CA,'Statements Legacy Report '!$CG:$CG,F$2,'Statements Legacy Report '!$F:$F,"SALE",'Statements Legacy Report '!$BW:$BW,$B24) -> 0 | G24: =sumifs('Statements Legacy Report '!$CA:$CA,'Statements Legacy Report '!$CG:$CG,G$2,'Statements Legacy Report '!$F:$F,"SALE",'Statements Legacy Report '!$BW:$BW,$B24) -> 0
B26: Sales | C26: =IFERROR(__xludf.DUMMYFUNCTION("importrange(""https://docs.google.com/spreadsheets/d/1SpIQ08zdW-3HpkzcmPmRLalvhgOSNVUg8BE8acIkxHI/edit?gid=0#gid=0"",""PeriodSynch"")"),"Year to Date") -> Year to Date | D26: =IFERROR(__xludf.DUMMYFUNCTION("""COMPUTED_VALUE"""),"Last Month") -> Last Month | E26: =IFERROR(__xludf.DUMMYFUNCTION("""COMPUTED_VALUE"""),"Month to Date") -> Month to Date | F26: =IFERROR(__xludf.DUMMYFUNCTION("""COMPUTED_VALUE"""),"This Week") -> This Week | G26: =IFERROR(__xludf.DUMMYFUNCTION("""COMPUTED_VALUE"""),"Last Week") -> Last Week
C27: =IFERROR(__xludf.DUMMYFUNCTION("""COMPUTED_VALUE"""),2025.0) -> 2025 | D27: =IFERROR(__xludf.DUMMYFUNCTION("""COMPUTED_VALUE"""),"November") -> November | E27: =IFERROR(__xludf.DUMMYFUNCTION("""COMPUTED_VALUE"""),"December") -> December | F27: =IFERROR(__xludf.DUMMYFUNCTION("""COMPUTED_VALUE"""),45999.0) -> 45999 | G27: =IFERROR(__xludf.DUMMYFUNCTION("""COMPUTED_VALUE"""),45992.0) -> 45992
B28: All Vendors | C28: =SUM(C29:C31) -> 33274 | D28: =SUM(D29:D31) -> 4244.8 | E28: =SUM(E29:E31) -> 0 | F28: =SUM(F29:F31) -> 0 | G28: =SUM(G29:G31) -> 0
B29: Keystone | C29: =sumifs('Statements Legacy Report '!$U:$U,'Statements Legacy Report '!$CE:$CE,C$3,'Statements Legacy Report '!$F:$F,"SALE",'Statements Legacy Report '!$BW:$BW,$B29) -> 33274 | D29: =sumifs('Statements Legacy Report '!$U:$U,'Statements Legacy Report '!$CF:$CF,D$3,'Statements Legacy Report '!$F:$F,"SALE",'Statements Legacy Report '!$BW:$BW,$B29) -> 4244.8 | E29: =sumifs('Statements Legacy Report '!$U:$U,'Statements Legacy Report '!$CF:$CF,E$3,'Statements Legacy Report '!$F:$F,"SALE",'Statements Legacy Report '!$BW:$BW,$B29) -> 0 | F29: =sumifs('Statements Legacy Report '!$U:$U,'Statements Legacy Report '!$CG:$CG,F$2,'Statements Legacy Report '!$F:$F,"SALE",'Statements Legacy Report '!$BW:$BW,$B29) -> 0 | G29: =sumifs('Statements Legacy Report '!$U:$U,'Statements Legacy Report '!$CG:$CG,G$2,'Statements Legacy Report '!$F:$F,"SALE",'Statements Legacy Report '!$BW:$BW,$B29) -> 0
B30: eBay | C30: =sumifs('Statements Legacy Report '!$U:$U,'Statements Legacy Report '!$CE:$CE,C$3,'Statements Legacy Report '!$F:$F,"SALE",'Statements Legacy Report '!$BW:$BW,$B30) -> 0 | D30: =sumifs('Statements Legacy Report '!$U:$U,'Statements Legacy Report '!$CF:$CF,D$3,'Statements Legacy Report '!$F:$F,"SALE",'Statements Legacy Report '!$BW:$BW,$B30) -> 0 | E30: =sumifs('Statements Legacy Report '!$U:$U,'Statements Legacy Report '!$CF:$CF,E$3,'Statements Legacy Report '!$F:$F,"SALE",'Statements Legacy Report '!$BW:$BW,$B30) -> 0 | F30: =sumifs('Statements Legacy Report '!$U:$U,'Statements Legacy Report '!$CG:$CG,F$2,'Statements Legacy Report '!$F:$F,"SALE",'Statements Legacy Report '!$BW:$BW,$B30) -> 0 | G30: =sumifs('Statements Legacy Report '!$U:$U,'Statements Legacy Report '!$CG:$CG,G$2,'Statements Legacy Report '!$F:$F,"SALE",'Statements Legacy Report '!$BW:$BW,$B30) -> 0
B31: TAAS | C31: =sumifs('Statements Legacy Report '!$U:$U,'Statements Legacy Report '!$CE:$CE,C$3,'Statements Legacy Report '!$F:$F,"SALE",'Statements Legacy Report '!$BW:$BW,$B31) -> 0 | D31: =sumifs('Statements Legacy Report '!$U:$U,'Statements Legacy Report '!$CF:$CF,D$3,'Statements Legacy Report '!$F:$F,"SALE",'Statements Legacy Report '!$BW:$BW,$B31) -> 0 | E31: =sumifs('Statements Legacy Report '!$U:$U,'Statements Legacy Report '!$CF:$CF,E$3,'Statements Legacy Report '!$F:$F,"SALE",'Statements Legacy Report '!$BW:$BW,$B31) -> 0 | F31: =sumifs('Statements Legacy Report '!$U:$U,'Statements Legacy Report '!$CG:$CG,F$2,'Statements Legacy Report '!$F:$F,"SALE",'Statements Legacy Report '!$BW:$BW,$B31) -> 0 | G31: =sumifs('Statements Legacy Report '!$U:$U,'Statements Legacy Report '!$CG:$CG,G$2,'Statements Legacy Report '!$F:$F,"SALE",'Statements Legacy Report '!$BW:$BW,$B31) -> 0
B33: Ads and Campaigns

Sheet Statements Legacy Report 
A1: Walmart.com Order # | B1: Walmart.com Order Line # | C1: Walmart.com PO # | D1: Walmart.com P.O. Line # | E1: Partner Order # | F1: Transaction Type | G1: Transaction Date Time | H1: Shipped Qty | I1: Partner Item ID | J1: Partner GTIN | K1: Partner Item name | L1: Product tax code | M1: Shipping tax code | N1: Gift wrap tax code | O1: Ship to state | P1: Ship to county | Q1: County Code | R1: Ship to city | S1: Zip code | T1: shipping_method | U1: Total tender to / from customer | V1: Payable to Partner from Sale | W1: Commission from Sale | X1: Commission Rate | Y1: Gross Sales Revenue | Z1: Refunded Retail Sales | AA1: Sales refund for Escalation | AB1: Gross Shipping Revenue | AC1: Gross Shipping Refunded | AD1: Shipping refund for Escalation | AE1: Net Shipping Revenue | AF1: Gross Fee Revenue | AG1: Gross Fee Refunded | AH1: Fee refund for Escalation | AI1: Net Fee Revenue | AJ1: Gift Wrap Quantity | AK1: Gross Gift-Wrap Revenue | AL1: Gross Gift-Wrap Refunded | AM1: Gift wrap refund for Escalation | AN1: Net Gift Wrap Revenue | AO1: Tax on Sales Revenue | AP1: Tax on Shipping Revenue | AQ1: Tax on Gift-Wrap Revenue | AR1: Tax on Fee Revenue | AS1: Effective tax rate | AT1: Tax on Refunded Sales | AU1: Tax on Shipping Refund | AV1: Tax on Gift-Wrap Refund | AW1: Tax on Fee Refund | AX1: Tax on Sales refund for Escalation | AY1: Tax on Shipping Refund for Escalation | AZ1: Tax on Gift-Wrap Refund for escalation | BA1: Tax on Fee Refund for escalation | BB1: Total NET Tax Collected | BC1: Tax Withheld | BD1: Adjustment Description | BE1: Adjustment Code | BF1: Original Item price | BG1: Original Commission Amount | BH1: Spec Category | BI1: Contract Category | BJ1: Product Type | BK1: Flex Commission Rule | BL1: Return Reason Code | BM1: Return Reason Description | BN1: Fee Withheld Flag | BO1: Fulfillment Type | BP1: Fulfillment Details | BQ1: Commission Incentive Program | BR1: Commission Saving | BS1: Customer Promo Type | BT1: Total Walmart Funded Savings | BU1: Total Walmart Funded Savings Program | BV1: Item Condition | BW1: Vendor | BX1: Fill PN | BY1: Item Cost | BZ1: Ship Cost | CA1: Total Cost | CB1: Net Profit | CC1: Returned Item | CD1: Returned Item Vendor | CE1: Year | CF1: Month | CG1: ='Year to Date Profitability Repo'!F3 -> 45999
A2: 200013453756657 | B2: 1 | C2: 109015177922183 | D2: 1 | F2: SALE | G2: 45807 | H2: 1 | I2: WM-FR-IMP-4261104150-16CH6VP | J2: 460776237725 | K2: 16 Chrome Wheel Skins Set Compatible with 16-23 Toyota Tacoma TRD Off-Road TRD Sport SR SR5 Limited 17-23 Tacoma TRD Pro 2021 Tacoma Trail & 2023 Tacoma Trail Special Edition | L2: 2038710 | O2: FL | R2: Miami | S2: 33177 | T2: Marketplace standard | U2: 115.54 | V2: 100.42 | W2: 7.56 | X2: 7 | Y2: 107.98 | Z2: 0 | AA2: 0 | AB2: 0 | AC2: 0 | AD2: 0 | AE2: 0 | AF2: 0 | AG2: 0 | AH2: 0 | AI2: 0 | AJ2: 0 | AK2: 0 | AL2: 0 | AM2: 0 | AN2: 0 | AO2: 7.56 | AP2: 0 | AQ2: 0 | AR2: 0 | AS2: 0 | AT2: 0 | AU2: 0 | AV2: 0 | AW2: 0 | AX2: 0 | AY2: 0 | AZ2: 0 | BA2: 0 | BB2: 7.56 | BC2: Y | BG2: -10.8 | BH2: Wheels & Wheel Components | BI2: Tires & Wheels | BJ2: Automotive Wheel Covers & Hub Caps | BK2: PRO-119076-18.0 | BN2: N | BO2: Seller Fulfilled | BP2: Delivery | BQ2: New Seller Saving | BR2: 3.24 | BW2: =if(OR(F2="SALE",F2="REFUNDED"),IFERROR(Vlookup(I2,'Listing SKU - Fill SKU Mapping'!A:C,3,false),"Map"),"") -> Keystone | BX2: =IF(OR(F2="SALE",F2="REFUNDED")=TRUE,iferror(Vlookup(I2,'Listing SKU - Fill SKU Mapping'!A:B,2,false),"Map"),"") -> IMP445X | BY2: =IF(OR(F2="SALE",F2="REFUNDED")=TRUE,iferror(Vlookup(I2,'Listing SKU - Fill SKU Mapping'!A:D,4,false),"Map"),"") -> 49.71 | BZ2: =If(BW2="Keystone",11.5,"") -> 11.5 | CA2: =IF(ISNUMBER(BY2)=TRUE,BY2+BZ2,"") -> 61.21 | CB2: =if(F2="SALE",V2-CA2,"") -> 39.21 | CC2: =if(F2="REFUNDED",iferror(Vlookup(I2,'Listing SKU - Fill SKU Mapping'!A:B,2,false),"Map"),"") | CD2: =if(F2="REFUNDED",iferror(Vlookup(I2,'Listing SKU - Fill SKU Mapping'!A:C,3,false),"Map"),"") | CE2: =TEXT(G2,"YYYY") -> 2025 | CF2: =TEXT(G2,"MMMM") -> May | CG2: =IF(AND((G2-CG$1)>=0,(G2-CG$1)<=6), "This Week",IF(AND((G2-CG$1)>=-7,(G2-CG$1)<=-1), "Last Week",""))
A3: 200013452446032 | B3: 1 | C3: 109014451419163 | D3: 1 | F3: SALE | G3: 45804 | H3: 1 | I3: WM-FR-IMP-6BG71GSAAB-17CH10S | J3: 465595333719 | K3: Set of 4 17 inch Chrome ABS Wheel Skins Compatible with 2019 - 2021 Jeep Cherokee Latitude; 2019 - 2021 Jeep Cherokee Latitude Plus Impostors for 6BG71GSAAB Wheel Series | L3: 2038710 | O3: MD | R3: Essex | S3: 21221 | T3: Marketplace standard | U3: 93.26 | V3: 81.82 | W3: 6.16 | X3: 7 | Y3: 87.98 | Z3: 0 | AA3: 0 | AB3: 0 | AC3: 0 | AD3: 0 | AE3: 0 | AF3: 0 | AG3: 0 | AH3: 0 | AI3: 0 | AJ3: 0 | AK3: 0 | AL3: 0 | AM3: 0 | AN3: 0 | AO3: 5.28 | AP3: 0 | AQ3: 0 | AR3: 0 | AS3: 0 | AT3: 0 | AU3: 0 | AV3: 0 | AW3: 0 | AX3: 0 | AY3: 0 | AZ3: 0 | BA3: 0 | BB3: 5.28 | BC3: Y | BG3: -8.8 | BH3: Wheels & Wheel Components | BI3: Tires & Wheels | BJ3: Automotive Wheel Covers & Hub Caps | BK3: PRO-119076-17.0 | BN3: N | BO3: Seller Fulfilled | BP3: Delivery | BQ3: New Seller Saving | BR3: 2.64 | BW3: =if(OR(F3="SALE",F3="REFUNDED"),IFERROR(Vlookup(I3,'Listing SKU - Fill SKU Mapping'!A:C,3,false),"Map"),"") -> Keystone | BX3: =IF(OR(F3="SALE",F3="REFUNDED")=TRUE,iferror(Vlookup(I3,'Listing SKU - Fill SKU Mapping'!A:B,2,false),"Map"),"") -> IMP457X | BY3: =IF(OR(F3="SALE",F3="REFUNDED")=TRUE,iferror(Vlookup(I3,'Listing SKU - Fill SKU Mapping'!A:D,4,false),"Map"),"") -> 49.71 | BZ3: =If(BW3="Keystone",11.5,"") -> 11.5 | CA3: =IF(ISNUMBER(BY3)=TRUE,BY3+BZ3,"") -> 61.21 | CB3: =if(F3="SALE",V3-CA3,"") -> 20.61 | CC3: =if(F3="REFUNDED",iferror(Vlookup(I3,'Listing SKU - Fill SKU Mapping'!A:B,2,false),"Map"),"") | CD3: =if(F3="REFUNDED",iferror(Vlookup(I3,'Listing SKU - Fill SKU Mapping'!A:C,3,false),"Map"),"") | CE3: =TEXT(G3,"YYYY") -> 2025 | CF3: =TEXT(G3,"MMMM") -> May | CG3: =IF(AND((G3-CG$1)>=0,(G3-CG$1)<=6), "This Week",IF(AND((G3-CG$1)>=-7,(G3-CG$1)<=-1), "Last Week",""))
A4: 200013446882232 | B4: 1 | C4: 109014970676989 | D4: 1 | F4: SALE | G4: 45805 | H4: 1 | I4: WM-KS-FRHC-53094-17SL | J4: 467129945498 | K4: Fuel Rider Set of 4 17 inch Silver Snap-On Hubcaps With 10 Spoke Compatible With 2014-2020 Nissan Rogue S Standard Steel Wheel Covers | L4: 2038710 | O4: TN | R4: Dresden | S4: 38225 | T4: Marketplace standard | U4: 73.51 | V4: 62.29 | W4: 4.69 | X4: 7 | Y4: 66.98 | Z4: 0 | AA4: 0 | AB4: 0 | AC4: 0 | AD4: 0 | AE4: 0 | AF4: 0 | AG4: 0 | AH4: 0 | AI4: 0 | AJ4: 0 | AK4: 0 | AL4: 0 | AM4: 0 | AN4: 0 | AO4: 6.53 | AP4: 0 | AQ4: 0 | AR4: 0 | AS4: 0 | AT4: 0 | AU4: 0 | AV4: 0 | AW4: 0 | AX4: 0 | AY4: 0 | AZ4: 0 | BA4: 0 | BB4: 6.53 | BC4: Y | BG4: -6.7 | BH4: Wheels & Wheel Components | BI4: Tires & Wheels | BJ4: Automotive Wheel Covers & Hub Caps | BK4: PRO-119076-17.0 | BN4: N | BO4: Seller Fulfilled | BP4: Delivery | BQ4: New Seller Saving | BR4: 2.01 | BW4: =if(OR(F4="SALE",F4="REFUNDED"),IFERROR(Vlookup(I4,'Listing SKU - Fill SKU Mapping'!A:C,3,false),"Map"),"") -> Keystone | BX4: =IF(OR(F4="SALE",F4="REFUNDED")=TRUE,iferror(Vlookup(I4,'Listing SKU - Fill SKU Mapping'!A:B,2,false),"Map"),"") -> 51917S | BY4: =IF(OR(F4="SALE",F4="REFUNDED")=TRUE,iferror(Vlookup(I4,'Listing SKU - Fill SKU Mapping'!A:D,4,false),"Map"),"") -> 27.22 | BZ4: =If(BW4="Keystone",11.5,"") -> 11.5 | CA4: =IF(ISNUMBER(BY4)=TRUE,BY4+BZ4,"") -> 38.72 | CB4: =if(F4="SALE",V4-CA4,"") -> 23.57 | CC4: =if(F4="REFUNDED",iferror(Vlookup(I4,'Listing SKU - Fill SKU Mapping'!A:B,2,false),"Map"),"") | CD4: =if(F4="REFUNDED",iferror(Vlookup(I4,'Listing SKU - Fill SKU Mapping'!A:C,3,false),"Map"),"") | CE4: =TEXT(G4,"YYYY") -> 2025 | CF4: =TEXT(G4,"MMMM") -> May | CG4: =IF(AND((G4-CG$1)>=0,(G4-CG$1)<=6), "This Week",IF(AND((G4-CG$1)>=-7,(G4-CG$1)<=-1), "Last Week",""))
A5: 200013323467099 | B5: 1 | C5: 109014553225598 | D5: 1 | F5: SALE | G5: 45804 | H5: 1 | I5: WM-FR-IMP-9965087590-19GB5SS | J5: 465595354127 | K5: Set of 4 19 inch Gloss Black ABS Wheel Skins Compatible with 2014 - 2017 Mazda 6 Touring Impostors for 9965087590 Wheel Series | L5: 2038710 | O5: NC | R5: Fayetteville | S5: 28314 | T5: Marketplace standard | U5: 72.74 | V5: 63.22 | W5: 4.76 | X5: 7 | Y5: 67.98 | Z5: 0 | AA5: 0 | AB5: 0 | AC5: 0 | AD5: 0 | AE5: 0 | AF5: 0 | AG5: 0 | AH5: 0 | AI5: 0 | AJ5: 0 | AK5: 0 | AL5: 0 | AM5: 0 | AN5: 0 | AO5: 4.76 | AP5: 0 | AQ5: 0 | AR5: 0 | AS5: 0 | AT5: 0 | AU5: 0 | AV5: 0 | AW5: 0 | AX5: 0 | AY5: 0 | AZ5: 0 | BA5: 0 | BB5: 4.76 | BC5: Y | BG5: -6.8 | BH5: Wheels & Wheel Components | BI5: Tires & Wheels | BJ5: Automotive Wheel Covers & Hub Caps | BK5: PRO-119076-17.0 | BN5: N | BO5: Seller Fulfilled | BP5: Delivery | BQ5: New Seller Saving | BR5: 2.04 | BW5: =if(OR(F5="SALE",F5="REFUNDED"),IFERROR(Vlookup(I5,'Listing SKU - Fill SKU Mapping'!A:C,3,false),"Map"),"") -> Keystone | BX5: =IF(OR(F5="SALE",F5="REFUNDED")=TRUE,iferror(Vlookup(I5,'Listing SKU - Fill SKU Mapping'!A:B,2,false),"Map"),"") -> IMP472BLK | BY5: =IF(OR(F5="SALE",F5="REFUNDED")=TRUE,iferror(Vlookup(I5,'Listing SKU - Fill SKU Mapping'!A:D,4,false),"Map"),"") -> 48.52 | BZ5: =If(BW5="Keystone",11.5,"") -> 11.5 | CA5: =IF(ISNUMBER(BY5)=TRUE,BY5+BZ5,"") -> 60.02 | CB5: =if(F5="SALE",V5-CA5,"") -> 3.2 | CC5: =if(F5="REFUNDED",iferror(Vlookup(I5,'Listing SKU - Fill SKU Mapping'!A:B,2,false),"Map"),"") | CD5: =if(F5="REFUNDED",iferror(Vlookup(I5,'Listing SKU - Fill SKU Mapping'!A:C,3,false),"Map"),"") | CE5: =TEXT(G5,"YYYY") -> 2025 | CF5: =TEXT(G5,"MMMM") -> May | CG5: =IF(AND((G5-CG$1)>=0,(G5-CG$1)<=6), "This Week",IF(AND((G5-CG$1)>=-7,(G5-CG$1)<=-1), "Last Week",""))
A6: 200013323467099 | B6: 1 | C6: 109014553225598 | D6: 1 | F6: REFUNDED | G6: 45804 | H6: 1 | I6: WM-FR-IMP-9965087590-19GB5SS | J6: 465595354127 | K6: Set of 4 19 inch Gloss Black ABS Wheel Skins Compatible with 2014 - 2017 Mazda 6 Touring Impostors for 9965087590 Wheel Series | L6: 2038710 | R6: Fayetteville | S6: 28314 | U6: -72.74 | V6: -63.22 | W6: -4.76 | X6: 0 | Y6: 0 | Z6: -67.98 | AA6: 0 | AB6: 0 | AC6: 0 | AD6: 0 | AE6: 0 | AF6: 0 | AG6: 0 | AH6: 0 | AI6: 0 | AJ6: 0 | AK6: 0 | AL6: 0 | AM6: 0 | AN6: 0 | AO6: 0 | AP6: 0 | AQ6: 0 | AR6: 0 | AS6: 0 | AT6: -4.76 | AU6: 0 | AV6: 0 | AW6: 0 | AX6: 0 | AY6: 0 | AZ6: 0 | BA6: 0 | BB6: -4.76 | BC6: Y | BD6: Seller Initiated Returns | BE6: 5009 | BH6: Wheels & Wheel Components | BI6: Tires & Wheels | BL6: 1000 | BM6: No Longer Wanted | BN6: N | BO6: Seller Fulfilled | BW6: =if(OR(F6="SALE",F6="REFUNDED"),IFERROR(Vlookup(I6,'Listing SKU - Fill SKU Mapping'!A:C,3,false),"Map"),"") -> Keystone | BX6: =IF(OR(F6="SALE",F6="REFUNDED")=TRUE,iferror(Vlookup(I6,'Listing SKU - Fill SKU Mapping'!A:B,2,false),"Map"),"") -> IMP472BLK | BY6: =IF(OR(F6="SALE",F6="REFUNDED")=TRUE,iferror(Vlookup(I6,'Listing SKU - Fill SKU Mapping'!A:D,4,false),"Map"),"") -> 48.52 | BZ6: =If(BW6="Keystone",11.5,"") -> 11.5 | CA6: =IF(ISNUMBER(BY6)=TRUE,BY6+BZ6,"") -> 60.02 | CB6: =if(F6="SALE",V6-CA6,"") | CC6: =if(F6="REFUNDED",iferror(Vlookup(I6,'Listing SKU - Fill SKU Mapping'!A:B,2,false),"Map"),"") -> IMP472BLK | CD6: =if(F6="REFUNDED",iferror(Vlookup(I6,'Listing SKU - Fill SKU Mapping'!A:C,3,false),"Map"),"") -> Keystone | CE6: =TEXT(G6,"YYYY") -> 2025 | CF6: =TEXT(G6,"MMMM") -> May | CG6: =IF(AND((G6-CG$1)>=0,(G6-CG$1)<=6), "This Week",IF(AND((G6-CG$1)>=-7,(G6-CG$1)<=-1), "Last Week",""))
A7: 200013260994642 | B7: 1 | C7: 109015075316005 | D7: 1 | F7: SALE | G7: 45806 | H7: 1 | I7: WM-KS-FRHC-53073-15SL | J7: 469971001575 | K7: Fuel Rider Set of 4 15 inch Silver Snap-On Hubcaps With 6 Spoke Compatible With 2007-2012 Nissan Sentra Standard Steel Wheel Covers | L7: 2038710 | O7: MA | R7: Chicopee | S7: 1020 | T7: Marketplace standard | U7: 50.98 | V7: 44.62 | W7: 3.36 | X7: 7 | Y7: 47.98 | Z7: 0 | AA7: 0 | AB7: 0 | AC7: 0 | AD7: 0 | AE7: 0 | AF7: 0 | AG7: 0 | AH7: 0 | AI7: 0 | AJ7: 0 | AK7: 0 | AL7: 0 | AM7: 0 | AN7: 0 | AO7: 3 | AP7: 0 | AQ7: 0 | AR7: 0 | AS7: 0 | AT7: 0 | AU7: 0 | AV7: 0 | AW7: 0 | AX7: 0 | AY7: 0 | AZ7: 0 | BA7: 0 | BB7: 3 | BC7: Y | BG7: -4.8 | BH7: Wheels & Wheel Components | BI7: Tires & Wheels | BJ7: Automotive Wheel Covers & Hub Caps | BK7: PRO-119076-17.0 | BN7: N | BO7: Seller Fulfilled | BP7: Delivery | BQ7: New Seller Saving | BR7: 1.44 | BW7: =if(OR(F7="SALE",F7="REFUNDED"),IFERROR(Vlookup(I7,'Listing SKU - Fill SKU Mapping'!A:C,3,false),"Map"),"") -> Keystone | BX7: =IF(OR(F7="SALE",F7="REFUNDED")=TRUE,iferror(Vlookup(I7,'Listing SKU - Fill SKU Mapping'!A:B,2,false),"Map"),"") -> 43615S | BY7: =IF(OR(F7="SALE",F7="REFUNDED")=TRUE,iferror(Vlookup(I7,'Listing SKU - Fill SKU Mapping'!A:D,4,false),"Map"),"") -> 14.99 | BZ7: =If(BW7="Keystone",11.5,"") -> 11.5 | CA7: =IF(ISNUMBER(BY7)=TRUE,BY7+BZ7,"") -> 26.49 | CB7: =if(F7="SALE",V7-CA7,"") -> 18.13 | CC7: =if(F7="REFUNDED",iferror(Vlookup(I7,'Listing SKU - Fill SKU Mapping'!A:B,2,false),"Map"),"") | CD7: =if(F7="REFUNDED",iferror(Vlookup(I7,'Listing SKU - Fill SKU Mapping'!A:C,3,false),"Map"),"") | CE7: =TEXT(G7,"YYYY") -> 2025 | CF7: =TEXT(G7,"MMMM") -> May | CG7: =IF(AND((G7-CG$1)>=0,(G7-CG$1)<=6), "This Week",IF(AND((G7-CG$1)>=-7,(G7-CG$1)<=-1), "Last Week",""))
A8: 200013238424317 | B8: 1 | C8: 109015074290606 | D8: 1 | F8: SALE | G8: 45806 | H8: 1 | I8: WM-FR-IMP-3943-17CH5SP | J8: 460776238333 | K8: 17 inch Chrome ABS Wheel Skins Set Compatible with 2013-2016 Ford Escape 2017-2019 Escape SE & Impostors for 3943 Wheel Series | L8: 2038710 | O8: OH | R8: Amherst | S8: 44001 | T8: Marketplace standard | U8: 105.41 | V8: 92.05 | W8: 6.93 | X8: 7 | Y8: 98.98 | Z8: 0 | AA8: 0 | AB8: 0 | AC8: 0 | AD8: 0 | AE8: 0 | AF8: 0 | AG8: 0 | AH8: 0 | AI8: 0 | AJ8: 0 | AK8: 0 | AL8: 0 | AM8: 0 | AN8: 0 | AO8: 6.43 | AP8: 0 | AQ8: 0 | AR8: 0 | AS8: 0 | AT8: 0 | AU8: 0 | AV8: 0 | AW8: 0 | AX8: 0 | AY8: 0 | AZ8: 0 | BA8: 0 | BB8: 6.43 | BC8: Y | BG8: -9.9 | BH8: Wheels & Wheel Components | BI8: Tires & Wheels | BJ8: Automotive Wheel Covers & Hub Caps | BK8: PRO-119076-17.0 | BN8: N | BO8: Seller Fulfilled | BP8: Delivery | BQ8: New Seller Saving | BR8: 2.97 | BW8: =if(OR(F8="SALE",F8="REFUNDED"),IFERROR(Vlookup(I8,'Listing SKU - Fill SKU Mapping'!A:C,3,false),"Map"),"") -> Keystone | BX8: =IF(OR(F8="SALE",F8="REFUNDED")=TRUE,iferror(Vlookup(I8,'Listing SKU - Fill SKU Mapping'!A:B,2,false),"Map"),"") -> IMP371X | BY8: =IF(OR(F8="SALE",F8="REFUNDED")=TRUE,iferror(Vlookup(I8,'Listing SKU - Fill SKU Mapping'!A:D,4,false),"Map"),"") -> 43.79 | BZ8: =If(BW8="Keystone",11.5,"") -> 11.5 | CA8: =IF(ISNUMBER(BY8)=TRUE,BY8+BZ8,"") -> 55.29 | CB8: =if(F8="SALE",V8-CA8,"") -> 36.76 | CC8: =if(F8="REFUNDED",iferror(Vlookup(I8,'Listing SKU - Fill SKU Mapping'!A:B,2,false),"Map"),"") | CD8: =if(F8="REFUNDED",iferror(Vlookup(I8,'Listing SKU - Fill SKU Mapping'!A:C,3,false),"Map"),"") | CE8: =TEXT(G8,"YYYY") -> 2025 | CF8: =TEXT(G8,"MMMM") -> May | CG8: =IF(AND((G8-CG$1)>=0,(G8-CG$1)<=6), "This Week",IF(AND((G8-CG$1)>=-7,(G8-CG$1)<=-1), "Last Week",""))
A9: 200013169413632 | B9: 1 | C9: 109014759518921 | D9: 1 | F9: REFUNDED | G9: 45805 | H9: 1 | I9: WM-FR-IMP-84760166-18GB6VS | J9: 465595320771 | K9: Set of 4 18 inch Gloss Black ABS Wheel Skins Compatible with 2017 - 2019 GMC Acadia SLE; 2017 - 2019 GMC Acadia SLT Impostors for 84760166 22996315 Wheel Series | L9: 2038710 | R9: New Orleans | S9: 70125 | U9: -71.92 | V9: -61.36 | W9: -4.62 | X9: 0 | Y9: 0 | Z9: -65.98 | AA9: 0 | AB9: 0 | AC9: 0 | AD9: 0 | AE9: 0 | AF9: 0 | AG9: 0 | AH9: 0 | AI9: 0 | AJ9: 0 | AK9: 0 | AL9: 0 | AM9: 0 | AN9: 0 | AO9: 0 | AP9: 0 | AQ9: 0 | AR9: 0 | AS9: 0 | AT9: -5.94 | AU9: 0 | AV9: 0 | AW9: 0 | AX9: 0 | AY9: 0 | AZ9: 0 | BA9: 0 | BB9: -5.94 | BC9: Y | BD9: Seller Initiated Returns | BE9: 5009 | BH9: Wheels & Wheel Components | BI9: Tires & Wheels | BL9: 1000 | BM9: No Longer Wanted | BN9: N | BO9: Seller Fulfilled | BW9: =if(OR(F9="SALE",F9="REFUNDED"),IFERROR(Vlookup(I9,'Listing SKU - Fill SKU Mapping'!A:C,3,false),"Map"),"") -> Keystone | BX9: =IF(OR(F9="SALE",F9="REFUNDED")=TRUE,iferror(Vlookup(I9,'Listing SKU - Fill SKU Mapping'!A:B,2,false),"Map"),"") -> IMP466BLK | BY9: =IF(OR(F9="SALE",F9="REFUNDED")=TRUE,iferror(Vlookup(I9,'Listing SKU - Fill SKU Mapping'!A:D,4,false),"Map"),"") -> 62.33 | BZ9: =If(BW9="Keystone",11.5,"") -> 11.5 | CA9: =IF(ISNUMBER(BY9)=TRUE,BY9+BZ9,"") -> 73.83 | CB9: =if(F9="SALE",V9-CA9,"") | CC9: =if(F9="REFUNDED",iferror(Vlookup(I9,'Listing SKU - Fill SKU Mapping'!A:B,2,false),"Map"),"") -> IMP466BLK | CD9: =if(F9="REFUNDED",iferror(Vlookup(I9,'Listing SKU - Fill SKU Mapping'!A:C,3,false),"Map"),"") -> Keystone | CE9: =TEXT(G9,"YYYY") -> 2025 | CF9: =TEXT(G9,"MMMM") -> May | CG9: =IF(AND((G9-CG$1)>=0,(G9-CG$1)<=6), "This Week",IF(AND((G9-CG$1)>=-7,(G9-CG$1)<=-1), "Last Week",""))
A10: 200013169413632 | B10: 1 | C10: 109014759518921 | D10: 1 | F10: SALE | G10: 45804 | H10: 1 | I10: WM-FR-IMP-84760166-18GB6VS | J10: 465595320771 | K10: Set of 4 18 inch Gloss Black ABS Wheel Skins Compatible with 2017 - 2019 GMC Acadia SLE; 2017 - 2019 GMC Acadia SLT Impostors for 84760166 22996315 Wheel Series | L10: 2038710 | O10: LA | R10: New Orleans | S10: 70125 | T10: Marketplace standard | U10: 71.92 | V10: 61.36 | W10: 4.62 | X10: 7 | Y10: 65.98 | Z10: 0 | AA10: 0 | AB10: 0 | AC10: 0 | AD10: 0 | AE10: 0 | AF10: 0 | AG10: 0 | AH10: 0 | AI10: 0 | AJ10: 0 | AK10: 0 | AL10: 0 | AM10: 0 | AN10: 0 | AO10: 5.94 | AP10: 0 | AQ10: 0 | AR10: 0 | AS10: 0 | AT10: 0 | AU10: 0 | AV10: 0 | AW10: 0 | AX10: 0 | AY10: 0 | AZ10: 0 | BA10: 0 | BB10: 5.94 | BC10: Y | BG10: -6.6 | BH10: Wheels & Wheel Components | BI10: Tires & Wheels | BJ10: Automotive Wheel Covers & Hub Caps | BK10: PRO-119076-17.0 | BN10: N | BO10: Seller Fulfilled | BP10: Delivery | BQ10: New Seller Saving | BR10: 1.98 | BW10: =if(OR(F10="SALE",F10="REFUNDED"),IFERROR(Vlookup(I10,'Listing SKU - Fill SKU Mapping'!A:C,3,false),"Map"),"") -> Keystone | BX10: =IF(OR(F10="SALE",F10="REFUNDED")=TRUE,iferror(Vlookup(I10,'Listing SKU - Fill SKU Mapping'!A:B,2,false),"Map"),"") -> IMP466BLK | BY10: =IF(OR(F10="SALE",F10="REFUNDED")=TRUE,iferror(Vlookup(I10,'Listing SKU - Fill SKU Mapping'!A:D,4,false),"Map"),"") -> 62.33 | BZ10: =If(BW10="Keystone",11.5,"") -> 11.5 | CA10: =IF(ISNUMBER(BY10)=TRUE,BY10+BZ10,"") -> 73.83 | CB10: =if(F10="SALE",V10-CA10,"") -> -12.47 | CC10: =if(F10="REFUNDED",iferror(Vlookup(I10,'Listing SKU - Fill SKU Mapping'!A:B,2,false),"Map"),"") | CD10: =if(F10="REFUNDED",iferror(Vlookup(I10,'Listing SKU - Fill SKU Mapping'!A:C,3,false),"Map"),"") | CE10: =TEXT(G10,"YYYY") -> 2025 | CF10: =TEXT(G10,"MMMM") -> May | CG10: =IF(AND((G10-CG$1)>=0,(G10-CG$1)<=6), "This Week",IF(AND((G10-CG$1)>=-7,(G10-CG$1)<=-1), "Last Week",""))
A11: 200013143554738 | B11: 1 | C11: 109014348663493 | D11: 1 | F11: SALE | G11: 45800 | H11: 1 | I11: WM-FR-IMP-3957-17GB5DS | J11: 460776238265 | K11: Set of 4 17 inch Gloss Black Wheel Skins Covers Compatible with 13-16 Ford Fusion Impostors for 3957 Wheel Series | L11: 2038710 | O11: GA | R11: Pooler | S11: 31322 | T11: Marketplace standard | U11: 104.84 | V11: 91.12 | W11: 6.86 | X11: 7 | Y11: 97.98 | Z11: 0 | AA11: 0 | AB11: 0 | AC11: 0 | AD11: 0 | AE11: 0 | AF11: 0 | AG11: 0 | AH11: 0 | AI11: 0 | AJ11: 0 | AK11: 0 | AL11: 0 | AM11: 0 | AN11: 0 | AO11: 6.86 | AP11: 0 | AQ11: 0 | AR11: 0 | AS11: 0 | AT11: 0 | AU11: 0 | AV11: 0 | AW11: 0 | AX11: 0 | AY11: 0 | AZ11: 0 | BA11: 0 | BB11: 6.86 | BC11: Y | BG11: -9.8 | BH11: Wheels & Wheel Components | BI11: Tires & Wheels | BJ11: Automotive Wheel Covers & Hub Caps | BK11: PRO-119076-17.0 | BN11: N | BO11: Seller Fulfilled | BP11: Delivery | BQ11: New Seller Saving | BR11: 2.94 | BW11: =if(OR(F11="SALE",F11="REFUNDED"),IFERROR(Vlookup(I11,'Listing SKU - Fill SKU Mapping'!A:C,3,false),"Map"),"") -> Keystone | BX11: =IF(OR(F11="SALE",F11="REFUNDED")=TRUE,iferror(Vlookup(I11,'Listing SKU - Fill SKU Mapping'!A:B,2,false),"Map"),"") -> IMP372BLKN | BY11: =IF(OR(F11="SALE",F11="REFUNDED")=TRUE,iferror(Vlookup(I11,'Listing SKU - Fill SKU Mapping'!A:D,4,false),"Map"),"") -> 45.36 | BZ11: =If(BW11="Keystone",11.5,"") -> 11.5 | CA11: =IF(ISNUMBER(BY11)=TRUE,BY11+BZ11,"") -> 56.86 | CB11: =if(F11="SALE",V11-CA11,"") -> 34.26 | CC11: =if(F11="REFUNDED",iferror(Vlookup(I11,'Listing SKU - Fill SKU Mapping'!A:B,2,false),"Map"),"") | CD11: =if(F11="REFUNDED",iferror(Vlookup(I11,'Listing SKU - Fill SKU Mapping'!A:C,3,false),"Map"),"") | CE11: =TEXT(G11,"YYYY") -> 2025 | CF11: =TEXT(G11,"MMMM") -> May | CG11: =IF(AND((G11-CG$1)>=0,(G11-CG$1)<=6), "This Week",IF(AND((G11-CG$1)>=-7,(G11-CG$1)<=-1), "Last Week",""))
A12: 200013138589026 | B12: 1 | C12: 109014973533768 | D12: 1 | F12: SALE | G12: 45806 | H12: 1 | I12: WM-KS-FRHC-530696-16SL | J12: 467129929368 | K12: Fuel Rider Set of 4 16 inch Silver Snap-On Hubcaps With 6 Spoke Compatible With 2005-2006 Nissan Altima Standard Steel Wheel Covers | L12: 2038710 | O12: MS | R12: Brandon | S12: 39047 | T12: Marketplace standard | U12: 69.53 | V12: 60.43 | W12: 4.55 | X12: 7 | Y12: 64.98 | Z12: 0 | AA12: 0 | AB12: 0 | AC12: 0 | AD12: 0 | AE12: 0 | AF12: 0 | AG12: 0 | AH12: 0 | AI12: 0 | AJ12: 0 | AK12: 0 | AL12: 0 | AM12: 0 | AN12: 0 | AO12: 4.55 | AP12: 0 | AQ12: 0 | AR12: 0 | AS12: 0 | AT12: 0 | AU12: 0 | AV12: 0 | AW12: 0 | AX12: 0 | AY12: 0 | AZ12: 0 | BA12: 0 | BB12: 4.55 | BC12: Y | BG12: -6.5 | BH12: Wheels & Wheel Components | BI12: Tires & Wheels | BJ12: Automotive Wheel Covers & Hub Caps | BK12: PRO-119076-17.0 | BN12: N | BO12: Seller Fulfilled | BP12: Delivery | BQ12: New Seller Saving | BR12: 1.95 | BW12: =if(OR(F12="SALE",F12="REFUNDED"),IFERROR(Vlookup(I12,'Listing SKU - Fill SKU Mapping'!A:C,3,false),"Map"),"") -> Keystone | BX12: =IF(OR(F12="SALE",F12="REFUNDED")=TRUE,iferror(Vlookup(I12,'Listing SKU - Fill SKU Mapping'!A:B,2,false),"Map"),"") -> B887216S | BY12: =IF(OR(F12="SALE",F12="REFUNDED")=TRUE,iferror(Vlookup(I12,'Listing SKU - Fill SKU Mapping'!A:D,4,false),"Map"),"") -> 24.85 | BZ12: =If(BW12="Keystone",11.5,"") -> 11.5 | CA12: =IF(ISNUMBER(BY12)=TRUE,BY12+BZ12,"") -> 36.35 | CB12: =if(F12="SALE",V12-CA12,"") -> 24.08 | CC12: =if(F12="REFUNDED",iferror(Vlookup(I12,'Listing SKU - Fill SKU Mapping'!A:B,2,false),"Map"),"") | CD12: =if(F12="REFUNDED",iferror(Vlookup(I12,'Listing SKU - Fill SKU Mapping'!A:C,3,false),"Map"),"") | CE12: =TEXT(G12,"YYYY") -> 2025 | CF12: =TEXT(G12,"MMMM") -> May | CG12: =IF(AND((G12-CG$1)>=0,(G12-CG$1)<=6), "This Week",IF(AND((G12-CG$1)>=-7,(G12-CG$1)<=-1), "Last Week",""))
A13: 200013082357439 | B13: 1 | C13: 109014034395401 | D13: 1 | F13: SALE | G13: 45796 | H13: 1 | I13: WM-FR-IMP-94775676-16GB6S | J13: 460776233390 | K13: Set of 4 16 Gloss Black ABS Wheel Skins Compatible with 2015-2020 Chevrolet Colorado Base 2015-2022 Colorado WT LT Z71 2017-2022 Colorado ZR2 Impostors for 94775676 Wheel Series | L13: 2038710 | O13: OK | R13: Okmulgee | S13: 74447 | T13: Marketplace standard | U13: 121.07 | V13: 102.28 | W13: 7.7 | X13: 7 | Y13: 109.98 | Z13: 0 | AA13: 0 | AB13: 0 | AC13: 0 | AD13: 0 | AE13: 0 | AF13: 0 | AG13: 0 | AH13: 0 | AI13: 0 | AJ13: 0 | AK13: 0 | AL13: 0 | AM13: 0 | AN13: 0 | AO13: 11.09 | AP13: 0 | AQ13: 0 | AR13: 0 | AS13: 0 | AT13: 0 | AU13: 0 | AV13: 0 | AW13: 0 | AX13: 0 | AY13: 0 | AZ13: 0 | BA13: 0 | BB13: 11.09 | BC13: Y | BG13: -11 | BH13: Wheels & Wheel Components | BI13: Tires & Wheels | BJ13: Automotive Wheel Covers & Hub Caps | BK13: PRO-119076-16.0 | BN13: Y | BO13: Seller Fulfilled | BP13: Delivery | BQ13: New Seller Saving | BR13: 3.3 | BW13: =if(OR(F13="SALE",F13="REFUNDED"),IFERROR(Vlookup(I13,'Listing SKU - Fill SKU Mapping'!A:C,3,false),"Map"),"") -> Keystone | BX13: =IF(OR(F13="SALE",F13="REFUNDED")=TRUE,iferror(Vlookup(I13,'Listing SKU - Fill SKU Mapping'!A:B,2,false),"Map"),"") -> IMP444BLK | BY13: =IF(OR(F13="SALE",F13="REFUNDED")=TRUE,iferror(Vlookup(I13,'Listing SKU - Fill SKU Mapping'!A:D,4,false),"Map"),"") -> 54.05 | BZ13: =If(BW13="Keystone",11.5,"") -> 11.5 | CA13: =IF(ISNUMBER(BY13)=TRUE,BY13+BZ13,"") -> 65.55 | CB13: =if(F13="SALE",V13-CA13,"") -> 36.73 | CC13: =if(F13="REFUNDED",iferror(Vlookup(I13,'Listing SKU - Fill SKU Mapping'!A:B,2,false),"Map"),"") | CD13: =if(F13="REFUNDED",iferror(Vlookup(I13,'Listing SKU - Fill SKU Mapping'!A:C,3,false),"Map"),"") | CE13: =TEXT(G13,"YYYY") -> 2025 | CF13: =TEXT(G13,"MMMM") -> May | CG13: =IF(AND((G13-CG$1)>=0,(G13-CG$1)<=6), "This Week",IF(AND((G13-CG$1)>=-7,(G13-CG$1)<=-1), "Last Week",""))
A14: 200013082357439 | B14: 1 | C14: 109014034395401 | D14: 1 | F14: REFUNDED | G14: 45799 | H14: 1 | I14: WM-FR-IMP-94775676-16GB6S | J14: 460776233390 | K14: Set of 4 16 Gloss Black ABS Wheel Skins Compatible with 2015-2020 Chevrolet Colorado Base 2015-2022 Colorado WT LT Z71 2017-2022 Colorado ZR2 Impostors for 94775676 Wheel Series | L14: 2038710 | R14: Okmulgee | S14: 74447 | U14: -121.07 | V14: -102.28 | W14: -7.7 | X14: 0 | Y14: 0 | Z14: -109.98 | AA14: 0 | AB14: 0 | AC14: 0 | AD14: 0 | AE14: 0 | AF14: 0 | AG14: 0 | AH14: 0 | AI14: 0 | AJ14: 0 | AK14: 0 | AL14: 0 | AM14: 0 | AN14: 0 | AO14: 0 | AP14: 0 | AQ14: 0 | AR14: 0 | AS14: 0 | AT14: -11.09 | AU14: 0 | AV14: 0 | AW14: 0 | AX14: 0 | AY14: 0 | AZ14: 0 | BA14: 0 | BB14: -11.09 | BC14: Y | BD14: Return Refund | BE14: 5010 | BH14: Wheels & Wheel Components | BI14: Tires & Wheels | BL14: 1018 | BM14: Not as described/pictured | BN14: Y | BO14: Seller Fulfilled | BW14: =if(OR(F14="SALE",F14="REFUNDED"),IFERROR(Vlookup(I14,'Listing SKU - Fill SKU Mapping'!A:C,3,false),"Map"),"") -> Keystone | BX14: =IF(OR(F14="SALE",F14="REFUNDED")=TRUE,iferror(Vlookup(I14,'Listing SKU - Fill SKU Mapping'!A:B,2,false),"Map"),"") -> IMP444BLK | BY14: =IF(OR(F14="SALE",F14="REFUNDED")=TRUE,iferror(Vlookup(I14,'Listing SKU - Fill SKU Mapping'!A:D,4,false),"Map"),"") -> 54.05 | BZ14: =If(BW14="Keystone",11.5,"") -> 11.5 | CA14: =IF(ISNUMBER(BY14)=TRUE,BY14+BZ14,"") -> 65.55 | CB14: =if(F14="SALE",V14-CA14,"") | CC14: =if(F14="REFUNDED",iferror(Vlookup(I14,'Listing SKU - Fill SKU Mapping'!A:B,2,false),"Map"),"") -> IMP444BLK | CD14: =if(F14="REFUNDED",iferror(Vlookup(I14,'Listing SKU - Fill SKU Mapping'!A:C,3,false),"Map"),"") -> Keystone | CE14: =TEXT(G14,"YYYY") -> 2025 | CF14: =TEXT(G14,"MMMM") -> May | CG14: =IF(AND((G14-CG$1)>=0,(G14-CG$1)<=6), "This Week",IF(AND((G14-CG$1)>=-7,(G14-CG$1)<=-1), "Last Week",""))
A15: 200013060278696 | B15: 7 | C15: 109011942953061 | D15: 7 | F15: ADJMNT | G15: 45802 | H15: 1 | I15: WM-FR-IMP-3943-17GB5SP | J15: 460776234854 | K15: Set of 4 17 inch Gloss Black Wheel Skins Covers Compatible with 17-19 Ford Escape SE 13-16 Ford Escape Impostors for 3943 Wheel Series | L15: 2038710 | O15: CA | R15: Whittier | S15: 90605 | T15: Marketplace standard | U15: 0 | V15: -8.89 | W15: 0 | X15: 0 | Y15: 0 | Z15: 0 | AA15: 0 | AB15: 0 | AC15: 0 | AD15: 0 | AE15: 0 | AF15: 0 | AG15: 0 | AH15: 0 | AI15: 0 | AJ15: 0 | AK15: 0 | AL15: 0 | AM15: 0 | AN15: 0 | AO15: 0 | AP15: 0 | AQ15: 0 | AR15: 0 | AS15: 0 | AT15: 0 | AU15: 0 | AV15: 0 | AW15: 0 | AX15: 0 | AY15: 0 | AZ15: 0 | BA15: 0 | BB15: 0 | BC15: Y | BD15: Walmart Return Shipping Charge | BE15: 5013 | BH15: Wheels & Wheel Components | BI15: Tires & Wheels | BN15: N | BO15: Seller Fulfilled | BW15: =if(OR(F15="SALE",F15="REFUNDED"),IFERROR(Vlookup(I15,'Listing SKU - Fill SKU Mapping'!A:C,3,false),"Map"),"") | BX15: =IF(OR(F15="SALE",F15="REFUNDED")=TRUE,iferror(Vlookup(I15,'Listing SKU - Fill SKU Mapping'!A:B,2,false),"Map"),"") | BY15: =IF(OR(F15="SALE",F15="REFUNDED")=TRUE,iferror(Vlookup(I15,'Listing SKU - Fill SKU Mapping'!A:D,4,false),"Map"),"") | BZ15: =If(BW15="Keystone",11.5,"") | CA15: =IF(ISNUMBER(BY15)=TRUE,BY15+BZ15,"") | CB15: =if(F15="SALE",V15-CA15,"") | CC15: =if(F15="REFUNDED",iferror(Vlookup(I15,'Listing SKU - Fill SKU Mapping'!A:B,2,false),"Map"),"") | CD15: =if(F15="REFUNDED",iferror(Vlookup(I15,'Listing SKU - Fill SKU Mapping'!A:C,3,false),"Map"),"") | CE15: =TEXT(G15,"YYYY") -> 2025 | CF15: =TEXT(G15,"MMMM") -> May | CG15: =IF(AND((G15-CG$1)>=0,(G15-CG$1)<=6), "This Week",IF(AND((G15-CG$1)>=-7,(G15-CG$1)<=-1), "Last Week",""))
A16: 200013049604965 | B16: 1 | C16: 109011426675392 | D16: 1 | F16: ADJMNT | G16: 45795 | H16: 1 | I16: WM-FR-IMP-5833-17GB5DS | J16: 460776235042 | K16: 17 inch Gloss Black ABS Wheel Skins Set Compatible with 2018-2021 GMC Terrain SL 2018-2023 GMC Terrain SLE & Impostors for 5833 Wheel Series | L16: 2038710 | O16: VA | R16: South Prince George | S16: 23805 | T16: Marketplace standard | U16: 0 | V16: -8.89 | W16: 0 | X16: 0 | Y16: 0 | Z16: 0 | AA16: 0 | AB16: 0 | AC16: 0 | AD16: 0 | AE16: 0 | AF16: 0 | AG16: 0 | AH16: 0 | AI16: 0 | AJ16: 0 | AK16: 0 | AL16: 0 | AM16: 0 | AN16: 0 | AO16: 0 | AP16: 0 | AQ16: 0 | AR16: 0 | AS16: 0 | AT16: 0 | AU16: 0 | AV16: 0 | AW16: 0 | AX16: 0 | AY16: 0 | AZ16: 0 | BA16: 0 | BB16: 0 | BC16: Y | BD16: Walmart Return Shipping Charge | BE16: 5013 | BH16: Wheels & Wheel Components | BI16: Tires & Wheels | BN16: N | BO16: Seller Fulfilled | BW16: =if(OR(F16="SALE",F16="REFUNDED"),IFERROR(Vlookup(I16,'Listing SKU - Fill SKU Mapping'!A:C,3,false),"Map"),"") | BX16: =IF(OR(F16="SALE",F16="REFUNDED")=TRUE,iferror(Vlookup(I16,'Listing SKU - Fill SKU Mapping'!A:B,2,false),"Map"),"") | BY16: =IF(OR(F16="SALE",F16="REFUNDED")=TRUE,iferror(Vlookup(I16,'Listing SKU - Fill SKU Mapping'!A:D,4,false),"Map"),"") | BZ16: =If(BW16="Keystone",11.5,"") | CA16: =IF(ISNUMBER(BY16)=TRUE,BY16+BZ16,"") | CB16: =if(F16="SALE",V16-CA16,"") | CC16: =if(F16="REFUNDED",iferror(Vlookup(I16,'Listing SKU - Fill SKU Mapping'!A:B,2,false),"Map"),"") | CD16: =if(F16="REFUNDED",iferror(Vlookup(I16,'Listing SKU - Fill SKU Mapping'!A:C,3,false),"Map"),"") | CE16: =TEXT(G16,"YYYY") -> 2025 | CF16: =TEXT(G16,"MMMM") -> May | CG16: =IF(AND((G16-CG$1)>=0,(G16-CG$1)<=6), "This Week",IF(AND((G16-CG$1)>=-7,(G16-CG$1)<=-1), "Last Week",""))
A17: 200013038493104 | B17: 1 | C17: 109011116508241 | D17: 1 | F17: ADJMNT | G17: 45802 | H17: 1 | I17: WM-FR-IMP-2363-20CH5SP | J17: 464567112352 | K17: Set of 4 20 inch Chrome Wheel Skins Covers compatible with 09-10 Dodge Ram 1500 11-24 Ram 1500 Classic Sport Laramie Rebel Tradesman Big Horn SLT Express Lone Star Limited Impostors | L17: 2038710 | O17: IN | R17: Beech Grove | S17: 46107 | T17: Marketplace standard | U17: 0 | V17: -10.81 | W17: 0 | X17: 0 | Y17: 0 | Z17: 0 | AA17: 0 | AB17: 0 | AC17: 0 | AD17: 0 | AE17: 0 | AF17: 0 | AG17: 0 | AH17: 0 | AI17: 0 | AJ17: 0 | AK17: 0 | AL17: 0 | AM17: 0 | AN17: 0 | AO17: 0 | AP17: 0 | AQ17: 0 | AR17: 0 | AS17: 0 | AT17: 0 | AU17: 0 | AV17: 0 | AW17: 0 | AX17: 0 | AY17: 0 | AZ17: 0 | BA17: 0 | BB17: 0 | BC17: Y | BD17: Walmart Return Shipping Charge | BE17: 5013 | BH17: Wheels & Wheel Components | BI17: Tires & Wheels | BN17: N | BO17: Seller Fulfilled | BW17: =if(OR(F17="SALE",F17="REFUNDED"),IFERROR(Vlookup(I17,'Listing SKU - Fill SKU Mapping'!A:C,3,false),"Map"),"") | BX17: =IF(OR(F17="SALE",F17="REFUNDED")=TRUE,iferror(Vlookup(I17,'Listing SKU - Fill SKU Mapping'!A:B,2,false),"Map"),"") | BY17: =IF(OR(F17="SALE",F17="REFUNDED")=TRUE,iferror(Vlookup(I17,'Listing SKU - Fill SKU Mapping'!A:D,4,false),"Map"),"") | BZ17: =If(BW17="Keystone",11.5,"") | CA17: =IF(ISNUMBER(BY17)=TRUE,BY17+BZ17,"") | CB17: =if(F17="SALE",V17-CA17,"") | CC17: =if(F17="REFUNDED",iferror(Vlookup(I17,'Listing SKU - Fill SKU Mapping'!A:B,2,false),"Map"),"") | CD17: =if(F17="REFUNDED",iferror(Vlookup(I17,'Listing SKU - Fill SKU Mapping'!A:C,3,false),"Map"),"") | CE17: =TEXT(G17,"YYYY") -> 2025 | CF17: =TEXT(G17,"MMMM") -> May | CG17: =IF(AND((G17-CG$1)>=0,(G17-CG$1)<=6), "This Week",IF(AND((G17-CG$1)>=-7,(G17-CG$1)<=-1), "Last Week",""))
A18: 200012993559082 | B18: 1 | C18: 109011114761058 | D18: 1 | F18: ADJMNT | G18: 45795 | H18: 1 | I18: WM-FR-IMP-10043-18CH5DS | J18: 464567131070 | K18: Set of 4 18 inch Chrome Wheel Skins Covers Compatible with 15-18 Ford Edge Impostors for 10043 Wheel Series | L18: 2038710 | O18: TX | R18: Houston | S18: 77040 | T18: Marketplace standard | U18: 0 | V18: -10.81 | W18: 0 | X18: 0 | Y18: 0 | Z18: 0 | AA18: 0 | AB18: 0 | AC18: 0 | AD18: 0 | AE18: 0 | AF18: 0 | AG18: 0 | AH18: 0 | AI18: 0 | AJ18: 0 | AK18: 0 | AL18: 0 | AM18: 0 | AN18: 0 | AO18: 0 | AP18: 0 | AQ18: 0 | AR18: 0 | AS18: 0 | AT18: 0 | AU18: 0 | AV18: 0 | AW18: 0 | AX18: 0 | AY18: 0 | AZ18: 0 | BA18: 0 | BB18: 0 | BC18: Y | BD18: Walmart Return Shipping Charge | BE18: 5013 | BH18: Wheels & Wheel Components | BI18: Tires & Wheels | BN18: N | BO18: Seller Fulfilled | BW18: =if(OR(F18="SALE",F18="REFUNDED"),IFERROR(Vlookup(I18,'Listing SKU - Fill SKU Mapping'!A:C,3,false),"Map"),"") | BX18: =IF(OR(F18="SALE",F18="REFUNDED")=TRUE,iferror(Vlookup(I18,'Listing SKU - Fill SKU Mapping'!A:B,2,false),"Map"),"") | BY18: =IF(OR(F18="SALE",F18="REFUNDED")=TRUE,iferror(Vlookup(I18,'Listing SKU - Fill SKU Mapping'!A:D,4,false),"Map"),"") | BZ18: =If(BW18="Keystone",11.5,"") | CA18: =IF(ISNUMBER(BY18)=TRUE,BY18+BZ18,"") | CB18: =if(F18="SALE",V18-CA18,"") | CC18: =if(F18="REFUNDED",iferror(Vlookup(I18,'Listing SKU - Fill SKU Mapping'!A:B,2,false),"Map"),"") | CD18: =if(F18="REFUNDED",iferror(Vlookup(I18,'Listing SKU - Fill SKU Mapping'!A:C,3,false),"Map"),"") | CE18: =TEXT(G18,"YYYY") -> 2025 | CF18: =TEXT(G18,"MMMM") -> May | CG18: =IF(AND((G18-CG$1)>=0,(G18-CG$1)<=6), "This Week",IF(AND((G18-CG$1)>=-7,(G18-CG$1)<=-1), "Last Week",""))
A19: 200012934607014 | B19: 1 | C19: 109010168324919 | D19: 1 | F19: ADJMNT | G19: 45795 | H19: 1 | I19: WM-FR-IMP-DS7Z1007Q-17CC10S | J19: 460776230283 | K19: Set of 4 17 Chrome & Charcoal ABS Wheel Skins Compatible with 2017-2020 Ford Fusion SE 2015-2016 Ford Fusion Impostors for DS7Z1007Q Wheel Series | L19: 2038710 | O19: VA | R19: Roanoke | S19: 24013 | T19: Marketplace standard | U19: 0 | V19: -8.89 | W19: 0 | X19: 0 | Y19: 0 | Z19: 0 | AA19: 0 | AB19: 0 | AC19: 0 | AD19: 0 | AE19: 0 | AF19: 0 | AG19: 0 | AH19: 0 | AI19: 0 | AJ19: 0 | AK19: 0 | AL19: 0 | AM19: 0 | AN19: 0 | AO19: 0 | AP19: 0 | AQ19: 0 | AR19: 0 | AS19: 0 | AT19: 0 | AU19: 0 | AV19: 0 | AW19: 0 | AX19: 0 | AY19: 0 | AZ19: 0 | BA19: 0 | BB19: 0 | BC19: Y | BD19: Walmart Return Shipping Charge | BE19: 5013 | BH19: Wheels & Wheel Components | BI19: Tires & Wheels | BN19: N | BO19: Seller Fulfilled | BW19: =if(OR(F19="SALE",F19="REFUNDED"),IFERROR(Vlookup(I19,'Listing SKU - Fill SKU Mapping'!A:C,3,false),"Map"),"") | BX19: =IF(OR(F19="SALE",F19="REFUNDED")=TRUE,iferror(Vlookup(I19,'Listing SKU - Fill SKU Mapping'!A:B,2,false),"Map"),"") | BY19: =IF(OR(F19="SALE",F19="REFUNDED")=TRUE,iferror(Vlookup(I19,'Listing SKU - Fill SKU Mapping'!A:D,4,false),"Map"),"") | BZ19: =If(BW19="Keystone",11.5,"") | CA19: =IF(ISNUMBER(BY19)=TRUE,BY19+BZ19,"") | CB19: =if(F19="SALE",V19-CA19,"") | CC19: =if(F19="REFUNDED",iferror(Vlookup(I19,'Listing SKU - Fill SKU Mapping'!A:B,2,false),"Map"),"") | CD19: =if(F19="REFUNDED",iferror(Vlookup(I19,'Listing SKU - Fill SKU Mapping'!A:C,3,false),"Map"),"") | CE19: =TEXT(G19,"YYYY") -> 2025 | CF19: =TEXT(G19,"MMMM") -> May | CG19: =IF(AND((G19-CG$1)>=0,(G19-CG$1)<=6), "This Week",IF(AND((G19-CG$1)>=-7,(G19-CG$1)<=-1), "Last Week",""))
A20: 200013328886328 | B20: 1 | C20: 109012673709835 | D20: 1 | F20: SALE | G20: 45783 | H20: 1 | I20: WM-FR-IMP-5473-16GB5SP | J20: 460776230986 | K20: Set of 4 16 inch Gloss Black ABS Wheel Skins Compatible with 11-15 Chevrolet Cruze 16 Cruze Limited Impostors for 5473 5674 Wheel Series | L20: 2038710 | O20: TX | R20: Mcallen | S20: 78501 | T20: Marketplace standard | U20: 98.49 | V20: 84.61 | W20: 6.37 | X20: 7 | Y20: 90.98 | Z20: 0 | AA20: 0 | AB20: 0 | AC20: 0 | AD20: 0 | AE20: 0 | AF20: 0 | AG20: 0 | AH20: 0 | AI20: 0 | AJ20: 0 | AK20: 0 | AL20: 0 | AM20: 0 | AN20: 0 | AO20: 7.51 | AP20: 0 | AQ20: 0 | AR20: 0 | AS20: 0 | AT20: 0 | AU20: 0 | AV20: 0 | AW20: 0 | AX20: 0 | AY20: 0 | AZ20: 0 | BA20: 0 | BB20: 7.51 | BC20: Y | BG20: -9.1 | BH20: Wheels & Wheel Components | BI20: Tires & Wheels | BJ20: Automotive Wheel Covers & Hub Caps | BK20: PRO-119076-14.0 | BN20: N | BO20: Seller Fulfilled | BP20: Delivery | BQ20: New Seller Saving | BR20: 2.73 | BW20: =if(OR(F20="SALE",F20="REFUNDED"),IFERROR(Vlookup(I20,'Listing SKU - Fill SKU Mapping'!A:C,3,false),"Map"),"") -> Keystone | BX20: =IF(OR(F20="SALE",F20="REFUNDED")=TRUE,iferror(Vlookup(I20,'Listing SKU - Fill SKU Mapping'!A:B,2,false),"Map"),"") -> IMP375BLK | BY20: =IF(OR(F20="SALE",F20="REFUNDED")=TRUE,iferror(Vlookup(I20,'Listing SKU - Fill SKU Mapping'!A:D,4,false),"Map"),"") -> 41.03 | BZ20: =If(BW20="Keystone",11.5,"") -> 11.5 | CA20: =IF(ISNUMBER(BY20)=TRUE,BY20+BZ20,"") -> 52.53 | CB20: =if(F20="SALE",V20-CA20,"") -> 32.08 | CC20: =if(F20="REFUNDED",iferror(Vlookup(I20,'Listing SKU - Fill SKU Mapping'!A:B,2,false),"Map"),"") | CD20: =if(F20="REFUNDED",iferror(Vlookup(I20,'Listing SKU - Fill SKU Mapping'!A:C,3,false),"Map"),"") | CE20: =TEXT(G20,"YYYY") -> 2025 | CF20: =TEXT(G20,"MMMM") -> May | CG20: =IF(AND((G20-CG$1)>=0,(G20-CG$1)<=6), "This Week",IF(AND((G20-CG$1)>=-7,(G20-CG$1)<=-1), "Last Week",""))
A21: 200013309638819 | B21: 1 | C21: 109013192839887 | D21: 1 | F21: SALE | G21: 45789 | H21: 1 | I21: WM-FR-IMP-5646-18CH5DS | J21: 460776229027 | K21: 18 inch Chrome ABS Wheel Skins Set Compatible with 2014-2018 Chevrolet Silverado 1500 LT LTZ 2015-2020 Tahoe Suburban LS LT & Impostors for 5646 Wheel Series | L21: 2038710 | O21: IN | R21: Evansville | S21: 47714 | T21: Marketplace standard | U21: 139.08 | V21: 120.88 | W21: 9.1 | X21: 7 | Y21: 129.98 | Z21: 0 | AA21: 0 | AB21: 0 | AC21: 0 | AD21: 0 | AE21: 0 | AF21: 0 | AG21: 0 | AH21: 0 | AI21: 0 | AJ21: 0 | AK21: 0 | AL21: 0 | AM21: 0 | AN21: 0 | AO21: 9.1 | AP21: 0 | AQ21: 0 | AR21: 0 | AS21: 0 | AT21: 0 | AU21: 0 | AV21: 0 | AW21: 0 | AX21: 0 | AY21: 0 | AZ21: 0 | BA21: 0 | BB21: 9.1 | BC21: Y | BG21: -13 | BH21: Wheels & Wheel Components | BI21: Tires & Wheels | BJ21: Automotive Wheel Covers & Hub Caps | BK21: PRO-119076-15.0 | BN21: N | BO21: Seller Fulfilled | BP21: Delivery | BQ21: New Seller Saving | BR21: 3.9 | BW21: =if(OR(F21="SALE",F21="REFUNDED"),IFERROR(Vlookup(I21,'Listing SKU - Fill SKU Mapping'!A:C,3,false),"Map"),"") -> Keystone | BX21: =IF(OR(F21="SALE",F21="REFUNDED")=TRUE,iferror(Vlookup(I21,'Listing SKU - Fill SKU Mapping'!A:B,2,false),"Map"),"") -> IMP377XN | BY21: =IF(OR(F21="SALE",F21="REFUNDED")=TRUE,iferror(Vlookup(I21,'Listing SKU - Fill SKU Mapping'!A:D,4,false),"Map"),"") -> 67.85 | BZ21: =If(BW21="Keystone",11.5,"") -> 11.5 | CA21: =IF(ISNUMBER(BY21)=TRUE,BY21+BZ21,"") -> 79.35 | CB21: =if(F21="SALE",V21-CA21,"") -> 41.53 | CC21: =if(F21="REFUNDED",iferror(Vlookup(I21,'Listing SKU - Fill SKU Mapping'!A:B,2,false),"Map"),"") | CD21: =if(F21="REFUNDED",iferror(Vlookup(I21,'Listing SKU - Fill SKU Mapping'!A:C,3,false),"Map"),"") | CE21: =TEXT(G21,"YYYY") -> 2025 | CF21: =TEXT(G21,"MMMM") -> May | CG21: =IF(AND((G21-CG$1)>=0,(G21-CG$1)<=6), "This Week",IF(AND((G21-CG$1)>=-7,(G21-CG$1)<=-1), "Last Week",""))
A22: 200013296634411 | B22: 1 | C22: 109013191993463 | D22: 1 | F22: SALE | G22: 45789 | H22: 1 | I22: WM-FR-IMP-4261148040-16CH5DMS | J22: 464567125864 | K22: Set of 4 16 inch Chrome Wheel Skins Covers compatible with 01-05 Toyota RAV4 01-07 Toyota Highlander Impostors for 4261148040 Wheel Series | L22: 2038710 | O22: FL | R22: Palm Bay | S22: 32908 | T22: Marketplace standard | U22: 98.42 | V22: 85.54 | W22: 6.44 | X22: 7 | Y22: 91.98 | Z22: 0 | AA22: 0 | AB22: 0 | AC22: 0 | AD22: 0 | AE22: 0 | AF22: 0 | AG22: 0 | AH22: 0 | AI22: 0 | AJ22: 0 | AK22: 0 | AL22: 0 | AM22: 0 | AN22: 0 | AO22: 6.44 | AP22: 0 | AQ22: 0 | AR22: 0 | AS22: 0 | AT22: 0 | AU22: 0 | AV22: 0 | AW22: 0 | AX22: 0 | AY22: 0 | AZ22: 0 | BA22: 0 | BB22: 6.44 | BC22: Y | BG22: -9.2 | BH22: Wheels & Wheel Components | BI22: Tires & Wheels | BJ22: Automotive Wheel Covers & Hub Caps | BK22: PRO-119076-15.0 | BN22: N | BO22: Seller Fulfilled | BP22: Delivery | BQ22: New Seller Saving | BR22: 2.76 | BW22: =if(OR(F22="SALE",F22="REFUNDED"),IFERROR(Vlookup(I22,'Listing SKU - Fill SKU Mapping'!A:C,3,false),"Map"),"") -> Keystone | BX22: =IF(OR(F22="SALE",F22="REFUNDED")=TRUE,iferror(Vlookup(I22,'Listing SKU - Fill SKU Mapping'!A:B,2,false),"Map"),"") -> IMP42X | BY22: =IF(OR(F22="SALE",F22="REFUNDED")=TRUE,iferror(Vlookup(I22,'Listing SKU - Fill SKU Mapping'!A:D,4,false),"Map"),"") -> 51.28 | BZ22: =If(BW22="Keystone",11.5,"") -> 11.5 | CA22: =IF(ISNUMBER(BY22)=TRUE,BY22+BZ22,"") -> 62.78 | CB22: =if(F22="SALE",V22-CA22,"") -> 22.76 | CC22: =if(F22="REFUNDED",iferror(Vlookup(I22,'Listing SKU - Fill SKU Mapping'!A:B,2,false),"Map"),"") | CD22: =if(F22="REFUNDED",iferror(Vlookup(I22,'Listing SKU - Fill SKU Mapping'!A:C,3,false),"Map"),"") | CE22: =TEXT(G22,"YYYY") -> 2025 | CF22: =TEXT(G22,"MMMM") -> May | CG22: =IF(AND((G22-CG$1)>=0,(G22-CG$1)<=6), "This Week",IF(AND((G22-CG$1)>=-7,(G22-CG$1)<=-1), "Last Week",""))
A23: 200013250701552 | B23: 1 | C23: 109013412941626 | D23: 1 | F23: SALE | G23: 45790 | H23: 1 | I23: WM-FR-IMP-63927-17CH5SP | J23: 460776231020 | K23: Set of 4 17 inch Chrome Wheel Skins Covers compatible with 07-11 Honda CR-V LX Impostors for 63927 Wheel Series | L23: 2038710 | O23: WI | R23: New Berlin | S23: 53151 | T23: Marketplace standard | U23: 123.88 | V23: 109.72 | W23: 8.26 | X23: 7 | Y23: 117.98 | Z23: 0 | AA23: 0 | AB23: 0 | AC23: 0 | AD23: 0 | AE23: 0 | AF23: 0 | AG23: 0 | AH23: 0 | AI23: 0 | AJ23: 0 | AK23: 0 | AL23: 0 | AM23: 0 | AN23: 0 | AO23: 5.9 | AP23: 0 | AQ23: 0 | AR23: 0 | AS23: 0 | AT23: 0 | AU23: 0 | AV23: 0 | AW23: 0 | AX23: 0 | AY23: 0 | AZ23: 0 | BA23: 0 | BB23: 5.9 | BC23: Y | BG23: -11.8 | BH23: Wheels & Wheel Components | BI23: Tires & Wheels | BJ23: Automotive Wheel Covers & Hub Caps | BK23: PRO-119076-15.0 | BN23: N | BO23: Seller Fulfilled | BP23: Delivery | BQ23: New Seller Saving | BR23: 3.54 | BW23: =if(OR(F23="SALE",F23="REFUNDED"),IFERROR(Vlookup(I23,'Listing SKU - Fill SKU Mapping'!A:C,3,false),"Map"),"") -> Keystone | BX23: =IF(OR(F23="SALE",F23="REFUNDED")=TRUE,iferror(Vlookup(I23,'Listing SKU - Fill SKU Mapping'!A:B,2,false),"Map"),"") -> IMP75X | BY23: =IF(OR(F23="SALE",F23="REFUNDED")=TRUE,iferror(Vlookup(I23,'Listing SKU - Fill SKU Mapping'!A:D,4,false),"Map"),"") -> 59.57 | BZ23: =If(BW23="Keystone",11.5,"") -> 11.5 | CA23: =IF(ISNUMBER(BY23)=TRUE,BY23+BZ23,"") -> 71.07 | CB23: =if(F23="SALE",V23-CA23,"") -> 38.65 | CC23: =if(F23="REFUNDED",iferror(Vlookup(I23,'Listing SKU - Fill SKU Mapping'!A:B,2,false),"Map"),"") | CD23: =if(F23="REFUNDED",iferror(Vlookup(I23,'Listing SKU - Fill SKU Mapping'!A:C,3,false),"Map"),"") | CE23: =TEXT(G23,"YYYY") -> 2025 | CF23: =TEXT(G23,"MMMM") -> May | CG23: =IF(AND((G23-CG$1)>=0,(G23-CG$1)<=6), "This Week",IF(AND((G23-CG$1)>=-7,(G23-CG$1)<=-1), "Last Week",""))
A24: 200013222975528 | B24: 1 | C24: 109013397530691 | D24: 1 | F24: SALE | G24: 45789 | H24: 1 | I24: WM-FR-IMP-LJ6Z1007A-17GB10S | J24: 460776231785 | K24: 17 inch Gloss Black ABS Wheel Skins Set Compatible with 2020-2022 Ford Escape & Impostors for LJ6Z1007A Wheel Series | L24: 2038710 | O24: MD | R24: Frederick | S24: 21703 | T24: Marketplace standard | U24: 108.1 | V24: 94.84 | W24: 7.14 | X24: 7 | Y24: 101.98 | Z24: 0 | AA24: 0 | AB24: 0 | AC24: 0 | AD24: 0 | AE24: 0 | AF24: 0 | AG24: 0 | AH24: 0 | AI24: 0 | AJ24: 0 | AK24: 0 | AL24: 0 | AM24: 0 | AN24: 0 | AO24: 6.12 | AP24: 0 | AQ24: 0 | AR24: 0 | AS24: 0 | AT24: 0 | AU24: 0 | AV24: 0 | AW24: 0 | AX24: 0 | AY24: 0 | AZ24: 0 | BA24: 0 | BB24: 6.12 | BC24: Y | BG24: -10.2 | BH24: Wheels & Wheel Components | BI24: Tires & Wheels | BJ24: Automotive Wheel Covers & Hub Caps | BK24: PRO-119076-15.0 | BN24: N | BO24: Seller Fulfilled | BP24: Delivery | BQ24: New Seller Saving | BR24: 3.06 | BW24: =if(OR(F24="SALE",F24="REFUNDED"),IFERROR(Vlookup(I24,'Listing SKU - Fill SKU Mapping'!A:C,3,false),"Map"),"") -> Keystone | BX24: =IF(OR(F24="SALE",F24="REFUNDED")=TRUE,iferror(Vlookup(I24,'Listing SKU - Fill SKU Mapping'!A:B,2,false),"Map"),"") -> IMP462BLK | BY24: =IF(OR(F24="SALE",F24="REFUNDED")=TRUE,iferror(Vlookup(I24,'Listing SKU - Fill SKU Mapping'!A:D,4,false),"Map"),"") -> 48.52 | BZ24: =If(BW24="Keystone",11.5,"") -> 11.5 | CA24: =IF(ISNUMBER(BY24)=TRUE,BY24+BZ24,"") -> 60.02 | CB24: =if(F24="SALE",V24-CA24,"") -> 34.82 | CC24: =if(F24="REFUNDED",iferror(Vlookup(I24,'Listing SKU - Fill SKU Mapping'!A:B,2,false),"Map"),"") | CD24: =if(F24="REFUNDED",iferror(Vlookup(I24,'Listing SKU - Fill SKU Mapping'!A:C,3,false),"Map"),"") | CE24: =TEXT(G24,"YYYY") -> 2025 | CF24: =TEXT(G24,"MMMM") -> May | CG24: =IF(AND((G24-CG$1)>=0,(G24-CG$1)<=6), "This Week",IF(AND((G24-CG$1)>=-7,(G24-CG$1)<=-1), "Last Week",""))
A25: 200013139259493 | B25: 1 | C25: 109012880994491 | D25: 1 | F25: SALE | G25: 45785 | H25: 1 | I25: WM-FR-IMP-3943-17GB5SP | J25: 460776234854 | K25: Set of 4 17 inch Gloss Black Wheel Skins Covers Compatible with 17-19 Ford Escape SE 13-16 Ford Escape Impostors for 3943 Wheel Series | L25: 2038710 | O25: FL | R25: Ponte Vedra | S25: 32082 | T25: Marketplace standard | U25: 101.15 | V25: 88.33 | W25: 6.65 | X25: 7 | Y25: 94.98 | Z25: 0 | AA25: 0 | AB25: 0 | AC25: 0 | AD25: 0 | AE25: 0 | AF25: 0 | AG25: 0 | AH25: 0 | AI25: 0 | AJ25: 0 | AK25: 0 | AL25: 0 | AM25: 0 | AN25: 0 | AO25: 6.17 | AP25: 0 | AQ25: 0 | AR25: 0 | AS25: 0 | AT25: 0 | AU25: 0 | AV25: 0 | AW25: 0 | AX25: 0 | AY25: 0 | AZ25: 0 | BA25: 0 | BB25: 6.17 | BC25: Y | BG25: -9.5 | BH25: Wheels & Wheel Components | BI25: Tires & Wheels | BJ25: Automotive Wheel Covers & Hub Caps | BK25: PRO-119076-14.0 | BN25: N | BO25: Seller Fulfilled | BP25: Delivery | BQ25: New Seller Saving | BR25: 2.85 | BW25: =if(OR(F25="SALE",F25="REFUNDED"),IFERROR(Vlookup(I25,'Listing SKU - Fill SKU Mapping'!A:C,3,false),"Map"),"") -> Keystone | BX25: =IF(OR(F25="SALE",F25="REFUNDED")=TRUE,iferror(Vlookup(I25,'Listing SKU - Fill SKU Mapping'!A:B,2,false),"Map"),"") -> IMP371BLK | BY25: =IF(OR(F25="SALE",F25="REFUNDED")=TRUE,iferror(Vlookup(I25,'Listing SKU - Fill SKU Mapping'!A:D,4,false),"Map"),"") -> 43.79 | BZ25: =If(BW25="Keystone",11.5,"") -> 11.5 | CA25: =IF(ISNUMBER(BY25)=TRUE,BY25+BZ25,"") -> 55.29 | CB25: =if(F25="SALE",V25-CA25,"") -> 33.04 | CC25: =if(F25="REFUNDED",iferror(Vlookup(I25,'Listing SKU - Fill SKU Mapping'!A:B,2,false),"Map"),"") | CD25: =if(F25="REFUNDED",iferror(Vlookup(I25,'Listing SKU - Fill SKU Mapping'!A:C,3,false),"Map"),"") | CE25: =TEXT(G25,"YYYY") -> 2025 | CF25: =TEXT(G25,"MMMM") -> May | CG25: =IF(AND((G25-CG$1)>=0,(G25-CG$1)<=6), "This Week",IF(AND((G25-CG$1)>=-7,(G25-CG$1)<=-1), "Last Week",""))
A26: 200013138466310 | B26: 1 | C26: 109011528057285 | D26: 1 | F26: REFUNDED | G26: 45789 | H26: 1 | I26: WM-FR-IMP-22996312-17GB6S | J26: 460776240152 | K26: 17 inch Gloss Black ABS Wheel Skins Set Compatible with 2017-2021 GMC Acadia SL 2017-2023 Acadia SLE & Impostors for 22996312 Wheel Series | L26: 2038710 | R26: South Prince George | S26: 23805 | U26: -101.07 | V26: -89.26 | W26: -6.72 | X26: 0 | Y26: 0 | Z26: -95.98 | AA26: 0 | AB26: 0 | AC26: 0 | AD26: 0 | AE26: 0 | AF26: 0 | AG26: 0 | AH26: 0 | AI26: 0 | AJ26: 0 | AK26: 0 | AL26: 0 | AM26: 0 | AN26: 0 | AO26: 0 | AP26: 0 | AQ26: 0 | AR26: 0 | AS26: 0 | AT26: -5.09 | AU26: 0 | AV26: 0 | AW26: 0 | AX26: 0 | AY26: 0 | AZ26: 0 | BA26: 0 | BB26: -5.09 | BC26: Y | BD26: Return Refund | BE26: 5010 | BH26: Wheels & Wheel Components | BI26: Tires & Wheels | BL26: 1003 | BM26: Bought Somewhere Else | BN26: N | BO26: Seller Fulfilled | BW26: =if(OR(F26="SALE",F26="REFUNDED"),IFERROR(Vlookup(I26,'Listing SKU - Fill SKU Mapping'!A:C,3,false),"Map"),"") -> Keystone | BX26: =IF(OR(F26="SALE",F26="REFUNDED")=TRUE,iferror(Vlookup(I26,'Listing SKU - Fill SKU Mapping'!A:B,2,false),"Map"),"") -> IMP395BLK | BY26: =IF(OR(F26="SALE",F26="REFUNDED")=TRUE,iferror(Vlookup(I26,'Listing SKU - Fill SKU Mapping'!A:D,4,false),"Map"),"") -> 44.58 | BZ26: =If(BW26="Keystone",11.5,"") -> 11.5 | CA26: =IF(ISNUMBER(BY26)=TRUE,BY26+BZ26,"") -> 56.08 | CB26: =if(F26="SALE",V26-CA26,"") | CC26: =if(F26="REFUNDED",iferror(Vlookup(I26,'Listing SKU - Fill SKU Mapping'!A:B,2,false),"Map"),"") -> IMP395BLK | CD26: =if(F26="REFUNDED",iferror(Vlookup(I26,'Listing SKU - Fill SKU Mapping'!A:C,3,false),"Map"),"") -> Keystone | CE26: =TEXT(G26,"YYYY") -> 2025 | CF26: =TEXT(G26,"MMMM") -> May | CG26: =IF(AND((G26-CG$1)>=0,(G26-CG$1)<=6), "This Week",IF(AND((G26-CG$1)>=-7,(G26-CG$1)<=-1), "Last Week",""))
A27: 200013083775008 | B27: 4 | C27: 109009126618420 | D27: 4 | F27: ADJMNT | G27: 45788 | H27: 1 | I27: WM-FR-IMP-5934-18CH6SS | J27: 460776276861 | K27: 18 inch Chrome ABS Wheel Skins Set Compatible with 2019-2025 Chevrolet Blazer & Impostors for 5934 Wheel Series | L27: 2038710 | O27: IN | R27: Ossian | S27: 46777 | T27: Marketplace standard | U27: 0 | V27: -10.81 | W27: 0 | X27: 0 | Y27: 0 | Z27: 0 | AA27: 0 | AB27: 0 | AC27: 0 | AD27: 0 | AE27: 0 | AF27: 0 | AG27: 0 | AH27: 0 | AI27: 0 | AJ27: 0 | AK27: 0 | AL27: 0 | AM27: 0 | AN27: 0 | AO27: 0 | AP27: 0 | AQ27: 0 | AR27: 0 | AS27: 0 | AT27: 0 | AU27: 0 | AV27: 0 | AW27: 0 | AX27: 0 | AY27: 0 | AZ27: 0 | BA27: 0 | BB27: 0 | BC27: Y | BD27: Walmart Return Shipping Charge | BE27: 5013 | BH27: Wheels & Wheel Components | BI27: Tires & Wheels | BN27: N | BO27: Seller Fulfilled | BW27: =if(OR(F27="SALE",F27="REFUNDED"),IFERROR(Vlookup(I27,'Listing SKU - Fill SKU Mapping'!A:C,3,false),"Map"),"") | BX27: =IF(OR(F27="SALE",F27="REFUNDED")=TRUE,iferror(Vlookup(I27,'Listing SKU - Fill SKU Mapping'!A:B,2,false),"Map"),"") | BY27: =IF(OR(F27="SALE",F27="REFUNDED")=TRUE,iferror(Vlookup(I27,'Listing SKU - Fill SKU Mapping'!A:D,4,false),"Map"),"") | BZ27: =If(BW27="Keystone",11.5,"") | CA27: =IF(ISNUMBER(BY27)=TRUE,BY27+BZ27,"") | CB27: =if(F27="SALE",V27-CA27,"") | CC27: =if(F27="REFUNDED",iferror(Vlookup(I27,'Listing SKU - Fill SKU Mapping'!A:B,2,false),"Map"),"") | CD27: =if(F27="REFUNDED",iferror(Vlookup(I27,'Listing SKU - Fill SKU Mapping'!A:C,3,false),"Map"),"") | CE27: =TEXT(G27,"YYYY") -> 2025 | CF27: =TEXT(G27,"MMMM") -> May | CG27: =IF(AND((G27-CG$1)>=0,(G27-CG$1)<=6), "This Week",IF(AND((G27-CG$1)>=-7,(G27-CG$1)<=-1), "Last Week",""))
A28: 200013060278696 | B28: 7 | C28: 109011942953061 | D28: 7 | F28: REFUNDED | G28: 45787 | H28: 1 | I28: WM-FR-IMP-3943-17GB5SP | J28: 460776234854 | K28: Set of 4 17 inch Gloss Black Wheel Skins Covers Compatible with 17-19 Ford Escape SE 13-16 Ford Escape Impostors for 3943 Wheel Series | L28: 2038710 | R28: Whittier | S28: 90605 | U28: -104.24 | V28: -88.33 | W28: -6.65 | X28: 0 | Y28: 0 | Z28: -94.98 | AA28: 0 | AB28: 0 | AC28: 0 | AD28: 0 | AE28: 0 | AF28: 0 | AG28: 0 | AH28: 0 | AI28: 0 | AJ28: 0 | AK28: 0 | AL28: 0 | AM28: 0 | AN28: 0 | AO28: 0 | AP28: 0 | AQ28: 0 | AR28: 0 | AS28: 0 | AT28: -9.26 | AU28: 0 | AV28: 0 | AW28: 0 | AX28: 0 | AY28: 0 | AZ28: 0 | BA28: 0 | BB28: -9.26 | BC28: Y | BD28: Return Refund | BE28: 5010 | BH28: Wheels & Wheel Components | BI28: Tires & Wheels | BL28: 1010 | BM28: Defective/Broken | BN28: N | BO28: Seller Fulfilled | BW28: =if(OR(F28="SALE",F28="REFUNDED"),IFERROR(Vlookup(I28,'Listing SKU - Fill SKU Mapping'!A:C,3,false),"Map"),"") -> Keystone | BX28: =IF(OR(F28="SALE",F28="REFUNDED")=TRUE,iferror(Vlookup(I28,'Listing SKU - Fill SKU Mapping'!A:B,2,false),"Map"),"") -> IMP371BLK | BY28: =IF(OR(F28="SALE",F28="REFUNDED")=TRUE,iferror(Vlookup(I28,'Listing SKU - Fill SKU Mapping'!A:D,4,false),"Map"),"") -> 43.79 | BZ28: =If(BW28="Keystone",11.5,"") -> 11.5 | CA28: =IF(ISNUMBER(BY28)=TRUE,BY28+BZ28,"") -> 55.29 | CB28: =if(F28="SALE",V28-CA28,"") | CC28: =if(F28="REFUNDED",iferror(Vlookup(I28,'Listing SKU - Fill SKU Mapping'!A:B,2,false),"Map"),"") -> IMP371BLK | CD28: =if(F28="REFUNDED",iferror(Vlookup(I28,'Listing SKU - Fill SKU Mapping'!A:C,3,false),"Map"),"") -> Keystone | CE28: =TEXT(G28,"YYYY") -> 2025 | CF28: =TEXT(G28,"MMMM") -> May | CG28: =IF(AND((G28-CG$1)>=0,(G28-CG$1)<=6), "This Week",IF(AND((G28-CG$1)>=-7,(G28-CG$1)<=-1), "Last Week",""))
A29: 200013041673912 | B29: 1 | C29: 109008919231712 | D29: 1 | F29: ADJMNT | G29: 45781 | H29: 1 | I29: WM-FR-IMP-62593-17CH5DS | J29: 460776231143 | K29: 17 inch Chrome ABS Wheel Skins Set Compatible with 2013-2018 Nissan Altima & Impostors for 62593 Wheel Series | L29: 2038710 | O29: AR | R29: Little Rock | S29: 72204 | T29: Marketplace standard | U29: 0 | V29: -10.81 | W29: 0 | X29: 0 | Y29: 0 | Z29: 0 | AA29: 0 | AB29: 0 | AC29: 0 | AD29: 0 | AE29: 0 | AF29: 0 | AG29: 0 | AH29: 0 | AI29: 0 | AJ29: 0 | AK29: 0 | AL29: 0 | AM29: 0 | AN29: 0 | AO29: 0 | AP29: 0 | AQ29: 0 | AR29: 0 | AS29: 0 | AT29: 0 | AU29: 0 | AV29: 0 | AW29: 0 | AX29: 0 | AY29: 0 | AZ29: 0 | BA29: 0 | BB29: 0 | BC29: Y | BD29: Walmart Return Shipping Charge | BE29: 5013 | BH29: Wheels & Wheel Components | BI29: Tires & Wheels | BN29: N | BO29: Seller Fulfilled | BW29: =if(OR(F29="SALE",F29="REFUNDED"),IFERROR(Vlookup(I29,'Listing SKU - Fill SKU Mapping'!A:C,3,false),"Map"),"") | BX29: =IF(OR(F29="SALE",F29="REFUNDED")=TRUE,iferror(Vlookup(I29,'Listing SKU - Fill SKU Mapping'!A:B,2,false),"Map"),"") | BY29: =IF(OR(F29="SALE",F29="REFUNDED")=TRUE,iferror(Vlookup(I29,'Listing SKU - Fill SKU Mapping'!A:D,4,false),"Map"),"") | BZ29: =If(BW29="Keystone",11.5,"") | CA29: =IF(ISNUMBER(BY29)=TRUE,BY29+BZ29,"") | CB29: =if(F29="SALE",V29-CA29,"") | CC29: =if(F29="REFUNDED",iferror(Vlookup(I29,'Listing SKU - Fill SKU Mapping'!A:B,2,false),"Map"),"") | CD29: =if(F29="REFUNDED",iferror(Vlookup(I29,'Listing SKU - Fill SKU Mapping'!A:C,3,false),"Map"),"") | CE29: =TEXT(G29,"YYYY") -> 2025 | CF29: =TEXT(G29,"MMMM") -> May | CG29: =IF(AND((G29-CG$1)>=0,(G29-CG$1)<=6), "This Week",IF(AND((G29-CG$1)>=-7,(G29-CG$1)<=-1), "Last Week",""))
A30: 200013038493104 | B30: 1 | C30: 109011116508241 | D30: 1 | F30: REFUNDED | G30: 45776 | H30: 1 | I30: WM-FR-IMP-2363-20CH5SP | J30: 464567112352 | K30: Set of 4 20 inch Chrome Wheel Skins Covers compatible with 09-10 Dodge Ram 1500 11-24 Ram 1500 Classic Sport Laramie Rebel Tradesman Big Horn SLT Express Lone Star Limited Impostors | L30: 2038710 | R30: Beech Grove | S30: 46107 | U30: -92 | V30: -79.96 | W30: -6.02 | X30: 0 | Y30: 0 | Z30: -85.98 | AA30: 0 | AB30: 0 | AC30: 0 | AD30: 0 | AE30: 0 | AF30: 0 | AG30: 0 | AH30: 0 | AI30: 0 | AJ30: 0 | AK30: 0 | AL30: 0 | AM30: 0 | AN30: 0 | AO30: 0 | AP30: 0 | AQ30: 0 | AR30: 0 | AS30: 0 | AT30: -6.02 | AU30: 0 | AV30: 0 | AW30: 0 | AX30: 0 | AY30: 0 | AZ30: 0 | BA30: 0 | BB30: -6.02 | BC30: Y | BD30: Return Refund | BE30: 5010 | BH30: Wheels & Wheel Components | BI30: Tires & Wheels | BL30: 1000 | BM30: No Longer Wanted | BN30: N | BO30: Seller Fulfilled | BW30: =if(OR(F30="SALE",F30="REFUNDED"),IFERROR(Vlookup(I30,'Listing SKU - Fill SKU Mapping'!A:C,3,false),"Map"),"") -> Keystone | BX30: =IF(OR(F30="SALE",F30="REFUNDED")=TRUE,iferror(Vlookup(I30,'Listing SKU - Fill SKU Mapping'!A:B,2,false),"Map"),"") -> IMP331X | BY30: =IF(OR(F30="SALE",F30="REFUNDED")=TRUE,iferror(Vlookup(I30,'Listing SKU - Fill SKU Mapping'!A:D,4,false),"Map"),"") -> 61.94 | BZ30: =If(BW30="Keystone",11.5,"") -> 11.5 | CA30: =IF(ISNUMBER(BY30)=TRUE,BY30+BZ30,"") -> 73.44 | CB30: =if(F30="SALE",V30-CA30,"") | CC30: =if(F30="REFUNDED",iferror(Vlookup(I30,'Listing SKU - Fill SKU Mapping'!A:B,2,false),"Map"),"") -> IMP331X | CD30: =if(F30="REFUNDED",iferror(Vlookup(I30,'Listing SKU - Fill SKU Mapping'!A:C,3,false),"Map"),"") -> Keystone | CE30: =TEXT(G30,"YYYY") -> 2025 | CF30: =TEXT(G30,"MMMM") -> April | CG30: =IF(AND((G30-CG$1)>=0,(G30-CG$1)<=6), "This Week",IF(AND((G30-CG$1)>=-7,(G30-CG$1)<=-1), "Last Week",""))
A31: 200012947880406 | B31: 1 | C31: 109013723253596 | D31: 1 | F31: SALE | G31: 45793 | H31: 1 | I31: WM-FR-IMP-KT4Z1007A-18GB5SS | J31: 465595354004 | K31: Set of 4 18 inch Gloss Black ABS Wheel Skins Compatible with 2019 - 2022 Ford Edge SEL Impostors for KT4Z1007A Wheel Series | L31: 2038710 | O31: AL | R31: Gadsden | S31: 35903 | T31: Marketplace standard | U31: 71.26 | V31: 61.36 | W31: 4.62 | X31: 7 | Y31: 65.98 | Z31: 0 | AA31: 0 | AB31: 0 | AC31: 0 | AD31: 0 | AE31: 0 | AF31: 0 | AG31: 0 | AH31: 0 | AI31: 0 | AJ31: 0 | AK31: 0 | AL31: 0 | AM31: 0 | AN31: 0 | AO31: 5.28 | AP31: 0 | AQ31: 0 | AR31: 0 | AS31: 0 | AT31: 0 | AU31: 0 | AV31: 0 | AW31: 0 | AX31: 0 | AY31: 0 | AZ31: 0 | BA31: 0 | BB31: 5.28 | BC31: Y | BG31: -6.6 | BH31: Wheels & Wheel Components | BI31: Tires & Wheels | BJ31: Automotive Wheel Covers & Hub Caps | BK31: PRO-119076-16.0 | BN31: N | BO31: Seller Fulfilled | BP31: Delivery | BQ31: New Seller Saving | BR31: 1.98 | BW31: =if(OR(F31="SALE",F31="REFUNDED"),IFERROR(Vlookup(I31,'Listing SKU - Fill SKU Mapping'!A:C,3,false),"Map"),"") -> Keystone | BX31: =IF(OR(F31="SALE",F31="REFUNDED")=TRUE,iferror(Vlookup(I31,'Listing SKU - Fill SKU Mapping'!A:B,2,false),"Map"),"") -> IMP492BLK | BY31: =IF(OR(F31="SALE",F31="REFUNDED")=TRUE,iferror(Vlookup(I31,'Listing SKU - Fill SKU Mapping'!A:D,4,false),"Map"),"") -> 49.31 | BZ31: =If(BW31="Keystone",11.5,"") -> 11.5 | CA31: =IF(ISNUMBER(BY31)=TRUE,BY31+BZ31,"") -> 60.81 | CB31: =if(F31="SALE",V31-CA31,"") -> 0.55 | CC31: =if(F31="REFUNDED",iferror(Vlookup(I31,'Listing SKU - Fill SKU Mapping'!A:B,2,false),"Map"),"") | CD31: =if(F31="REFUNDED",iferror(Vlookup(I31,'Listing SKU - Fill SKU Mapping'!A:C,3,false),"Map"),"") | CE31: =TEXT(G31,"YYYY") -> 2025 | CF31: =TEXT(G31,"MMMM") -> May | CG31: =IF(AND((G31-CG$1)>=0,(G31-CG$1)<=6), "This Week",IF(AND((G31-CG$1)>=-7,(G31-CG$1)<=-1), "Last Week",""))
A32: 200012841383047 | B32: 1 | C32: 109007662415839 | D32: 1 | F32: REFUNDED | G32: 45791 | H32: 1 | I32: WM-FR-IMP-5712-18GB10S | J32: 460776230832 | K32: Set of 4 18 inch Gloss Black Wheel Skins Covers Compatible with 18-24 Chevrolet Equinox LS LT Premier 18-21 Equinox L 16-20 Impala Impostors for 5712 Wheel Series | L32: 2038710 | R32: Galesburg | S32: 61401 | U32: -113.34 | V32: -96.7 | W32: -7.28 | X32: 0 | Y32: 0 | Z32: -103.98 | AA32: 0 | AB32: 0 | AC32: 0 | AD32: 0 | AE32: 0 | AF32: 0 | AG32: 0 | AH32: 0 | AI32: 0 | AJ32: 0 | AK32: 0 | AL32: 0 | AM32: 0 | AN32: 0 | AO32: 0 | AP32: 0 | AQ32: 0 | AR32: 0 | AS32: 0 | AT32: -9.36 | AU32: 0 | AV32: 0 | AW32: 0 | AX32: 0 | AY32: 0 | AZ32: 0 | BA32: 0 | BB32: -9.36 | BC32: Y | BD32: Return Refund | BE32: 5010 | BH32: Wheels & Wheel Components | BI32: Tires & Wheels | BL32: 1000 | BM32: No Longer Wanted | BN32: N | BO32: Seller Fulfilled | BW32: =if(OR(F32="SALE",F32="REFUNDED"),IFERROR(Vlookup(I32,'Listing SKU - Fill SKU Mapping'!A:C,3,false),"Map"),"") -> Keystone | BX32: =IF(OR(F32="SALE",F32="REFUNDED")=TRUE,iferror(Vlookup(I32,'Listing SKU - Fill SKU Mapping'!A:B,2,false),"Map"),"") -> IMP407BLK | BY32: =IF(OR(F32="SALE",F32="REFUNDED")=TRUE,iferror(Vlookup(I32,'Listing SKU - Fill SKU Mapping'!A:D,4,false),"Map"),"") -> 49.71 | BZ32: =If(BW32="Keystone",11.5,"") -> 11.5 | CA32: =IF(ISNUMBER(BY32)=TRUE,BY32+BZ32,"") -> 61.21 | CB32: =if(F32="SALE",V32-CA32,"") | CC32: =if(F32="REFUNDED",iferror(Vlookup(I32,'Listing SKU - Fill SKU Mapping'!A:B,2,false),"Map"),"") -> IMP407BLK | CD32: =if(F32="REFUNDED",iferror(Vlookup(I32,'Listing SKU - Fill SKU Mapping'!A:C,3,false),"Map"),"") -> Keystone | CE32: =TEXT(G32,"YYYY") -> 2025 | CF32: =TEXT(G32,"MMMM") -> May | CG32: =IF(AND((G32-CG$1)>=0,(G32-CG$1)<=6), "This Week",IF(AND((G32-CG$1)>=-7,(G32-CG$1)<=-1), "Last Week",""))
A33: 200013365128295 | B33: 1 | C33: 109011840932398 | D33: 1 | F33: SALE | G33: 45775 | H33: 1 | I33: WM-FR-IMP-5629-18CH10S | J33: 460776231204 | K33: 18 inch Chrome ABS Wheel Skins Set Compatible with 2013-2015 Chevrolet Camaro LS LT & Impostors for 5629 5575 Wheel Series | L33: 2038710 | O33: IN | R33: New Albany | S33: 47150 | T33: Marketplace standard | U33: 155.13 | V33: 134.83 | W33: 10.15 | X33: 7 | Y33: 144.98 | Z33: 0 | AA33: 0 | AB33: 0 | AC33: 0 | AD33: 0 | AE33: 0 | AF33: 0 | AG33: 0 | AH33: 0 | AI33: 0 | AJ33: 0 | AK33: 0 | AL33: 0 | AM33: 0 | AN33: 0 | AO33: 10.15 | AP33: 0 | AQ33: 0 | AR33: 0 | AS33: 0 | AT33: 0 | AU33: 0 | AV33: 0 | AW33: 0 | AX33: 0 | AY33: 0 | AZ33: 0 | BA33: 0 | BB33: 10.15 | BC33: Y | BG33: -14.5 | BH33: Wheels & Wheel Components | BI33: Tires & Wheels | BJ33: Automotive Wheel Covers & Hub Caps | BK33: PRO-119076-13.0 | BN33: N | BO33: Seller Fulfilled | BP33: Delivery | BQ33: New Seller Saving | BR33: 4.35 | BW33: =if(OR(F33="SALE",F33="REFUNDED"),IFERROR(Vlookup(I33,'Listing SKU - Fill SKU Mapping'!A:C,3,false),"Map"),"") -> Keystone | BX33: =IF(OR(F33="SALE",F33="REFUNDED")=TRUE,iferror(Vlookup(I33,'Listing SKU - Fill SKU Mapping'!A:B,2,false),"Map"),"") -> IMP398X | BY33: =IF(OR(F33="SALE",F33="REFUNDED")=TRUE,iferror(Vlookup(I33,'Listing SKU - Fill SKU Mapping'!A:D,4,false),"Map"),"") -> 74.21 | BZ33: =If(BW33="Keystone",11.5,"") -> 11.5 | CA33: =IF(ISNUMBER(BY33)=TRUE,BY33+BZ33,"") -> 85.71 | CB33: =if(F33="SALE",V33-CA33,"") -> 49.12 | CC33: =if(F33="REFUNDED",iferror(Vlookup(I33,'Listing SKU - Fill SKU Mapping'!A:B,2,false),"Map"),"") | CD33: =if(F33="REFUNDED",iferror(Vlookup(I33,'Listing SKU - Fill SKU Mapping'!A:C,3,false),"Map"),"") | CE33: =TEXT(G33,"YYYY") -> 2025 | CF33: =TEXT(G33,"MMMM") -> April | CG33: =IF(AND((G33-CG$1)>=0,(G33-CG$1)<=6), "This Week",IF(AND((G33-CG$1)>=-7,(G33-CG$1)<=-1), "Last Week",""))
A34: 200013138466310 | B34: 1 | C34: 109011528057285 | D34: 1 | F34: SALE | G34: 45772 | H34: 1 | I34: WM-FR-IMP-22996312-17GB6S | J34: 460776240152 | K34: 17 inch Gloss Black ABS Wheel Skins Set Compatible with 2017-2021 GMC Acadia SL 2017-2023 Acadia SLE & Impostors for 22996312 Wheel Series | L34: 2038710 | O34: VA | R34: South Prince George | S34: 23805 | T34: Marketplace standard | U34: 101.07 | V34: 89.26 | W34: 6.72 | X34: 7 | Y34: 95.98 | Z34: 0 | AA34: 0 | AB34: 0 | AC34: 0 | AD34: 0 | AE34: 0 | AF34: 0 | AG34: 0 | AH34: 0 | AI34: 0 | AJ34: 0 | AK34: 0 | AL34: 0 | AM34: 0 | AN34: 0 | AO34: 5.09 | AP34: 0 | AQ34: 0 | AR34: 0 | AS34: 0 | AT34: 0 | AU34: 0 | AV34: 0 | AW34: 0 | AX34: 0 | AY34: 0 | AZ34: 0 | BA34: 0 | BB34: 5.09 | BC34: Y | BG34: -9.6 | BH34: Wheels & Wheel Components | BI34: Tires & Wheels | BJ34: Automotive Wheel Covers & Hub Caps | BK34: PRO-119076-13.0 | BN34: N | BO34: Seller Fulfilled | BP34: Delivery | BQ34: New Seller Saving | BR34: 2.88 | BW34: =if(OR(F34="SALE",F34="REFUNDED"),IFERROR(Vlookup(I34,'Listing SKU - Fill SKU Mapping'!A:C,3,false),"Map"),"") -> Keystone | BX34: =IF(OR(F34="SALE",F34="REFUNDED")=TRUE,iferror(Vlookup(I34,'Listing SKU - Fill SKU Mapping'!A:B,2,false),"Map"),"") -> IMP395BLK | BY34: =IF(OR(F34="SALE",F34="REFUNDED")=TRUE,iferror(Vlookup(I34,'Listing SKU - Fill SKU Mapping'!A:D,4,false),"Map"),"") -> 44.58 | BZ34: =If(BW34="Keystone",11.5,"") -> 11.5 | CA34: =IF(ISNUMBER(BY34)=TRUE,BY34+BZ34,"") -> 56.08 | CB34: =if(F34="SALE",V34-CA34,"") -> 33.18 | CC34: =if(F34="REFUNDED",iferror(Vlookup(I34,'Listing SKU - Fill SKU Mapping'!A:B,2,false),"Map"),"") | CD34: =if(F34="REFUNDED",iferror(Vlookup(I34,'Listing SKU - Fill SKU Mapping'!A:C,3,false),"Map"),"") | CE34: =TEXT(G34,"YYYY") -> 2025 | CF34: =TEXT(G34,"MMMM") -> April | CG34: =IF(AND((G34-CG$1)>=0,(G34-CG$1)<=6), "This Week",IF(AND((G34-CG$1)>=-7,(G34-CG$1)<=-1), "Last Week",""))
A35: 200013107061952 | B35: 5 | C35: 109011838951391 | D35: 5 | F35: SALE | G35: 45775 | H35: 1 | I35: WM-FR-IMP-22968927-17GB5VS | J35: 460776238135 | K35: Set of 4 17 inch Gloss Black ABS Wheel Skins Wheel Covers compatible with 18-24 Chevrolet Equinox LT LS 18-21 Equinox L Impostors for 22968927 Wheel Series | L35: 2038710 | O35: TX | R35: San Antonio | S35: 78218 | T35: Marketplace standard | U35: 113.63 | V35: 97.63 | W35: 7.35 | X35: 7 | Y35: 104.98 | Z35: 0 | AA35: 0 | AB35: 0 | AC35: 0 | AD35: 0 | AE35: 0 | AF35: 0 | AG35: 0 | AH35: 0 | AI35: 0 | AJ35: 0 | AK35: 0 | AL35: 0 | AM35: 0 | AN35: 0 | AO35: 8.65 | AP35: 0 | AQ35: 0 | AR35: 0 | AS35: 0 | AT35: 0 | AU35: 0 | AV35: 0 | AW35: 0 | AX35: 0 | AY35: 0 | AZ35: 0 | BA35: 0 | BB35: 8.65 | BC35: Y | BG35: -10.5 | BH35: Wheels & Wheel Components | BI35: Tires & Wheels | BJ35: Automotive Wheel Covers & Hub Caps | BK35: PRO-119076-13.0 | BN35: N | BO35: Seller Fulfilled | BP35: Delivery | BQ35: New Seller Saving | BR35: 3.15 | BW35: =if(OR(F35="SALE",F35="REFUNDED"),IFERROR(Vlookup(I35,'Listing SKU - Fill SKU Mapping'!A:C,3,false),"Map"),"") -> Keystone | BX35: =IF(OR(F35="SALE",F35="REFUNDED")=TRUE,iferror(Vlookup(I35,'Listing SKU - Fill SKU Mapping'!A:B,2,false),"Map"),"") -> IMP409BLK | BY35: =IF(OR(F35="SALE",F35="REFUNDED")=TRUE,iferror(Vlookup(I35,'Listing SKU - Fill SKU Mapping'!A:D,4,false),"Map"),"") -> 50.49 | BZ35: =If(BW35="Keystone",11.5,"") -> 11.5 | CA35: =IF(ISNUMBER(BY35)=TRUE,BY35+BZ35,"") -> 61.99 | CB35: =if(F35="SALE",V35-CA35,"") -> 35.64 | CC35: =if(F35="REFUNDED",iferror(Vlookup(I35,'Listing SKU - Fill SKU Mapping'!A:B,2,false),"Map"),"") | CD35: =if(F35="REFUNDED",iferror(Vlookup(I35,'Listing SKU - Fill SKU Mapping'!A:C,3,false),"Map"),"") | CE35: =TEXT(G35,"YYYY") -> 2025 | CF35: =TEXT(G35,"MMMM") -> April | CG35: =IF(AND((G35-CG$1)>=0,(G35-CG$1)<=6), "This Week",IF(AND((G35-CG$1)>=-7,(G35-CG$1)<=-1), "Last Week",""))
A36: 200013070499551 | B36: 6 | C36: 109012152656186 | D36: 6 | F36: SALE | G36: 45778 | H36: 1 | I36: WM-FR-IMP-9077-16GB5SP | J36: 460776231075 | K36: Set of 4 16 inch Gloss Black Wheel Skins Covers Compatible with 07-17 Jeep Patriot 14-16 Jeep Compass Impostors for 9077 Wheel Series | L36: 2038710 | O36: DE | R36: Newark | S36: 19711 | T36: Marketplace standard | U36: 98.98 | V36: 92.05 | W36: 6.93 | X36: 7 | Y36: 98.98 | Z36: 0 | AA36: 0 | AB36: 0 | AC36: 0 | AD36: 0 | AE36: 0 | AF36: 0 | AG36: 0 | AH36: 0 | AI36: 0 | AJ36: 0 | AK36: 0 | AL36: 0 | AM36: 0 | AN36: 0 | AO36: 0 | AP36: 0 | AQ36: 0 | AR36: 0 | AS36: 0 | AT36: 0 | AU36: 0 | AV36: 0 | AW36: 0 | AX36: 0 | AY36: 0 | AZ36: 0 | BA36: 0 | BB36: 0 | BC36: N | BG36: -9.9 | BH36: Wheels & Wheel Components | BI36: Tires & Wheels | BJ36: Automotive Wheel Covers & Hub Caps | BK36: PRO-119076-13.0 | BN36: N | BO36: Seller Fulfilled | BP36: Delivery | BQ36: New Seller Saving | BR36: 2.97 | BW36: =if(OR(F36="SALE",F36="REFUNDED"),IFERROR(Vlookup(I36,'Listing SKU - Fill SKU Mapping'!A:C,3,false),"Map"),"") -> Keystone | BX36: =IF(OR(F36="SALE",F36="REFUNDED")=TRUE,iferror(Vlookup(I36,'Listing SKU - Fill SKU Mapping'!A:B,2,false),"Map"),"") -> IMP78BLK | BY36: =IF(OR(F36="SALE",F36="REFUNDED")=TRUE,iferror(Vlookup(I36,'Listing SKU - Fill SKU Mapping'!A:D,4,false),"Map"),"") -> 46.16 | BZ36: =If(BW36="Keystone",11.5,"") -> 11.5 | CA36: =IF(ISNUMBER(BY36)=TRUE,BY36+BZ36,"") -> 57.66 | CB36: =if(F36="SALE",V36-CA36,"") -> 34.39 | CC36: =if(F36="REFUNDED",iferror(Vlookup(I36,'Listing SKU - Fill SKU Mapping'!A:B,2,false),"Map"),"") | CD36: =if(F36="REFUNDED",iferror(Vlookup(I36,'Listing SKU - Fill SKU Mapping'!A:C,3,false),"Map"),"") | CE36: =TEXT(G36,"YYYY") -> 2025 | CF36: =TEXT(G36,"MMMM") -> May | CG36: =IF(AND((G36-CG$1)>=0,(G36-CG$1)<=6), "This Week",IF(AND((G36-CG$1)>=-7,(G36-CG$1)<=-1), "Last Week",""))
A37: 200013060278696 | B37: 7 | C37: 109011942953061 | D37: 7 | F37: SALE | G37: 45775 | H37: 1 | I37: WM-FR-IMP-3943-17GB5SP | J37: 460776234854 | K37: Set of 4 17 inch Gloss Black Wheel Skins Covers Compatible with 17-19 Ford Escape SE 13-16 Ford Escape Impostors for 3943 Wheel Series | L37: 2038710 | O37: CA | R37: Whittier | S37: 90605 | T37: Marketplace standard | U37: 104.24 | V37: 88.33 | W37: 6.65 | X37: 7 | Y37: 94.98 | Z37: 0 | AA37: 0 | AB37: 0 | AC37: 0 | AD37: 0 | AE37: 0 | AF37: 0 | AG37: 0 | AH37: 0 | AI37: 0 | AJ37: 0 | AK37: 0 | AL37: 0 | AM37: 0 | AN37: 0 | AO37: 9.26 | AP37: 0 | AQ37: 0 | AR37: 0 | AS37: 0 | AT37: 0 | AU37: 0 | AV37: 0 | AW37: 0 | AX37: 0 | AY37: 0 | AZ37: 0 | BA37: 0 | BB37: 9.26 | BC37: Y | BG37: -9.5 | BH37: Wheels & Wheel Components | BI37: Tires & Wheels | BJ37: Automotive Wheel Covers & Hub Caps | BK37: PRO-119076-13.0 | BN37: N | BO37: Seller Fulfilled | BP37: Delivery | BQ37: New Seller Saving | BR37: 2.85 | BW37: =if(OR(F37="SALE",F37="REFUNDED"),IFERROR(Vlookup(I37,'Listing SKU - Fill SKU Mapping'!A:C,3,false),"Map"),"") -> Keystone | BX37: =IF(OR(F37="SALE",F37="REFUNDED")=TRUE,iferror(Vlookup(I37,'Listing SKU - Fill SKU Mapping'!A:B,2,false),"Map"),"") -> IMP371BLK | BY37: =IF(OR(F37="SALE",F37="REFUNDED")=TRUE,iferror(Vlookup(I37,'Listing SKU - Fill SKU Mapping'!A:D,4,false),"Map"),"") -> 43.79 | BZ37: =If(BW37="Keystone",11.5,"") -> 11.5 | CA37: =IF(ISNUMBER(BY37)=TRUE,BY37+BZ37,"") -> 55.29 | CB37: =if(F37="SALE",V37-CA37,"") -> 33.04 | CC37: =if(F37="REFUNDED",iferror(Vlookup(I37,'Listing SKU - Fill SKU Mapping'!A:B,2,false),"Map"),"") | CD37: =if(F37="REFUNDED",iferror(Vlookup(I37,'Listing SKU - Fill SKU Mapping'!A:C,3,false),"Map"),"") | CE37: =TEXT(G37,"YYYY") -> 2025 | CF37: =TEXT(G37,"MMMM") -> April | CG37: =IF(AND((G37-CG$1)>=0,(G37-CG$1)<=6), "This Week",IF(AND((G37-CG$1)>=-7,(G37-CG$1)<=-1), "Last Week",""))
A38: 200013053340689 | B38: 1 | C38: 109012256632702 | D38: 1 | F38: SALE | G38: 45778 | H38: 1 | I38: WM-FR-IMP-63927-17CH5SP | J38: 460776231020 | K38: Set of 4 17 inch Chrome Wheel Skins Covers compatible with 07-11 Honda CR-V LX Impostors for 63927 Wheel Series | L38: 2038710 | O38: MI | R38: Niles | S38: 49120 | T38: Marketplace standard | U38: 125.06 | V38: 109.72 | W38: 8.26 | X38: 7 | Y38: 117.98 | Z38: 0 | AA38: 0 | AB38: 0 | AC38: 0 | AD38: 0 | AE38: 0 | AF38: 0 | AG38: 0 | AH38: 0 | AI38: 0 | AJ38: 0 | AK38: 0 | AL38: 0 | AM38: 0 | AN38: 0 | AO38: 7.08 | AP38: 0 | AQ38: 0 | AR38: 0 | AS38: 0 | AT38: 0 | AU38: 0 | AV38: 0 | AW38: 0 | AX38: 0 | AY38: 0 | AZ38: 0 | BA38: 0 | BB38: 7.08 | BC38: Y | BG38: -11.8 | BH38: Wheels & Wheel Components | BI38: Tires & Wheels | BJ38: Automotive Wheel Covers & Hub Caps | BK38: PRO-119076-13.0 | BN38: N | BO38: Seller Fulfilled | BP38: Delivery | BQ38: New Seller Saving | BR38: 3.54 | BW38: =if(OR(F38="SALE",F38="REFUNDED"),IFERROR(Vlookup(I38,'Listing SKU - Fill SKU Mapping'!A:C,3,false),"Map"),"") -> Keystone | BX38: =IF(OR(F38="SALE",F38="REFUNDED")=TRUE,iferror(Vlookup(I38,'Listing SKU - Fill SKU Mapping'!A:B,2,false),"Map"),"") -> IMP75X | BY38: =IF(OR(F38="SALE",F38="REFUNDED")=TRUE,iferror(Vlookup(I38,'Listing SKU - Fill SKU Mapping'!A:D,4,false),"Map"),"") -> 59.57 | BZ38: =If(BW38="Keystone",11.5,"") -> 11.5 | CA38: =IF(ISNUMBER(BY38)=TRUE,BY38+BZ38,"") -> 71.07 | CB38: =if(F38="SALE",V38-CA38,"") -> 38.65 | CC38: =if(F38="REFUNDED",iferror(Vlookup(I38,'Listing SKU - Fill SKU Mapping'!A:B,2,false),"Map"),"") | CD38: =if(F38="REFUNDED",iferror(Vlookup(I38,'Listing SKU - Fill SKU Mapping'!A:C,3,false),"Map"),"") | CE38: =TEXT(G38,"YYYY") -> 2025 | CF38: =TEXT(G38,"MMMM") -> May | CG38: =IF(AND((G38-CG$1)>=0,(G38-CG$1)<=6), "This Week",IF(AND((G38-CG$1)>=-7,(G38-CG$1)<=-1), "Last Week",""))
A39: 200013049604965 | B39: 1 | C39: 109011426675392 | D39: 1 | F39: SALE | G39: 45771 | H39: 1 | I39: WM-FR-IMP-5833-17GB5DS | J39: 460776235042 | K39: 17 inch Gloss Black ABS Wheel Skins Set Compatible with 2018-2021 GMC Terrain SL 2018-2023 GMC Terrain SLE & Impostors for 5833 Wheel Series | L39: 2038710 | O39: VA | R39: South Prince George | S39: 23805 | T39: Marketplace standard | U39: 109.49 | V39: 96.7 | W39: 7.28 | X39: 7 | Y39: 103.98 | Z39: 0 | AA39: 0 | AB39: 0 | AC39: 0 | AD39: 0 | AE39: 0 | AF39: 0 | AG39: 0 | AH39: 0 | AI39: 0 | AJ39: 0 | AK39: 0 | AL39: 0 | AM39: 0 | AN39: 0 | AO39: 5.51 | AP39: 0 | AQ39: 0 | AR39: 0 | AS39: 0 | AT39: 0 | AU39: 0 | AV39: 0 | AW39: 0 | AX39: 0 | AY39: 0 | AZ39: 0 | BA39: 0 | BB39: 5.51 | BC39: Y | BG39: -10.4 | BH39: Wheels & Wheel Components | BI39: Tires & Wheels | BJ39: Automotive Wheel Covers & Hub Caps | BK39: PRO-119076-12.0 | BN39: N | BO39: Seller Fulfilled | BP39: Delivery | BQ39: New Seller Saving | BR39: 3.12 | BW39: =if(OR(F39="SALE",F39="REFUNDED"),IFERROR(Vlookup(I39,'Listing SKU - Fill SKU Mapping'!A:C,3,false),"Map"),"") -> Keystone | BX39: =IF(OR(F39="SALE",F39="REFUNDED")=TRUE,iferror(Vlookup(I39,'Listing SKU - Fill SKU Mapping'!A:B,2,false),"Map"),"") -> IMP417BLK | BY39: =IF(OR(F39="SALE",F39="REFUNDED")=TRUE,iferror(Vlookup(I39,'Listing SKU - Fill SKU Mapping'!A:D,4,false),"Map"),"") -> 50.1 | BZ39: =If(BW39="Keystone",11.5,"") -> 11.5 | CA39: =IF(ISNUMBER(BY39)=TRUE,BY39+BZ39,"") -> 61.6 | CB39: =if(F39="SALE",V39-CA39,"") -> 35.1 | CC39: =if(F39="REFUNDED",iferror(Vlookup(I39,'Listing SKU - Fill SKU Mapping'!A:B,2,false),"Map"),"") | CD39: =if(F39="REFUNDED",iferror(Vlookup(I39,'Listing SKU - Fill SKU Mapping'!A:C,3,false),"Map"),"") | CE39: =TEXT(G39,"YYYY") -> 2025 | CF39: =TEXT(G39,"MMMM") -> April | CG39: =IF(AND((G39-CG$1)>=0,(G39-CG$1)<=6), "This Week",IF(AND((G39-CG$1)>=-7,(G39-CG$1)<=-1), "Last Week",""))
A40: 200013049604965 | B40: 1 | C40: 109011426675392 | D40: 1 | F40: REFUNDED | G40: 45775 | H40: 1 | I40: WM-FR-IMP-5833-17GB5DS | J40: 460776235042 | K40: 17 inch Gloss Black ABS Wheel Skins Set Compatible with 2018-2021 GMC Terrain SL 2018-2023 GMC Terrain SLE & Impostors for 5833 Wheel Series | L40: 2038710 | R40: South Prince George | S40: 23805 | U40: -109.49 | V40: -96.7 | W40: -7.28 | X40: 0 | Y40: 0 | Z40: -103.98 | AA40: 0 | AB40: 0 | AC40: 0 | AD40: 0 | AE40: 0 | AF40: 0 | AG40: 0 | AH40: 0 | AI40: 0 | AJ40: 0 | AK40: 0 | AL40: 0 | AM40: 0 | AN40: 0 | AO40: 0 | AP40: 0 | AQ40: 0 | AR40: 0 | AS40: 0 | AT40: -5.51 | AU40: 0 | AV40: 0 | AW40: 0 | AX40: 0 | AY40: 0 | AZ40: 0 | BA40: 0 | BB40: -5.51 | BC40: Y | BD40: Return Refund | BE40: 5010 | BH40: Wheels & Wheel Components | BI40: Tires & Wheels | BL40: 1000 | BM40: No Longer Wanted | BN40: N | BO40: Seller Fulfilled | BW40: =if(OR(F40="SALE",F40="REFUNDED"),IFERROR(Vlookup(I40,'Listing SKU - Fill SKU Mapping'!A:C,3,false),"Map"),"") -> Keystone | BX40: =IF(OR(F40="SALE",F40="REFUNDED")=TRUE,iferror(Vlookup(I40,'Listing SKU - Fill SKU Mapping'!A:B,2,false),"Map"),"") -> IMP417BLK | BY40: =IF(OR(F40="SALE",F40="REFUNDED")=TRUE,iferror(Vlookup(I40,'Listing SKU - Fill SKU Mapping'!A:D,4,false),"Map"),"") -> 50.1 | BZ40: =If(BW40="Keystone",11.5,"") -> 11.5 | CA40: =IF(ISNUMBER(BY40)=TRUE,BY40+BZ40,"") -> 61.6 | CB40: =if(F40="SALE",V40-CA40,"") | CC40: =if(F40="REFUNDED",iferror(Vlookup(I40,'Listing SKU - Fill SKU Mapping'!A:B,2,false),"Map"),"") -> IMP417BLK | CD40: =if(F40="REFUNDED",iferror(Vlookup(I40,'Listing SKU - Fill SKU Mapping'!A:C,3,false),"Map"),"") -> Keystone | CE40: =TEXT(G40,"YYYY") -> 2025 | CF40: =TEXT(G40,"MMMM") -> April | CG40: =IF(AND((G40-CG$1)>=0,(G40-CG$1)<=6), "This Week",IF(AND((G40-CG$1)>=-7,(G40-CG$1)<=-1), "Last Week",""))
A41: 200013038493104 | B41: 1 | C41: 109011116508241 | D41: 1 | F41: SALE | G41: 45768 | H41: 1 | I41: WM-FR-IMP-2363-20CH5SP | J41: 464567112352 | K41: Set of 4 20 inch Chrome Wheel Skins Covers compatible with 09-10 Dodge Ram 1500 11-24 Ram 1500 Classic Sport Laramie Rebel Tradesman Big Horn SLT Express Lone Star Limited Impostors | L41: 2038710 | O41: IN | R41: Beech Grove | S41: 46107 | T41: Marketplace standard | U41: 92 | V41: 79.96 | W41: 6.02 | X41: 7 | Y41: 85.98 | Z41: 0 | AA41: 0 | AB41: 0 | AC41: 0 | AD41: 0 | AE41: 0 | AF41: 0 | AG41: 0 | AH41: 0 | AI41: 0 | AJ41: 0 | AK41: 0 | AL41: 0 | AM41: 0 | AN41: 0 | AO41: 6.02 | AP41: 0 | AQ41: 0 | AR41: 0 | AS41: 0 | AT41: 0 | AU41: 0 | AV41: 0 | AW41: 0 | AX41: 0 | AY41: 0 | AZ41: 0 | BA41: 0 | BB41: 6.02 | BC41: Y | BG41: -8.6 | BH41: Wheels & Wheel Components | BI41: Tires & Wheels | BJ41: Automotive Wheel Covers & Hub Caps | BK41: PRO-119076-12.0 | BN41: N | BO41: Seller Fulfilled | BP41: Delivery | BQ41: New Seller Saving | BR41: 2.58 | BW41: =if(OR(F41="SALE",F41="REFUNDED"),IFERROR(Vlookup(I41,'Listing SKU - Fill SKU Mapping'!A:C,3,false),"Map"),"") -> Keystone | BX41: =IF(OR(F41="SALE",F41="REFUNDED")=TRUE,iferror(Vlookup(I41,'Listing SKU - Fill SKU Mapping'!A:B,2,false),"Map"),"") -> IMP331X | BY41: =IF(OR(F41="SALE",F41="REFUNDED")=TRUE,iferror(Vlookup(I41,'Listing SKU - Fill SKU Mapping'!A:D,4,false),"Map"),"") -> 61.94 | BZ41: =If(BW41="Keystone",11.5,"") -> 11.5 | CA41: =IF(ISNUMBER(BY41)=TRUE,BY41+BZ41,"") -> 73.44 | CB41: =if(F41="SALE",V41-CA41,"") -> 6.52 | CC41: =if(F41="REFUNDED",iferror(Vlookup(I41,'Listing SKU - Fill SKU Mapping'!A:B,2,false),"Map"),"") | CD41: =if(F41="REFUNDED",iferror(Vlookup(I41,'Listing SKU - Fill SKU Mapping'!A:C,3,false),"Map"),"") | CE41: =TEXT(G41,"YYYY") -> 2025 | CF41: =TEXT(G41,"MMMM") -> April | CG41: =IF(AND((G41-CG$1)>=0,(G41-CG$1)<=6), "This Week",IF(AND((G41-CG$1)>=-7,(G41-CG$1)<=-1), "Last Week",""))
A42: 200013001971046 | B42: 1 | C42: 109010999475878 | D42: 1 | F42: SALE | G42: 45768 | H42: 1 | I42: WM-FR-IMP-5657-17GB5SP | J42: 460776230825 | K42: Set of 4 17 inch Gloss Black Wheel Skins Covers Compatible with 15-18 Chevrolet Silverado 1500 LS Impostors for 5657 Wheel Series | L42: 2038710 | O42: PA | R42: Mount Union | S42: 17066 | T42: Marketplace standard | U42: 116.58 | V42: 102.28 | W42: 7.7 | X42: 7 | Y42: 109.98 | Z42: 0 | AA42: 0 | AB42: 0 | AC42: 0 | AD42: 0 | AE42: 0 | AF42: 0 | AG42: 0 | AH42: 0 | AI42: 0 | AJ42: 0 | AK42: 0 | AL42: 0 | AM42: 0 | AN42: 0 | AO42: 6.6 | AP42: 0 | AQ42: 0 | AR42: 0 | AS42: 0 | AT42: 0 | AU42: 0 | AV42: 0 | AW42: 0 | AX42: 0 | AY42: 0 | AZ42: 0 | BA42: 0 | BB42: 6.6 | BC42: Y | BG42: -11 | BH42: Wheels & Wheel Components | BI42: Tires & Wheels | BJ42: Automotive Wheel Covers & Hub Caps | BK42: PRO-119076-12.0 | BN42: N | BO42: Seller Fulfilled | BP42: Delivery | BQ42: New Seller Saving | BR42: 3.3 | BW42: =if(OR(F42="SALE",F42="REFUNDED"),IFERROR(Vlookup(I42,'Listing SKU - Fill SKU Mapping'!A:C,3,false),"Map"),"") -> Keystone | BX42: =IF(OR(F42="SALE",F42="REFUNDED")=TRUE,iferror(Vlookup(I42,'Listing SKU - Fill SKU Mapping'!A:B,2,false),"Map"),"") -> IMP390BLKN | BY42: =IF(OR(F42="SALE",F42="REFUNDED")=TRUE,iferror(Vlookup(I42,'Listing SKU - Fill SKU Mapping'!A:D,4,false),"Map"),"") -> 54.05 | BZ42: =If(BW42="Keystone",11.5,"") -> 11.5 | CA42: =IF(ISNUMBER(BY42)=TRUE,BY42+BZ42,"") -> 65.55 | CB42: =if(F42="SALE",V42-CA42,"") -> 36.73 | CC42: =if(F42="REFUNDED",iferror(Vlookup(I42,'Listing SKU - Fill SKU Mapping'!A:B,2,false),"Map"),"") | CD42: =if(F42="REFUNDED",iferror(Vlookup(I42,'Listing SKU - Fill SKU Mapping'!A:C,3,false),"Map"),"") | CE42: =TEXT(G42,"YYYY") -> 2025 | CF42: =TEXT(G42,"MMMM") -> April | CG42: =IF(AND((G42-CG$1)>=0,(G42-CG$1)<=6), "This Week",IF(AND((G42-CG$1)>=-7,(G42-CG$1)<=-1), "Last Week",""))
A43: 200013001971046 | B43: 1 | C43: 109010999475878 | D43: 1 | F43: REFUNDED | G43: 45779 | H43: 1 | I43: WM-FR-IMP-5657-17GB5SP | J43: 460776230825 | K43: Set of 4 17 inch Gloss Black Wheel Skins Covers Compatible with 15-18 Chevrolet Silverado 1500 LS Impostors for 5657 Wheel Series | L43: 2038710 | R43: Mount Union | S43: 17066 | U43: -116.58 | V43: -102.28 | W43: -7.7 | X43: 0 | Y43: 0 | Z43: -109.98 | AA43: 0 | AB43: 0 | AC43: 0 | AD43: 0 | AE43: 0 | AF43: 0 | AG43: 0 | AH43: 0 | AI43: 0 | AJ43: 0 | AK43: 0 | AL43: 0 | AM43: 0 | AN43: 0 | AO43: 0 | AP43: 0 | AQ43: 0 | AR43: 0 | AS43: 0 | AT43: -6.6 | AU43: 0 | AV43: 0 | AW43: 0 | AX43: 0 | AY43: 0 | AZ43: 0 | BA43: 0 | BB43: -6.6 | BC43: Y | BD43: Return Refund | BE43: 5010 | BH43: Wheels & Wheel Components | BI43: Tires & Wheels | BL43: 1018 | BM43: Not as described/pictured | BN43: N | BO43: Seller Fulfilled | BW43: =if(OR(F43="SALE",F43="REFUNDED"),IFERROR(Vlookup(I43,'Listing SKU - Fill SKU Mapping'!A:C,3,false),"Map"),"") -> Keystone | BX43: =IF(OR(F43="SALE",F43="REFUNDED")=TRUE,iferror(Vlookup(I43,'Listing SKU - Fill SKU Mapping'!A:B,2,false),"Map"),"") -> IMP390BLKN | BY43: =IF(OR(F43="SALE",F43="REFUNDED")=TRUE,iferror(Vlookup(I43,'Listing SKU - Fill SKU Mapping'!A:D,4,false),"Map"),"") -> 54.05 | BZ43: =If(BW43="Keystone",11.5,"") -> 11.5 | CA43: =IF(ISNUMBER(BY43)=TRUE,BY43+BZ43,"") -> 65.55 | CB43: =if(F43="SALE",V43-CA43,"") | CC43: =if(F43="REFUNDED",iferror(Vlookup(I43,'Listing SKU - Fill SKU Mapping'!A:B,2,false),"Map"),"") -> IMP390BLKN | CD43: =if(F43="REFUNDED",iferror(Vlookup(I43,'Listing SKU - Fill SKU Mapping'!A:C,3,false),"Map"),"") -> Keystone | CE43: =TEXT(G43,"YYYY") -> 2025 | CF43: =TEXT(G43,"MMMM") -> May | CG43: =IF(AND((G43-CG$1)>=0,(G43-CG$1)<=6), "This Week",IF(AND((G43-CG$1)>=-7,(G43-CG$1)<=-1), "Last Week",""))
A44: 200012993559082 | B44: 1 | C44: 109011114761058 | D44: 1 | F44: SALE | G44: 45768 | H44: 1 | I44: WM-FR-IMP-10043-18CH5DS | J44: 464567131070 | K44: Set of 4 18 inch Chrome Wheel Skins Covers Compatible with 15-18 Ford Edge Impostors for 10043 Wheel Series | L44: 2038710 | O44: TX | R44: Houston | S44: 77040 | T44: Marketplace standard | U44: 108.23 | V44: 92.98 | W44: 7 | X44: 7 | Y44: 99.98 | Z44: 0 | AA44: 0 | AB44: 0 | AC44: 0 | AD44: 0 | AE44: 0 | AF44: 0 | AG44: 0 | AH44: 0 | AI44: 0 | AJ44: 0 | AK44: 0 | AL44: 0 | AM44: 0 | AN44: 0 | AO44: 8.25 | AP44: 0 | AQ44: 0 | AR44: 0 | AS44: 0 | AT44: 0 | AU44: 0 | AV44: 0 | AW44: 0 | AX44: 0 | AY44: 0 | AZ44: 0 | BA44: 0 | BB44: 8.25 | BC44: Y | BG44: -10 | BH44: Wheels & Wheel Components | BI44: Tires & Wheels | BJ44: Automotive Wheel Covers & Hub Caps | BK44: PRO-119076-12.0 | BN44: N | BO44: Seller Fulfilled | BP44: Delivery | BQ44: New Seller Saving | BR44: 3 | BW44: =if(OR(F44="SALE",F44="REFUNDED"),IFERROR(Vlookup(I44,'Listing SKU - Fill SKU Mapping'!A:C,3,false),"Map"),"") -> Keystone | BX44: =IF(OR(F44="SALE",F44="REFUNDED")=TRUE,iferror(Vlookup(I44,'Listing SKU - Fill SKU Mapping'!A:B,2,false),"Map"),"") -> IMP385X | BY44: =IF(OR(F44="SALE",F44="REFUNDED")=TRUE,iferror(Vlookup(I44,'Listing SKU - Fill SKU Mapping'!A:D,4,false),"Map"),"") -> 51.68 | BZ44: =If(BW44="Keystone",11.5,"") -> 11.5 | CA44: =IF(ISNUMBER(BY44)=TRUE,BY44+BZ44,"") -> 63.18 | CB44: =if(F44="SALE",V44-CA44,"") -> 29.8 | CC44: =if(F44="REFUNDED",iferror(Vlookup(I44,'Listing SKU - Fill SKU Mapping'!A:B,2,false),"Map"),"") | CD44: =if(F44="REFUNDED",iferror(Vlookup(I44,'Listing SKU - Fill SKU Mapping'!A:C,3,false),"Map"),"") | CE44: =TEXT(G44,"YYYY") -> 2025 | CF44: =TEXT(G44,"MMMM") -> April | CG44: =IF(AND((G44-CG$1)>=0,(G44-CG$1)<=6), "This Week",IF(AND((G44-CG$1)>=-7,(G44-CG$1)<=-1), "Last Week",""))
A45: 200012993559082 | B45: 1 | C45: 109011114761058 | D45: 1 | F45: REFUNDED | G45: 45775 | H45: 1 | I45: WM-FR-IMP-10043-18CH5DS | J45: 464567131070 | K45: Set of 4 18 inch Chrome Wheel Skins Covers Compatible with 15-18 Ford Edge Impostors for 10043 Wheel Series | L45: 2038710 | R45: Houston | S45: 77040 | U45: -108.23 | V45: -92.98 | W45: -7 | X45: 0 | Y45: 0 | Z45: -99.98 | AA45: 0 | AB45: 0 | AC45: 0 | AD45: 0 | AE45: 0 | AF45: 0 | AG45: 0 | AH45: 0 | AI45: 0 | AJ45: 0 | AK45: 0 | AL45: 0 | AM45: 0 | AN45: 0 | AO45: 0 | AP45: 0 | AQ45: 0 | AR45: 0 | AS45: 0 | AT45: -8.25 | AU45: 0 | AV45: 0 | AW45: 0 | AX45: 0 | AY45: 0 | AZ45: 0 | BA45: 0 | BB45: -8.25 | BC45: Y | BD45: Return Refund | BE45: 5010 | BH45: Wheels & Wheel Components | BI45: Tires & Wheels | BL45: 1000 | BM45: No Longer Wanted | BN45: N | BO45: Seller Fulfilled | BW45: =if(OR(F45="SALE",F45="REFUNDED"),IFERROR(Vlookup(I45,'Listing SKU - Fill SKU Mapping'!A:C,3,false),"Map"),"") -> Keystone | BX45: =IF(OR(F45="SALE",F45="REFUNDED")=TRUE,iferror(Vlookup(I45,'Listing SKU - Fill SKU Mapping'!A:B,2,false),"Map"),"") -> IMP385X | BY45: =IF(OR(F45="SALE",F45="REFUNDED")=TRUE,iferror(Vlookup(I45,'Listing SKU - Fill SKU Mapping'!A:D,4,false),"Map"),"") -> 51.68 | BZ45: =If(BW45="Keystone",11.5,"") -> 11.5 | CA45: =IF(ISNUMBER(BY45)=TRUE,BY45+BZ45,"") -> 63.18 | CB45: =if(F45="SALE",V45-CA45,"") | CC45: =if(F45="REFUNDED",iferror(Vlookup(I45,'Listing SKU - Fill SKU Mapping'!A:B,2,false),"Map"),"") -> IMP385X | CD45: =if(F45="REFUNDED",iferror(Vlookup(I45,'Listing SKU - Fill SKU Mapping'!A:C,3,false),"Map"),"") -> Keystone | CE45: =TEXT(G45,"YYYY") -> 2025 | CF45: =TEXT(G45,"MMMM") -> April | CG45: =IF(AND((G45-CG$1)>=0,(G45-CG$1)<=6), "This Week",IF(AND((G45-CG$1)>=-7,(G45-CG$1)<=-1), "Last Week",""))
A46: 200012986276514 | B46: 1 | C46: 109011841148324 | D46: 1 | F46: SALE | G46: 45775 | H46: 1 | I46: WM-FR-IMP-5908-17GB6S | J46: 460776240275 | K46: 17 Gloss Black Wheel Skins Set Compatible with 2019-2025 GMC Sierra 1500 2019-2021 Chevrolet Silverado 1500 2022-2025 Silverado 1500 Custom RST LT ZR2 High Country Impostors | L46: 2038710 | O46: OH | R46: Canton | S46: 44706 | T46: Marketplace standard | U46: 128.84 | V46: 112.51 | W46: 8.47 | X46: 7 | Y46: 120.98 | Z46: 0 | AA46: 0 | AB46: 0 | AC46: 0 | AD46: 0 | AE46: 0 | AF46: 0 | AG46: 0 | AH46: 0 | AI46: 0 | AJ46: 0 | AK46: 0 | AL46: 0 | AM46: 0 | AN46: 0 | AO46: 7.86 | AP46: 0 | AQ46: 0 | AR46: 0 | AS46: 0 | AT46: 0 | AU46: 0 | AV46: 0 | AW46: 0 | AX46: 0 | AY46: 0 | AZ46: 0 | BA46: 0 | BB46: 7.86 | BC46: Y | BG46: -12.1 | BH46: Wheels & Wheel Components | BI46: Tires & Wheels | BJ46: Automotive Wheel Covers & Hub Caps | BK46: PRO-119076-13.0 | BN46: N | BO46: Seller Fulfilled | BP46: Delivery | BQ46: New Seller Saving | BR46: 3.63 | BW46: =if(OR(F46="SALE",F46="REFUNDED"),IFERROR(Vlookup(I46,'Listing SKU - Fill SKU Mapping'!A:C,3,false),"Map"),"") -> Keystone | BX46: =IF(OR(F46="SALE",F46="REFUNDED")=TRUE,iferror(Vlookup(I46,'Listing SKU - Fill SKU Mapping'!A:B,2,false),"Map"),"") -> IMP436BLK | BY46: =IF(OR(F46="SALE",F46="REFUNDED")=TRUE,iferror(Vlookup(I46,'Listing SKU - Fill SKU Mapping'!A:D,4,false),"Map"),"") -> 61.14 | BZ46: =If(BW46="Keystone",11.5,"") -> 11.5 | CA46: =IF(ISNUMBER(BY46)=TRUE,BY46+BZ46,"") -> 72.64 | CB46: =if(F46="SALE",V46-CA46,"") -> 39.87 | CC46: =if(F46="REFUNDED",iferror(Vlookup(I46,'Listing SKU - Fill SKU Mapping'!A:B,2,false),"Map"),"") | CD46: =if(F46="REFUNDED",iferror(Vlookup(I46,'Listing SKU - Fill SKU Mapping'!A:C,3,false),"Map"),"") | CE46: =TEXT(G46,"YYYY") -> 2025 | CF46: =TEXT(G46,"MMMM") -> April | CG46: =IF(AND((G46-CG$1)>=0,(G46-CG$1)<=6), "This Week",IF(AND((G46-CG$1)>=-7,(G46-CG$1)<=-1), "Last Week",""))
A47: 200012934607014 | B47: 1 | C47: 109010168324919 | D47: 1 | F47: REFUNDED | G47: 45770 | H47: 1 | I47: WM-FR-IMP-DS7Z1007Q-17CC10S | J47: 460776230283 | K47: Set of 4 17 Chrome & Charcoal ABS Wheel Skins Compatible with 2017-2020 Ford Fusion SE 2015-2016 Ford Fusion Impostors for DS7Z1007Q Wheel Series | L47: 2038710 | R47: Roanoke | S47: 24013 | U47: -91.59 | V47: -80.89 | W47: -6.09 | X47: 0 | Y47: 0 | Z47: -86.98 | AA47: 0 | AB47: 0 | AC47: 0 | AD47: 0 | AE47: 0 | AF47: 0 | AG47: 0 | AH47: 0 | AI47: 0 | AJ47: 0 | AK47: 0 | AL47: 0 | AM47: 0 | AN47: 0 | AO47: 0 | AP47: 0 | AQ47: 0 | AR47: 0 | AS47: 0 | AT47: -4.61 | AU47: 0 | AV47: 0 | AW47: 0 | AX47: 0 | AY47: 0 | AZ47: 0 | BA47: 0 | BB47: -4.61 | BC47: Y | BD47: Return Refund | BE47: 5010 | BH47: Wheels & Wheel Components | BI47: Tires & Wheels | BL47: 1000 | BM47: No Longer Wanted | BN47: N | BO47: Seller Fulfilled | BW47: =if(OR(F47="SALE",F47="REFUNDED"),IFERROR(Vlookup(I47,'Listing SKU - Fill SKU Mapping'!A:C,3,false),"Map"),"") -> Keystone | BX47: =IF(OR(F47="SALE",F47="REFUNDED")=TRUE,iferror(Vlookup(I47,'Listing SKU - Fill SKU Mapping'!A:B,2,false),"Map"),"") -> IMP447CC | BY47: =IF(OR(F47="SALE",F47="REFUNDED")=TRUE,iferror(Vlookup(I47,'Listing SKU - Fill SKU Mapping'!A:D,4,false),"Map"),"") -> 67.46 | BZ47: =If(BW47="Keystone",11.5,"") -> 11.5 | CA47: =IF(ISNUMBER(BY47)=TRUE,BY47+BZ47,"") -> 78.96 | CB47: =if(F47="SALE",V47-CA47,"") | CC47: =if(F47="REFUNDED",iferror(Vlookup(I47,'Listing SKU - Fill SKU Mapping'!A:B,2,false),"Map"),"") -> IMP447CC | CD47: =if(F47="REFUNDED",iferror(Vlookup(I47,'Listing SKU - Fill SKU Mapping'!A:C,3,false),"Map"),"") -> Keystone | CE47: =TEXT(G47,"YYYY") -> 2025 | CF47: =TEXT(G47,"MMMM") -> April | CG47: =IF(AND((G47-CG$1)>=0,(G47-CG$1)<=6), "This Week",IF(AND((G47-CG$1)>=-7,(G47-CG$1)<=-1), "Last Week",""))
A48: 200012893572614 | B48: 1 | C48: 109008493702855 | D48: 1 | F48: ADJMNT | G48: 45767 | H48: 1 | I48: WM-FR-IMP-5712-18GB10S | J48: 460776230832 | K48: Set of 4 18 inch Gloss Black Wheel Skins Covers Compatible with 18-24 Chevrolet Equinox LS LT Premier 18-21 Equinox L 16-20 Impala Impostors for 5712 Wheel Series | L48: 2038710 | O48: SC | R48: Conway | S48: 29527 | T48: Marketplace standard | U48: 0 | V48: -10.81 | W48: 0 | X48: 0 | Y48: 0 | Z48: 0 | AA48: 0 | AB48: 0 | AC48: 0 | AD48: 0 | AE48: 0 | AF48: 0 | AG48: 0 | AH48: 0 | AI48: 0 | AJ48: 0 | AK48: 0 | AL48: 0 | AM48: 0 | AN48: 0 | AO48: 0 | AP48: 0 | AQ48: 0 | AR48: 0 | AS48: 0 | AT48: 0 | AU48: 0 | AV48: 0 | AW48: 0 | AX48: 0 | AY48: 0 | AZ48: 0 | BA48: 0 | BB48: 0 | BC48: Y | BD48: Walmart Return Shipping Charge | BE48: 5013 | BH48: Wheels & Wheel Components | BI48: Tires & Wheels | BN48: N | BO48: Seller Fulfilled | BW48: =if(OR(F48="SALE",F48="REFUNDED"),IFERROR(Vlookup(I48,'Listing SKU - Fill SKU Mapping'!A:C,3,false),"Map"),"") | BX48: =IF(OR(F48="SALE",F48="REFUNDED")=TRUE,iferror(Vlookup(I48,'Listing SKU - Fill SKU Mapping'!A:B,2,false),"Map"),"") | BY48: =IF(OR(F48="SALE",F48="REFUNDED")=TRUE,iferror(Vlookup(I48,'Listing SKU - Fill SKU Mapping'!A:D,4,false),"Map"),"") | BZ48: =If(BW48="Keystone",11.5,"") | CA48: =IF(ISNUMBER(BY48)=TRUE,BY48+BZ48,"") | CB48: =if(F48="SALE",V48-CA48,"") | CC48: =if(F48="REFUNDED",iferror(Vlookup(I48,'Listing SKU - Fill SKU Mapping'!A:B,2,false),"Map"),"") | CD48: =if(F48="REFUNDED",iferror(Vlookup(I48,'Listing SKU - Fill SKU Mapping'!A:C,3,false),"Map"),"") | CE48: =TEXT(G48,"YYYY") -> 2025 | CF48: =TEXT(G48,"MMMM") -> April | CG48: =IF(AND((G48-CG$1)>=0,(G48-CG$1)<=6), "This Week",IF(AND((G48-CG$1)>=-7,(G48-CG$1)<=-1), "Last Week",""))
A49: 200013232673504 | B49: 1 | C49: 109010583959963 | D49: 1 | F49: SALE | G49: 45762 | H49: 1 | I49: WM-FR-IMP-10010-16GB10S | J49: 460776236148 | K49: 16 inch Gloss Black ABS Wheel Skins Set Compatible with 2015-2018 Ford Focus SE & Impostors for 10010 Wheel Series | L49: 2038710 | O49: UT | R49: West Valley City | S49: 84119 | T49: Marketplace standard | U49: 107.23 | V49: 92.98 | W49: 7 | X49: 7 | Y49: 99.98 | Z49: 0 | AA49: 0 | AB49: 0 | AC49: 0 | AD49: 0 | AE49: 0 | AF49: 0 | AG49: 0 | AH49: 0 | AI49: 0 | AJ49: 0 | AK49: 0 | AL49: 0 | AM49: 0 | AN49: 0 | AO49: 7.25 | AP49: 0 | AQ49: 0 | AR49: 0 | AS49: 0 | AT49: 0 | AU49: 0 | AV49: 0 | AW49: 0 | AX49: 0 | AY49: 0 | AZ49: 0 | BA49: 0 | BB49: 7.25 | BC49: Y | BG49: -10 | BH49: Wheels & Wheel Components | BI49: Tires & Wheels | BJ49: Automotive Wheel Covers & Hub Caps | BK49: PRO-119076-11.0 | BN49: N | BO49: Seller Fulfilled | BP49: Delivery | BQ49: New Seller Saving | BR49: 3 | BW49: =if(OR(F49="SALE",F49="REFUNDED"),IFERROR(Vlookup(I49,'Listing SKU - Fill SKU Mapping'!A:C,3,false),"Map"),"") -> Keystone | BX49: =IF(OR(F49="SALE",F49="REFUNDED")=TRUE,iferror(Vlookup(I49,'Listing SKU - Fill SKU Mapping'!A:B,2,false),"Map"),"") -> IMP423BLK | BY49: =IF(OR(F49="SALE",F49="REFUNDED")=TRUE,iferror(Vlookup(I49,'Listing SKU - Fill SKU Mapping'!A:D,4,false),"Map"),"") -> 47.34 | BZ49: =If(BW49="Keystone",11.5,"") -> 11.5 | CA49: =IF(ISNUMBER(BY49)=TRUE,BY49+BZ49,"") -> 58.84 | CB49: =if(F49="SALE",V49-CA49,"") -> 34.14 | CC49: =if(F49="REFUNDED",iferror(Vlookup(I49,'Listing SKU - Fill SKU Mapping'!A:B,2,false),"Map"),"") | CD49: =if(F49="REFUNDED",iferror(Vlookup(I49,'Listing SKU - Fill SKU Mapping'!A:C,3,false),"Map"),"") | CE49: =TEXT(G49,"YYYY") -> 2025 | CF49: =TEXT(G49,"MMMM") -> April | CG49: =IF(AND((G49-CG$1)>=0,(G49-CG$1)<=6), "This Week",IF(AND((G49-CG$1)>=-7,(G49-CG$1)<=-1), "Last Week",""))
A50: 200013138757466 | B50: 1 | C50: 109008699469676 | D50: 1 | F50: SALE | G50: 45743 | H50: 1 | I50: WM-FR-IMP-5299-17CH5SP | J50: 460776241128 | K50: Set of 4 17 inch Chrome Wheel Skins Covers compatible with 07-14 Chevrolet Suburban 1500 Tahoe 07-13 Suburban 2500 Silverado 1500 Impostors for 5299 5421 Wheel Series | L50: 2038710 | O50: MI | R50: STANWOOD | S50: 49346 | T50: Marketplace standard | U50: 100.68 | V50: 88.33 | W50: 6.65 | X50: 7 | Y50: 94.98 | Z50: 0 | AA50: 0 | AB50: 0 | AC50: 0 | AD50: 0 | AE50: 0 | AF50: 0 | AG50: 0 | AH50: 0 | AI50: 0 | AJ50: 0 | AK50: 0 | AL50: 0 | AM50: 0 | AN50: 0 | AO50: 5.7 | AP50: 0 | AQ50: 0 | AR50: 0 | AS50: 0 | AT50: 0 | AU50: 0 | AV50: 0 | AW50: 0 | AX50: 0 | AY50: 0 | AZ50: 0 | BA50: 0 | BB50: 5.7 | BC50: Y | BG50: -9.5 | BH50: Wheels & Wheel Components | BI50: Tires & Wheels | BJ50: Automotive Wheel Covers & Hub Caps | BK50: PRO-119076-8.0 | BN50: N | BO50: Seller Fulfilled | BP50: Delivery | BQ50: New Seller Saving | BR50: 2.85 | BW50: =if(OR(F50="SALE",F50="REFUNDED"),IFERROR(Vlookup(I50,'Listing SKU - Fill SKU Mapping'!A:C,3,false),"Map"),"") -> Keystone | BX50: =IF(OR(F50="SALE",F50="REFUNDED")=TRUE,iferror(Vlookup(I50,'Listing SKU - Fill SKU Mapping'!A:B,2,false),"Map"),"") -> IMP347X | BY50: =IF(OR(F50="SALE",F50="REFUNDED")=TRUE,iferror(Vlookup(I50,'Listing SKU - Fill SKU Mapping'!A:D,4,false),"Map"),"") -> 43.79 | BZ50: =If(BW50="Keystone",11.5,"") -> 11.5 | CA50: =IF(ISNUMBER(BY50)=TRUE,BY50+BZ50,"") -> 55.29 | CB50: =if(F50="SALE",V50-CA50,"") -> 33.04 | CC50: =if(F50="REFUNDED",iferror(Vlookup(I50,'Listing SKU - Fill SKU Mapping'!A:B,2,false),"Map"),"") | CD50: =if(F50="REFUNDED",iferror(Vlookup(I50,'Listing SKU - Fill SKU Mapping'!A:C,3,false),"Map"),"") | CE50: =TEXT(G50,"YYYY") -> 2025 | CF50: =TEXT(G50,"MMMM") -> March | CG50: =IF(AND((G50-CG$1)>=0,(G50-CG$1)<=6), "This Week",IF(AND((G50-CG$1)>=-7,(G50-CG$1)<=-1), "Last Week",""))
A51: 200013116006538 | B51: 2 | C51: 109010167259537 | D51: 2 | F51: SALE | G51: 45757 | H51: 1 | I51: WM-FR-IMP-2521-18GB5SP | J51: 460776231082 | K51: Set of 4 18 inch Gloss Black Wheel Skins Covers Compatible with 15-17 Dodge Charger SXT 15-23 Dodge Challenger SXT 18 Charger SXT Plus Impostors for 2521 Wheel Series | L51: 2038710 | O51: VA | R51: Lyndhurst | S51: 22952 | T51: Marketplace standard | U51: 128.44 | V51: 113.44 | W51: 8.54 | X51: 7 | Y51: 121.98 | Z51: 0 | AA51: 0 | AB51: 0 | AC51: 0 | AD51: 0 | AE51: 0 | AF51: 0 | AG51: 0 | AH51: 0 | AI51: 0 | AJ51: 0 | AK51: 0 | AL51: 0 | AM51: 0 | AN51: 0 | AO51: 6.46 | AP51: 0 | AQ51: 0 | AR51: 0 | AS51: 0 | AT51: 0 | AU51: 0 | AV51: 0 | AW51: 0 | AX51: 0 | AY51: 0 | AZ51: 0 | BA51: 0 | BB51: 6.46 | BC51: Y | BG51: -12.2 | BH51: Wheels & Wheel Components | BI51: Tires & Wheels | BJ51: Automotive Wheel Covers & Hub Caps | BK51: PRO-119076-10.0 | BN51: N | BO51: Seller Fulfilled | BP51: Delivery | BQ51: New Seller Saving | BR51: 3.66 | BW51: =if(OR(F51="SALE",F51="REFUNDED"),IFERROR(Vlookup(I51,'Listing SKU - Fill SKU Mapping'!A:C,3,false),"Map"),"") -> Keystone | BX51: =IF(OR(F51="SALE",F51="REFUNDED")=TRUE,iferror(Vlookup(I51,'Listing SKU - Fill SKU Mapping'!A:B,2,false),"Map"),"") -> IMP401BLK | BY51: =IF(OR(F51="SALE",F51="REFUNDED")=TRUE,iferror(Vlookup(I51,'Listing SKU - Fill SKU Mapping'!A:D,4,false),"Map"),"") -> 62.33 | BZ51: =If(BW51="Keystone",11.5,"") -> 11.5 | CA51: =IF(ISNUMBER(BY51)=TRUE,BY51+BZ51,"") -> 73.83 | CB51: =if(F51="SALE",V51-CA51,"") -> 39.61 | CC51: =if(F51="REFUNDED",iferror(Vlookup(I51,'Listing SKU - Fill SKU Mapping'!A:B,2,false),"Map"),"") | CD51: =if(F51="REFUNDED",iferror(Vlookup(I51,'Listing SKU - Fill SKU Mapping'!A:C,3,false),"Map"),"") | CE51: =TEXT(G51,"YYYY") -> 2025 | CF51: =TEXT(G51,"MMMM") -> April | CG51: =IF(AND((G51-CG$1)>=0,(G51-CG$1)<=6), "This Week",IF(AND((G51-CG$1)>=-7,(G51-CG$1)<=-1), "Last Week",""))
A52: 200013099169767 | B52: 2 | C52: 109009128533166 | D52: 2 | F52: SALE | G52: 45748 | H52: 1 | I52: WM-FR-IMP-2511-17GB10S | J52: 460776233253 | K52: 17 inch Gloss Black ABS Wheel Skins Set Compatible with 2015-2017 Chrysler 200 Limited & Impostors for 2511 Wheel Series | L52: 2038710 | O52: IN | R52: Hammond | S52: 46324 | T52: Marketplace standard | U52: 104.84 | V52: 91.12 | W52: 6.86 | X52: 7 | Y52: 97.98 | Z52: 0 | AA52: 0 | AB52: 0 | AC52: 0 | AD52: 0 | AE52: 0 | AF52: 0 | AG52: 0 | AH52: 0 | AI52: 0 | AJ52: 0 | AK52: 0 | AL52: 0 | AM52: 0 | AN52: 0 | AO52: 6.86 | AP52: 0 | AQ52: 0 | AR52: 0 | AS52: 0 | AT52: 0 | AU52: 0 | AV52: 0 | AW52: 0 | AX52: 0 | AY52: 0 | AZ52: 0 | BA52: 0 | BB52: 6.86 | BC52: Y | BG52: -9.8 | BH52: Wheels & Wheel Components | BI52: Tires & Wheels | BJ52: Automotive Wheel Covers & Hub Caps | BK52: PRO-119076-9.0 | BN52: N | BO52: Seller Fulfilled | BP52: Delivery | BQ52: New Seller Saving | BR52: 2.94 | BW52: =if(OR(F52="SALE",F52="REFUNDED"),IFERROR(Vlookup(I52,'Listing SKU - Fill SKU Mapping'!A:C,3,false),"Map"),"") -> Keystone | BX52: =IF(OR(F52="SALE",F52="REFUNDED")=TRUE,iferror(Vlookup(I52,'Listing SKU - Fill SKU Mapping'!A:B,2,false),"Map"),"") -> IMP388BLK | BY52: =IF(OR(F52="SALE",F52="REFUNDED")=TRUE,iferror(Vlookup(I52,'Listing SKU - Fill SKU Mapping'!A:D,4,false),"Map"),"") -> 45.76 | BZ52: =If(BW52="Keystone",11.5,"") -> 11.5 | CA52: =IF(ISNUMBER(BY52)=TRUE,BY52+BZ52,"") -> 57.26 | CB52: =if(F52="SALE",V52-CA52,"") -> 33.86 | CC52: =if(F52="REFUNDED",iferror(Vlookup(I52,'Listing SKU - Fill SKU Mapping'!A:B,2,false),"Map"),"") | CD52: =if(F52="REFUNDED",iferror(Vlookup(I52,'Listing SKU - Fill SKU Mapping'!A:C,3,false),"Map"),"") | CE52: =TEXT(G52,"YYYY") -> 2025 | CF52: =TEXT(G52,"MMMM") -> April | CG52: =IF(AND((G52-CG$1)>=0,(G52-CG$1)<=6), "This Week",IF(AND((G52-CG$1)>=-7,(G52-CG$1)<=-1), "Last Week",""))
A53: 200013083775008 | B53: 4 | C53: 109009126618420 | D53: 4 | F53: SALE | G53: 45748 | H53: 1 | I53: WM-FR-IMP-5934-18CH6SS | J53: 460776276861 | K53: 18 inch Chrome ABS Wheel Skins Set Compatible with 2019-2025 Chevrolet Blazer & Impostors for 5934 Wheel Series | L53: 2038710 | O53: IN | R53: Ossian | S53: 46777 | T53: Marketplace standard | U53: 95.21 | V53: 82.75 | W53: 6.23 | X53: 7 | Y53: 88.98 | Z53: 0 | AA53: 0 | AB53: 0 | AC53: 0 | AD53: 0 | AE53: 0 | AF53: 0 | AG53: 0 | AH53: 0 | AI53: 0 | AJ53: 0 | AK53: 0 | AL53: 0 | AM53: 0 | AN53: 0 | AO53: 6.23 | AP53: 0 | AQ53: 0 | AR53: 0 | AS53: 0 | AT53: 0 | AU53: 0 | AV53: 0 | AW53: 0 | AX53: 0 | AY53: 0 | AZ53: 0 | BA53: 0 | BB53: 6.23 | BC53: Y | BG53: -8.9 | BH53: Wheels & Wheel Components | BI53: Tires & Wheels | BJ53: Automotive Rims | BK53: PRO-119076-9.0 | BN53: N | BO53: Seller Fulfilled | BP53: Delivery | BQ53: New Seller Saving | BR53: 2.67 | BW53: =if(OR(F53="SALE",F53="REFUNDED"),IFERROR(Vlookup(I53,'Listing SKU - Fill SKU Mapping'!A:C,3,false),"Map"),"") -> Keystone | BX53: =IF(OR(F53="SALE",F53="REFUNDED")=TRUE,iferror(Vlookup(I53,'Listing SKU - Fill SKU Mapping'!A:B,2,false),"Map"),"") -> IMP438X | BY53: =IF(OR(F53="SALE",F53="REFUNDED")=TRUE,iferror(Vlookup(I53,'Listing SKU - Fill SKU Mapping'!A:D,4,false),"Map"),"") -> 69.83 | BZ53: =If(BW53="Keystone",11.5,"") -> 11.5 | CA53: =IF(ISNUMBER(BY53)=TRUE,BY53+BZ53,"") -> 81.33 | CB53: =if(F53="SALE",V53-CA53,"") -> 1.42 | CC53: =if(F53="REFUNDED",iferror(Vlookup(I53,'Listing SKU - Fill SKU Mapping'!A:B,2,false),"Map"),"") | CD53: =if(F53="REFUNDED",iferror(Vlookup(I53,'Listing SKU - Fill SKU Mapping'!A:C,3,false),"Map"),"") | CE53: =TEXT(G53,"YYYY") -> 2025 | CF53: =TEXT(G53,"MMMM") -> April | CG53: =IF(AND((G53-CG$1)>=0,(G53-CG$1)<=6), "This Week",IF(AND((G53-CG$1)>=-7,(G53-CG$1)<=-1), "Last Week",""))
A54: 200013083775008 | B54: 4 | C54: 109009126618420 | D54: 4 | F54: REFUNDED | G54: 45764 | H54: 1 | I54: WM-FR-IMP-5934-18CH6SS | J54: 460776276861 | K54: 18 inch Chrome ABS Wheel Skins Set Compatible with 2019-2025 Chevrolet Blazer & Impostors for 5934 Wheel Series | L54: 2038710 | R54: Ossian | S54: 46777 | U54: -95.21 | V54: -82.75 | W54: -6.23 | X54: 0 | Y54: 0 | Z54: -88.98 | AA54: 0 | AB54: 0 | AC54: 0 | AD54: 0 | AE54: 0 | AF54: 0 | AG54: 0 | AH54: 0 | AI54: 0 | AJ54: 0 | AK54: 0 | AL54: 0 | AM54: 0 | AN54: 0 | AO54: 0 | AP54: 0 | AQ54: 0 | AR54: 0 | AS54: 0 | AT54: -6.23 | AU54: 0 | AV54: 0 | AW54: 0 | AX54: 0 | AY54: 0 | AZ54: 0 | BA54: 0 | BB54: -6.23 | BC54: Y | BD54: Return Refund | BE54: 5010 | BH54: Wheels & Wheel Components | BI54: Tires & Wheels | BL54: 1000 | BM54: No Longer Wanted | BN54: N | BO54: Seller Fulfilled | BW54: =if(OR(F54="SALE",F54="REFUNDED"),IFERROR(Vlookup(I54,'Listing SKU - Fill SKU Mapping'!A:C,3,false),"Map"),"") -> Keystone | BX54: =IF(OR(F54="SALE",F54="REFUNDED")=TRUE,iferror(Vlookup(I54,'Listing SKU - Fill SKU Mapping'!A:B,2,false),"Map"),"") -> IMP438X | BY54: =IF(OR(F54="SALE",F54="REFUNDED")=TRUE,iferror(Vlookup(I54,'Listing SKU - Fill SKU Mapping'!A:D,4,false),"Map"),"") -> 69.83 | BZ54: =If(BW54="Keystone",11.5,"") -> 11.5 | CA54: =IF(ISNUMBER(BY54)=TRUE,BY54+BZ54,"") -> 81.33 | CB54: =if(F54="SALE",V54-CA54,"") | CC54: =if(F54="REFUNDED",iferror(Vlookup(I54,'Listing SKU - Fill SKU Mapping'!A:B,2,false),"Map"),"") -> IMP438X | CD54: =if(F54="REFUNDED",iferror(Vlookup(I54,'Listing SKU - Fill SKU Mapping'!A:C,3,false),"Map"),"") -> Keystone | CE54: =TEXT(G54,"YYYY") -> 2025 | CF54: =TEXT(G54,"MMMM") -> April | CG54: =IF(AND((G54-CG$1)>=0,(G54-CG$1)<=6), "This Week",IF(AND((G54-CG$1)>=-7,(G54-CG$1)<=-1), "Last Week",""))
A55: 200013051814334 | B55: 1 | C55: 109008389627163 | D55: 1 | F55: SALE | G55: 45741 | H55: 1 | I55: WM-FR-IMP-DS7Z1007Q-17CC10S | J55: 460776230283 | K55: Set of 4 17 Chrome & Charcoal ABS Wheel Skins Compatible with 2017-2020 Ford Fusion SE 2015-2016 Ford Fusion Impostors for DS7Z1007Q Wheel Series | L55: 2038710 | O55: VA | R55: Ashland | S55: 23005 | T55: Marketplace standard | U55: 92.2 | V55: 80.89 | W55: 6.09 | X55: 7 | Y55: 86.98 | Z55: 0 | AA55: 0 | AB55: 0 | AC55: 0 | AD55: 0 | AE55: 0 | AF55: 0 | AG55: 0 | AH55: 0 | AI55: 0 | AJ55: 0 | AK55: 0 | AL55: 0 | AM55: 0 | AN55: 0 | AO55: 5.22 | AP55: 0 | AQ55: 0 | AR55: 0 | AS55: 0 | AT55: 0 | AU55: 0 | AV55: 0 | AW55: 0 | AX55: 0 | AY55: 0 | AZ55: 0 | BA55: 0 | BB55: 5.22 | BC55: Y | BG55: -8.7 | BH55: Wheels & Wheel Components | BI55: Tires & Wheels | BJ55: Automotive Wheel Covers & Hub Caps | BK55: PRO-119076-8.0 | BN55: N | BO55: Seller Fulfilled | BP55: Delivery | BQ55: New Seller Saving | BR55: 2.61 | BW55: =if(OR(F55="SALE",F55="REFUNDED"),IFERROR(Vlookup(I55,'Listing SKU - Fill SKU Mapping'!A:C,3,false),"Map"),"") -> Keystone | BX55: =IF(OR(F55="SALE",F55="REFUNDED")=TRUE,iferror(Vlookup(I55,'Listing SKU - Fill SKU Mapping'!A:B,2,false),"Map"),"") -> IMP447CC | BY55: =IF(OR(F55="SALE",F55="REFUNDED")=TRUE,iferror(Vlookup(I55,'Listing SKU - Fill SKU Mapping'!A:D,4,false),"Map"),"") -> 67.46 | BZ55: =If(BW55="Keystone",11.5,"") -> 11.5 | CA55: =IF(ISNUMBER(BY55)=TRUE,BY55+BZ55,"") -> 78.96 | CB55: =if(F55="SALE",V55-CA55,"") -> 1.93 | CC55: =if(F55="REFUNDED",iferror(Vlookup(I55,'Listing SKU - Fill SKU Mapping'!A:B,2,false),"Map"),"") | CD55: =if(F55="REFUNDED",iferror(Vlookup(I55,'Listing SKU - Fill SKU Mapping'!A:C,3,false),"Map"),"") | CE55: =TEXT(G55,"YYYY") -> 2025 | CF55: =TEXT(G55,"MMMM") -> March | CG55: =IF(AND((G55-CG$1)>=0,(G55-CG$1)<=6), "This Week",IF(AND((G55-CG$1)>=-7,(G55-CG$1)<=-1), "Last Week",""))
A56: 200013051814334 | B56: 1 | C56: 109008389627163 | D56: 1 | F56: REFUNDED | G56: 45743 | H56: 1 | I56: WM-FR-IMP-DS7Z1007Q-17CC10S | J56: 460776230283 | K56: Set of 4 17 Chrome & Charcoal ABS Wheel Skins Compatible with 2017-2020 Ford Fusion SE 2015-2016 Ford Fusion Impostors for DS7Z1007Q Wheel Series | L56: 2038710 | R56: Ashland | S56: 23005 | U56: -92.2 | V56: -80.89 | W56: -6.09 | X56: 0 | Y56: 0 | Z56: -86.98 | AA56: 0 | AB56: 0 | AC56: 0 | AD56: 0 | AE56: 0 | AF56: 0 | AG56: 0 | AH56: 0 | AI56: 0 | AJ56: 0 | AK56: 0 | AL56: 0 | AM56: 0 | AN56: 0 | AO56: 0 | AP56: 0 | AQ56: 0 | AR56: 0 | AS56: 0 | AT56: -5.22 | AU56: 0 | AV56: 0 | AW56: 0 | AX56: 0 | AY56: 0 | AZ56: 0 | BA56: 0 | BB56: -5.22 | BC56: Y | BD56: Return Refund | BE56: 5010 | BH56: Wheels & Wheel Components | BI56: Tires & Wheels | BL56: 1018 | BM56: Not as described/pictured | BN56: N | BO56: Seller Fulfilled | BW56: =if(OR(F56="SALE",F56="REFUNDED"),IFERROR(Vlookup(I56,'Listing SKU - Fill SKU Mapping'!A:C,3,false),"Map"),"") -> Keystone | BX56: =IF(OR(F56="SALE",F56="REFUNDED")=TRUE,iferror(Vlookup(I56,'Listing SKU - Fill SKU Mapping'!A:B,2,false),"Map"),"") -> IMP447CC | BY56: =IF(OR(F56="SALE",F56="REFUNDED")=TRUE,iferror(Vlookup(I56,'Listing SKU - Fill SKU Mapping'!A:D,4,false),"Map"),"") -> 67.46 | BZ56: =If(BW56="Keystone",11.5,"") -> 11.5 | CA56: =IF(ISNUMBER(BY56)=TRUE,BY56+BZ56,"") -> 78.96 | CB56: =if(F56="SALE",V56-CA56,"") | CC56: =if(F56="REFUNDED",iferror(Vlookup(I56,'Listing SKU - Fill SKU Mapping'!A:B,2,false),"Map"),"") -> IMP447CC | CD56: =if(F56="REFUNDED",iferror(Vlookup(I56,'Listing SKU - Fill SKU Mapping'!A:C,3,false),"Map"),"") -> Keystone | CE56: =TEXT(G56,"YYYY") -> 2025 | CF56: =TEXT(G56,"MMMM") -> March | CG56: =IF(AND((G56-CG$1)>=0,(G56-CG$1)<=6), "This Week",IF(AND((G56-CG$1)>=-7,(G56-CG$1)<=-1), "Last Week",""))
A57: 200013051814334 | B57: 1 | C57: 109008389627163 | D57: 1 | F57: ADJMNT | G57: 45760 | H57: 1 | I57: WM-FR-IMP-DS7Z1007Q-17CC10S | J57: 460776230283 | K57: Set of 4 17 Chrome & Charcoal ABS Wheel Skins Compatible with 2017-2020 Ford Fusion SE 2015-2016 Ford Fusion Impostors for DS7Z1007Q Wheel Series | L57: 2038710 | O57: VA | R57: Ashland | S57: 23005 | T57: Marketplace standard | U57: 0 | V57: -8.89 | W57: 0 | X57: 0 | Y57: 0 | Z57: 0 | AA57: 0 | AB57: 0 | AC57: 0 | AD57: 0 | AE57: 0 | AF57: 0 | AG57: 0 | AH57: 0 | AI57: 0 | AJ57: 0 | AK57: 0 | AL57: 0 | AM57: 0 | AN57: 0 | AO57: 0 | AP57: 0 | AQ57: 0 | AR57: 0 | AS57: 0 | AT57: 0 | AU57: 0 | AV57: 0 | AW57: 0 | AX57: 0 | AY57: 0 | AZ57: 0 | BA57: 0 | BB57: 0 | BC57: Y | BD57: Walmart Return Shipping Charge | BE57: 5013 | BH57: Wheels & Wheel Components | BI57: Tires & Wheels | BN57: N | BO57: Seller Fulfilled | BW57: =if(OR(F57="SALE",F57="REFUNDED"),IFERROR(Vlookup(I57,'Listing SKU - Fill SKU Mapping'!A:C,3,false),"Map"),"") | BX57: =IF(OR(F57="SALE",F57="REFUNDED")=TRUE,iferror(Vlookup(I57,'Listing SKU - Fill SKU Mapping'!A:B,2,false),"Map"),"") | BY57: =IF(OR(F57="SALE",F57="REFUNDED")=TRUE,iferror(Vlookup(I57,'Listing SKU - Fill SKU Mapping'!A:D,4,false),"Map"),"") | BZ57: =If(BW57="Keystone",11.5,"") | CA57: =IF(ISNUMBER(BY57)=TRUE,BY57+BZ57,"") | CB57: =if(F57="SALE",V57-CA57,"") | CC57: =if(F57="REFUNDED",iferror(Vlookup(I57,'Listing SKU - Fill SKU Mapping'!A:B,2,false),"Map"),"") | CD57: =if(F57="REFUNDED",iferror(Vlookup(I57,'Listing SKU - Fill SKU Mapping'!A:C,3,false),"Map"),"") | CE57: =TEXT(G57,"YYYY") -> 2025 | CF57: =TEXT(G57,"MMMM") -> April | CG57: =IF(AND((G57-CG$1)>=0,(G57-CG$1)<=6), "This Week",IF(AND((G57-CG$1)>=-7,(G57-CG$1)<=-1), "Last Week",""))
A58: 200013041673912 | B58: 1 | C58: 109008919231712 | D58: 1 | F58: SALE | G58: 45748 | H58: 1 | I58: WM-FR-IMP-62593-17CH5DS | J58: 460776231143 | K58: 17 inch Chrome ABS Wheel Skins Set Compatible with 2013-2018 Nissan Altima & Impostors for 62593 Wheel Series | L58: 2038710 | O58: AR | R58: Little Rock | S58: 72204 | T58: Marketplace standard | U58: 106.43 | V58: 91.12 | W58: 6.86 | X58: 7 | Y58: 97.98 | Z58: 0 | AA58: 0 | AB58: 0 | AC58: 0 | AD58: 0 | AE58: 0 | AF58: 0 | AG58: 0 | AH58: 0 | AI58: 0 | AJ58: 0 | AK58: 0 | AL58: 0 | AM58: 0 | AN58: 0 | AO58: 8.45 | AP58: 0 | AQ58: 0 | AR58: 0 | AS58: 0 | AT58: 0 | AU58: 0 | AV58: 0 | AW58: 0 | AX58: 0 | AY58: 0 | AZ58: 0 | BA58: 0 | BB58: 8.45 | BC58: Y | BG58: -9.8 | BH58: Wheels & Wheel Components | BI58: Tires & Wheels | BJ58: Automotive Wheel Covers & Hub Caps | BK58: PRO-119076-9.0 | BN58: N | BO58: Seller Fulfilled | BP58: Delivery | BQ58: New Seller Saving | BR58: 2.94 | BW58: =if(OR(F58="SALE",F58="REFUNDED"),IFERROR(Vlookup(I58,'Listing SKU - Fill SKU Mapping'!A:C,3,false),"Map"),"") -> Keystone | BX58: =IF(OR(F58="SALE",F58="REFUNDED")=TRUE,iferror(Vlookup(I58,'Listing SKU - Fill SKU Mapping'!A:B,2,false),"Map"),"") -> IMP378X | BY58: =IF(OR(F58="SALE",F58="REFUNDED")=TRUE,iferror(Vlookup(I58,'Listing SKU - Fill SKU Mapping'!A:D,4,false),"Map"),"") -> 45.36 | BZ58: =If(BW58="Keystone",11.5,"") -> 11.5 | CA58: =IF(ISNUMBER(BY58)=TRUE,BY58+BZ58,"") -> 56.86 | CB58: =if(F58="SALE",V58-CA58,"") -> 34.26 | CC58: =if(F58="REFUNDED",iferror(Vlookup(I58,'Listing SKU - Fill SKU Mapping'!A:B,2,false),"Map"),"") | CD58: =if(F58="REFUNDED",iferror(Vlookup(I58,'Listing SKU - Fill SKU Mapping'!A:C,3,false),"Map"),"") | CE58: =TEXT(G58,"YYYY") -> 2025 | CF58: =TEXT(G58,"MMMM") -> April | CG58: =IF(AND((G58-CG$1)>=0,(G58-CG$1)<=6), "This Week",IF(AND((G58-CG$1)>=-7,(G58-CG$1)<=-1), "Last Week",""))
A59: 200013041673912 | B59: 1 | C59: 109008919231712 | D59: 1 | F59: REFUNDED | G59: 45762 | H59: 1 | I59: WM-FR-IMP-62593-17CH5DS | J59: 460776231143 | K59: 17 inch Chrome ABS Wheel Skins Set Compatible with 2013-2018 Nissan Altima & Impostors for 62593 Wheel Series | L59: 2038710 | R59: Little Rock | S59: 72204 | U59: -106.43 | V59: -91.12 | W59: -6.86 | X59: 0 | Y59: 0 | Z59: -97.98 | AA59: 0 | AB59: 0 | AC59: 0 | AD59: 0 | AE59: 0 | AF59: 0 | AG59: 0 | AH59: 0 | AI59: 0 | AJ59: 0 | AK59: 0 | AL59: 0 | AM59: 0 | AN59: 0 | AO59: 0 | AP59: 0 | AQ59: 0 | AR59: 0 | AS59: 0 | AT59: -8.45 | AU59: 0 | AV59: 0 | AW59: 0 | AX59: 0 | AY59: 0 | AZ59: 0 | BA59: 0 | BB59: -8.45 | BC59: Y | BD59: Return Refund | BE59: 5010 | BH59: Wheels & Wheel Components | BI59: Tires & Wheels | BL59: 1016 | BM59: Incorrect item received | BN59: N | BO59: Seller Fulfilled | BW59: =if(OR(F59="SALE",F59="REFUNDED"),IFERROR(Vlookup(I59,'Listing SKU - Fill SKU Mapping'!A:C,3,false),"Map"),"") -> Keystone | BX59: =IF(OR(F59="SALE",F59="REFUNDED")=TRUE,iferror(Vlookup(I59,'Listing SKU - Fill SKU Mapping'!A:B,2,false),"Map"),"") -> IMP378X | BY59: =IF(OR(F59="SALE",F59="REFUNDED")=TRUE,iferror(Vlookup(I59,'Listing SKU - Fill SKU Mapping'!A:D,4,false),"Map"),"") -> 45.36 | BZ59: =If(BW59="Keystone",11.5,"") -> 11.5 | CA59: =IF(ISNUMBER(BY59)=TRUE,BY59+BZ59,"") -> 56.86 | CB59: =if(F59="SALE",V59-CA59,"") | CC59: =if(F59="REFUNDED",iferror(Vlookup(I59,'Listing SKU - Fill SKU Mapping'!A:B,2,false),"Map"),"") -> IMP378X | CD59: =if(F59="REFUNDED",iferror(Vlookup(I59,'Listing SKU - Fill SKU Mapping'!A:C,3,false),"Map"),"") -> Keystone | CE59: =TEXT(G59,"YYYY") -> 2025 | CF59: =TEXT(G59,"MMMM") -> April | CG59: =IF(AND((G59-CG$1)>=0,(G59-CG$1)<=6), "This Week",IF(AND((G59-CG$1)>=-7,(G59-CG$1)<=-1), "Last Week",""))
A60: 200013036979100 | B60: 1 | C60: 109009960845050 | D60: 1 | F60: SALE | G60: 45756 | H60: 1 | I60: WM-FR-IMP-8130-17CH12H | J60: 460776235257 | K60: Set of 4 17 inch Chrome Wheel Skins Covers compatible with 19-25 Chevrolet Silverado 1500 WT LT RST ZR2 Trail Boss High Country Custom LTZ PPV LTD Impostors for 8130 Wheel Series | L60: 2038710 | O60: MN | R60: Saint Cloud | S60: 56301 | T60: Marketplace standard | U60: 132.82 | V60: 114.37 | W60: 8.61 | X60: 7 | Y60: 122.98 | Z60: 0 | AA60: 0 | AB60: 0 | AC60: 0 | AD60: 0 | AE60: 0 | AF60: 0 | AG60: 0 | AH60: 0 | AI60: 0 | AJ60: 0 | AK60: 0 | AL60: 0 | AM60: 0 | AN60: 0 | AO60: 9.84 | AP60: 0 | AQ60: 0 | AR60: 0 | AS60: 0 | AT60: 0 | AU60: 0 | AV60: 0 | AW60: 0 | AX60: 0 | AY60: 0 | AZ60: 0 | BA60: 0 | BB60: 9.84 | BC60: Y | BG60: -12.3 | BH60: Wheels & Wheel Components | BI60: Tires & Wheels | BJ60: Automotive Wheel Covers & Hub Caps | BK60: PRO-119076-10.0 | BN60: N | BO60: Seller Fulfilled | BP60: Delivery | BQ60: New Seller Saving | BR60: 3.69 | BW60: =if(OR(F60="SALE",F60="REFUNDED"),IFERROR(Vlookup(I60,'Listing SKU - Fill SKU Mapping'!A:C,3,false),"Map"),"") -> Keystone | BX60: =IF(OR(F60="SALE",F60="REFUNDED")=TRUE,iferror(Vlookup(I60,'Listing SKU - Fill SKU Mapping'!A:B,2,false),"Map"),"") -> IMP100X | BY60: =IF(OR(F60="SALE",F60="REFUNDED")=TRUE,iferror(Vlookup(I60,'Listing SKU - Fill SKU Mapping'!A:D,4,false),"Map"),"") -> 62.72 | BZ60: =If(BW60="Keystone",11.5,"") -> 11.5 | CA60: =IF(ISNUMBER(BY60)=TRUE,BY60+BZ60,"") -> 74.22 | CB60: =if(F60="SALE",V60-CA60,"") -> 40.15 | CC60: =if(F60="REFUNDED",iferror(Vlookup(I60,'Listing SKU - Fill SKU Mapping'!A:B,2,false),"Map"),"") | CD60: =if(F60="REFUNDED",iferror(Vlookup(I60,'Listing SKU - Fill SKU Mapping'!A:C,3,false),"Map"),"") | CE60: =TEXT(G60,"YYYY") -> 2025 | CF60: =TEXT(G60,"MMMM") -> April | CG60: =IF(AND((G60-CG$1)>=0,(G60-CG$1)<=6), "This Week",IF(AND((G60-CG$1)>=-7,(G60-CG$1)<=-1), "Last Week",""))
A61: 200013033131335 | B61: 1 | C61: 109010479870296 | D61: 1 | F61: SALE | G61: 45761 | H61: 1 | I61: WM-FR-IMP-3857-17GB9S | J61: 460776235301 | K61: 17 Gloss Black ABS Wheel Skins Set Compatible with 2017-2023 Ford F-150 Limited King Ranch XLT Lariat Platinum Raptor XL SSV Police Responder & 2013 F-150 Impostors 3857 3996 | L61: 2038710 | O61: CA | R61: Bakersfield | S61: 93312 | T61: Marketplace standard | U61: 112.56 | V61: 96.7 | W61: 7.28 | X61: 7 | Y61: 103.98 | Z61: 0 | AA61: 0 | AB61: 0 | AC61: 0 | AD61: 0 | AE61: 0 | AF61: 0 | AG61: 0 | AH61: 0 | AI61: 0 | AJ61: 0 | AK61: 0 | AL61: 0 | AM61: 0 | AN61: 0 | AO61: 8.58 | AP61: 0 | AQ61: 0 | AR61: 0 | AS61: 0 | AT61: 0 | AU61: 0 | AV61: 0 | AW61: 0 | AX61: 0 | AY61: 0 | AZ61: 0 | BA61: 0 | BB61: 8.58 | BC61: Y | BG61: -10.4 | BH61: Wheels & Wheel Components | BI61: Tires & Wheels | BJ61: Automotive Wheel Covers & Hub Caps | BK61: PRO-119076-11.0 | BN61: N | BO61: Seller Fulfilled | BP61: Delivery | BQ61: New Seller Saving | BR61: 3.12 | BW61: =if(OR(F61="SALE",F61="REFUNDED"),IFERROR(Vlookup(I61,'Listing SKU - Fill SKU Mapping'!A:C,3,false),"Map"),"") -> Keystone | BX61: =IF(OR(F61="SALE",F61="REFUNDED")=TRUE,iferror(Vlookup(I61,'Listing SKU - Fill SKU Mapping'!A:B,2,false),"Map"),"") -> IMP80BLK | BY61: =IF(OR(F61="SALE",F61="REFUNDED")=TRUE,iferror(Vlookup(I61,'Listing SKU - Fill SKU Mapping'!A:D,4,false),"Map"),"") -> 49.71 | BZ61: =If(BW61="Keystone",11.5,"") -> 11.5 | CA61: =IF(ISNUMBER(BY61)=TRUE,BY61+BZ61,"") -> 61.21 | CB61: =if(F61="SALE",V61-CA61,"") -> 35.49 | CC61: =if(F61="REFUNDED",iferror(Vlookup(I61,'Listing SKU - Fill SKU Mapping'!A:B,2,false),"Map"),"") | CD61: =if(F61="REFUNDED",iferror(Vlookup(I61,'Listing SKU - Fill SKU Mapping'!A:C,3,false),"Map"),"") | CE61: =TEXT(G61,"YYYY") -> 2025 | CF61: =TEXT(G61,"MMMM") -> April | CG61: =IF(AND((G61-CG$1)>=0,(G61-CG$1)<=6), "This Week",IF(AND((G61-CG$1)>=-7,(G61-CG$1)<=-1), "Last Week",""))
A62: 200012953187165 | B62: 1 | C62: 109009751344900 | D62: 1 | F62: SALE | G62: 45754 | H62: 1 | I62: WM-FR-IMP-2521-18GB5SP | J62: 460776231082 | K62: Set of 4 18 inch Gloss Black Wheel Skins Covers Compatible with 15-17 Dodge Charger SXT 15-23 Dodge Challenger SXT 18 Charger SXT Plus Impostors for 2521 Wheel Series | L62: 2038710 | O62: PA | R62: Carnegie | S62: 15106 | T62: Marketplace standard | U62: 129.3 | V62: 109.78 | W62: 12.2 | X62: 10 | Y62: 121.98 | Z62: 0 | AA62: 0 | AB62: 0 | AC62: 0 | AD62: 0 | AE62: 0 | AF62: 0 | AG62: 0 | AH62: 0 | AI62: 0 | AJ62: 0 | AK62: 0 | AL62: 0 | AM62: 0 | AN62: 0 | AO62: 7.32 | AP62: 0 | AQ62: 0 | AR62: 0 | AS62: 0 | AT62: 0 | AU62: 0 | AV62: 0 | AW62: 0 | AX62: 0 | AY62: 0 | AZ62: 0 | BA62: 0 | BB62: 7.32 | BC62: Y | BG62: -12.2 | BH62: Wheels & Wheel Components | BI62: Tires & Wheels | BJ62: Automotive Wheel Covers & Hub Caps | BK62: BSE-31-4.0 | BN62: N | BO62: Seller Fulfilled | BP62: Delivery | BR62: 0 | BW62: =if(OR(F62="SALE",F62="REFUNDED"),IFERROR(Vlookup(I62,'Listing SKU - Fill SKU Mapping'!A:C,3,false),"Map"),"") -> Keystone | BX62: =IF(OR(F62="SALE",F62="REFUNDED")=TRUE,iferror(Vlookup(I62,'Listing SKU - Fill SKU Mapping'!A:B,2,false),"Map"),"") -> IMP401BLK | BY62: =IF(OR(F62="SALE",F62="REFUNDED")=TRUE,iferror(Vlookup(I62,'Listing SKU - Fill SKU Mapping'!A:D,4,false),"Map"),"") -> 62.33 | BZ62: =If(BW62="Keystone",11.5,"") -> 11.5 | CA62: =IF(ISNUMBER(BY62)=TRUE,BY62+BZ62,"") -> 73.83 | CB62: =if(F62="SALE",V62-CA62,"") -> 35.95 | CC62: =if(F62="REFUNDED",iferror(Vlookup(I62,'Listing SKU - Fill SKU Mapping'!A:B,2,false),"Map"),"") | CD62: =if(F62="REFUNDED",iferror(Vlookup(I62,'Listing SKU - Fill SKU Mapping'!A:C,3,false),"Map"),"") | CE62: =TEXT(G62,"YYYY") -> 2025 | CF62: =TEXT(G62,"MMMM") -> April | CG62: =IF(AND((G62-CG$1)>=0,(G62-CG$1)<=6), "This Week",IF(AND((G62-CG$1)>=-7,(G62-CG$1)<=-1), "Last Week",""))
A63: 200012952028357 | B63: 1 | C63: 109009544362781 | D63: 1 | F63: SALE | G63: 45754 | H63: 1 | I63: WM-FR-IMP-5748-16CH5DS | J63: 460776236087 | K63: 16 inch Chrome ABS Wheel Skins Set Compatible with 2016-2018 Chevrolet Cruze LT & Impostors for 5748 Wheel Series | L63: 2038710 | O63: IA | R63: Davenport | S63: 52807 | T63: Marketplace standard | U63: 117.68 | V63: 98.98 | W63: 11 | X63: 10 | Y63: 109.98 | Z63: 0 | AA63: 0 | AB63: 0 | AC63: 0 | AD63: 0 | AE63: 0 | AF63: 0 | AG63: 0 | AH63: 0 | AI63: 0 | AJ63: 0 | AK63: 0 | AL63: 0 | AM63: 0 | AN63: 0 | AO63: 7.7 | AP63: 0 | AQ63: 0 | AR63: 0 | AS63: 0 | AT63: 0 | AU63: 0 | AV63: 0 | AW63: 0 | AX63: 0 | AY63: 0 | AZ63: 0 | BA63: 0 | BB63: 7.7 | BC63: Y | BG63: -11 | BH63: Wheels & Wheel Components | BI63: Tires & Wheels | BJ63: Automotive Wheel Covers & Hub Caps | BK63: BSE-31-4.0 | BN63: N | BO63: Seller Fulfilled | BP63: Delivery | BR63: 0 | BW63: =if(OR(F63="SALE",F63="REFUNDED"),IFERROR(Vlookup(I63,'Listing SKU - Fill SKU Mapping'!A:C,3,false),"Map"),"") -> Keystone | BX63: =IF(OR(F63="SALE",F63="REFUNDED")=TRUE,iferror(Vlookup(I63,'Listing SKU - Fill SKU Mapping'!A:B,2,false),"Map"),"") -> IMP412XN | BY63: =IF(OR(F63="SALE",F63="REFUNDED")=TRUE,iferror(Vlookup(I63,'Listing SKU - Fill SKU Mapping'!A:D,4,false),"Map"),"") -> 53.65 | BZ63: =If(BW63="Keystone",11.5,"") -> 11.5 | CA63: =IF(ISNUMBER(BY63)=TRUE,BY63+BZ63,"") -> 65.15 | CB63: =if(F63="SALE",V63-CA63,"") -> 33.83 | CC63: =if(F63="REFUNDED",iferror(Vlookup(I63,'Listing SKU - Fill SKU Mapping'!A:B,2,false),"Map"),"") | CD63: =if(F63="REFUNDED",iferror(Vlookup(I63,'Listing SKU - Fill SKU Mapping'!A:C,3,false),"Map"),"") | CE63: =TEXT(G63,"YYYY") -> 2025 | CF63: =TEXT(G63,"MMMM") -> April | CG63: =IF(AND((G63-CG$1)>=0,(G63-CG$1)<=6), "This Week",IF(AND((G63-CG$1)>=-7,(G63-CG$1)<=-1), "Last Week",""))
A64: 200012934607014 | B64: 1 | C64: 109010168324919 | D64: 1 | F64: SALE | G64: 45757 | H64: 1 | I64: WM-FR-IMP-DS7Z1007Q-17CC10S | J64: 460776230283 | K64: Set of 4 17 Chrome & Charcoal ABS Wheel Skins Compatible with 2017-2020 Ford Fusion SE 2015-2016 Ford Fusion Impostors for DS7Z1007Q Wheel Series | L64: 2038710 | O64: VA | R64: Roanoke | S64: 24013 | T64: Marketplace standard | U64: 91.59 | V64: 80.89 | W64: 6.09 | X64: 7 | Y64: 86.98 | Z64: 0 | AA64: 0 | AB64: 0 | AC64: 0 | AD64: 0 | AE64: 0 | AF64: 0 | AG64: 0 | AH64: 0 | AI64: 0 | AJ64: 0 | AK64: 0 | AL64: 0 | AM64: 0 | AN64: 0 | AO64: 4.61 | AP64: 0 | AQ64: 0 | AR64: 0 | AS64: 0 | AT64: 0 | AU64: 0 | AV64: 0 | AW64: 0 | AX64: 0 | AY64: 0 | AZ64: 0 | BA64: 0 | BB64: 4.61 | BC64: Y | BG64: -8.7 | BH64: Wheels & Wheel Components | BI64: Tires & Wheels | BJ64: Automotive Wheel Covers & Hub Caps | BK64: PRO-119076-10.0 | BN64: N | BO64: Seller Fulfilled | BP64: Delivery | BQ64: New Seller Saving | BR64: 2.61 | BW64: =if(OR(F64="SALE",F64="REFUNDED"),IFERROR(Vlookup(I64,'Listing SKU - Fill SKU Mapping'!A:C,3,false),"Map"),"") -> Keystone | BX64: =IF(OR(F64="SALE",F64="REFUNDED")=TRUE,iferror(Vlookup(I64,'Listing SKU - Fill SKU Mapping'!A:B,2,false),"Map"),"") -> IMP447CC | BY64: =IF(OR(F64="SALE",F64="REFUNDED")=TRUE,iferror(Vlookup(I64,'Listing SKU - Fill SKU Mapping'!A:D,4,false),"Map"),"") -> 67.46 | BZ64: =If(BW64="Keystone",11.5,"") -> 11.5 | CA64: =IF(ISNUMBER(BY64)=TRUE,BY64+BZ64,"") -> 78.96 | CB64: =if(F64="SALE",V64-CA64,"") -> 1.93 | CC64: =if(F64="REFUNDED",iferror(Vlookup(I64,'Listing SKU - Fill SKU Mapping'!A:B,2,false),"Map"),"") | CD64: =if(F64="REFUNDED",iferror(Vlookup(I64,'Listing SKU - Fill SKU Mapping'!A:C,3,false),"Map"),"") | CE64: =TEXT(G64,"YYYY") -> 2025 | CF64: =TEXT(G64,"MMMM") -> April | CG64: =IF(AND((G64-CG$1)>=0,(G64-CG$1)<=6), "This Week",IF(AND((G64-CG$1)>=-7,(G64-CG$1)<=-1), "Last Week",""))
A65: 200012922778232 | B65: 1 | C65: 109010166234110 | D65: 1 | F65: SALE | G65: 45757 | H65: 1 | I65: WM-FR-IMP-10149-16GB7S | J65: 460776236261 | K65: 16 inch Gloss Black ABS Wheel Skins Set Compatible with 2018-2022 Ford EcoSport & Impostors for 10149 Wheel Series | L65: 2038710 | O65: MO | R65: Affton | S65: 63123 | T65: Marketplace standard | U65: 101.08 | V65: 90.19 | W65: 6.79 | X65: 7 | Y65: 96.98 | Z65: 0 | AA65: 0 | AB65: 0 | AC65: 0 | AD65: 0 | AE65: 0 | AF65: 0 | AG65: 0 | AH65: 0 | AI65: 0 | AJ65: 0 | AK65: 0 | AL65: 0 | AM65: 0 | AN65: 0 | AO65: 4.1 | AP65: 0 | AQ65: 0 | AR65: 0 | AS65: 0 | AT65: 0 | AU65: 0 | AV65: 0 | AW65: 0 | AX65: 0 | AY65: 0 | AZ65: 0 | BA65: 0 | BB65: 4.1 | BC65: Y | BG65: -9.7 | BH65: Wheels & Wheel Components | BI65: Tires & Wheels | BJ65: Automotive Wheel Covers & Hub Caps | BK65: PRO-119076-10.0 | BN65: N | BO65: Seller Fulfilled | BP65: Delivery | BQ65: New Seller Saving | BR65: 2.91 | BW65: =if(OR(F65="SALE",F65="REFUNDED"),IFERROR(Vlookup(I65,'Listing SKU - Fill SKU Mapping'!A:C,3,false),"Map"),"") -> Keystone | BX65: =IF(OR(F65="SALE",F65="REFUNDED")=TRUE,iferror(Vlookup(I65,'Listing SKU - Fill SKU Mapping'!A:B,2,false),"Map"),"") -> IMP456BLK | BY65: =IF(OR(F65="SALE",F65="REFUNDED")=TRUE,iferror(Vlookup(I65,'Listing SKU - Fill SKU Mapping'!A:D,4,false),"Map"),"") -> 44.97 | BZ65: =If(BW65="Keystone",11.5,"") -> 11.5 | CA65: =IF(ISNUMBER(BY65)=TRUE,BY65+BZ65,"") -> 56.47 | CB65: =if(F65="SALE",V65-CA65,"") -> 33.72 | CC65: =if(F65="REFUNDED",iferror(Vlookup(I65,'Listing SKU - Fill SKU Mapping'!A:B,2,false),"Map"),"") | CD65: =if(F65="REFUNDED",iferror(Vlookup(I65,'Listing SKU - Fill SKU Mapping'!A:C,3,false),"Map"),"") | CE65: =TEXT(G65,"YYYY") -> 2025 | CF65: =TEXT(G65,"MMMM") -> April | CG65: =IF(AND((G65-CG$1)>=0,(G65-CG$1)<=6), "This Week",IF(AND((G65-CG$1)>=-7,(G65-CG$1)<=-1), "Last Week",""))
A66: 200012893572614 | B66: 1 | C66: 109008493702855 | D66: 1 | F66: SALE | G66: 45741 | H66: 1 | I66: WM-FR-IMP-5712-18GB10S | J66: 460776230832 | K66: Set of 4 18 inch Gloss Black Wheel Skins Covers Compatible with 18-24 Chevrolet Equinox LS LT Premier 18-21 Equinox L 16-20 Impala Impostors for 5712 Wheel Series | L66: 2038710 | O66: SC | R66: Conway | S66: 29527 | T66: Marketplace standard | U66: 112.3 | V66: 96.7 | W66: 7.28 | X66: 7 | Y66: 103.98 | Z66: 0 | AA66: 0 | AB66: 0 | AC66: 0 | AD66: 0 | AE66: 0 | AF66: 0 | AG66: 0 | AH66: 0 | AI66: 0 | AJ66: 0 | AK66: 0 | AL66: 0 | AM66: 0 | AN66: 0 | AO66: 8.32 | AP66: 0 | AQ66: 0 | AR66: 0 | AS66: 0 | AT66: 0 | AU66: 0 | AV66: 0 | AW66: 0 | AX66: 0 | AY66: 0 | AZ66: 0 | BA66: 0 | BB66: 8.32 | BC66: Y | BG66: -10.4 | BH66: Wheels & Wheel Components | BI66: Tires & Wheels | BJ66: Automotive Wheel Covers & Hub Caps | BK66: PRO-119076-8.0 | BN66: N | BO66: Seller Fulfilled | BP66: Delivery | BQ66: New Seller Saving | BR66: 3.12 | BW66: =if(OR(F66="SALE",F66="REFUNDED"),IFERROR(Vlookup(I66,'Listing SKU - Fill SKU Mapping'!A:C,3,false),"Map"),"") -> Keystone | BX66: =IF(OR(F66="SALE",F66="REFUNDED")=TRUE,iferror(Vlookup(I66,'Listing SKU - Fill SKU Mapping'!A:B,2,false),"Map"),"") -> IMP407BLK | BY66: =IF(OR(F66="SALE",F66="REFUNDED")=TRUE,iferror(Vlookup(I66,'Listing SKU - Fill SKU Mapping'!A:D,4,false),"Map"),"") -> 49.71 | BZ66: =If(BW66="Keystone",11.5,"") -> 11.5 | CA66: =IF(ISNUMBER(BY66)=TRUE,BY66+BZ66,"") -> 61.21 | CB66: =if(F66="SALE",V66-CA66,"") -> 35.49 | CC66: =if(F66="REFUNDED",iferror(Vlookup(I66,'Listing SKU - Fill SKU Mapping'!A:B,2,false),"Map"),"") | CD66: =if(F66="REFUNDED",iferror(Vlookup(I66,'Listing SKU - Fill SKU Mapping'!A:C,3,false),"Map"),"") | CE66: =TEXT(G66,"YYYY") -> 2025 | CF66: =TEXT(G66,"MMMM") -> March | CG66: =IF(AND((G66-CG$1)>=0,(G66-CG$1)<=6), "This Week",IF(AND((G66-CG$1)>=-7,(G66-CG$1)<=-1), "Last Week",""))
A67: 200012893572614 | B67: 1 | C67: 109008493702855 | D67: 1 | F67: REFUNDED | G67: 45743 | H67: 1 | I67: WM-FR-IMP-5712-18GB10S | J67: 460776230832 | K67: Set of 4 18 inch Gloss Black Wheel Skins Covers Compatible with 18-24 Chevrolet Equinox LS LT Premier 18-21 Equinox L 16-20 Impala Impostors for 5712 Wheel Series | L67: 2038710 | R67: Conway | S67: 29527 | U67: -112.3 | V67: -96.7 | W67: -7.28 | X67: 0 | Y67: 0 | Z67: -103.98 | AA67: 0 | AB67: 0 | AC67: 0 | AD67: 0 | AE67: 0 | AF67: 0 | AG67: 0 | AH67: 0 | AI67: 0 | AJ67: 0 | AK67: 0 | AL67: 0 | AM67: 0 | AN67: 0 | AO67: 0 | AP67: 0 | AQ67: 0 | AR67: 0 | AS67: 0 | AT67: -8.32 | AU67: 0 | AV67: 0 | AW67: 0 | AX67: 0 | AY67: 0 | AZ67: 0 | BA67: 0 | BB67: -8.32 | BC67: Y | BD67: Return Refund | BE67: 5010 | BH67: Wheels & Wheel Components | BI67: Tires & Wheels | BL67: 1000 | BM67: No Longer Wanted | BN67: N | BO67: Seller Fulfilled | BW67: =if(OR(F67="SALE",F67="REFUNDED"),IFERROR(Vlookup(I67,'Listing SKU - Fill SKU Mapping'!A:C,3,false),"Map"),"") -> Keystone | BX67: =IF(OR(F67="SALE",F67="REFUNDED")=TRUE,iferror(Vlookup(I67,'Listing SKU - Fill SKU Mapping'!A:B,2,false),"Map"),"") -> IMP407BLK | BY67: =IF(OR(F67="SALE",F67="REFUNDED")=TRUE,iferror(Vlookup(I67,'Listing SKU - Fill SKU Mapping'!A:D,4,false),"Map"),"") -> 49.71 | BZ67: =If(BW67="Keystone",11.5,"") -> 11.5 | CA67: =IF(ISNUMBER(BY67)=TRUE,BY67+BZ67,"") -> 61.21 | CB67: =if(F67="SALE",V67-CA67,"") | CC67: =if(F67="REFUNDED",iferror(Vlookup(I67,'Listing SKU - Fill SKU Mapping'!A:B,2,false),"Map"),"") -> IMP407BLK | CD67: =if(F67="REFUNDED",iferror(Vlookup(I67,'Listing SKU - Fill SKU Mapping'!A:C,3,false),"Map"),"") -> Keystone | CE67: =TEXT(G67,"YYYY") -> 2025 | CF67: =TEXT(G67,"MMMM") -> March | CG67: =IF(AND((G67-CG$1)>=0,(G67-CG$1)<=6), "This Week",IF(AND((G67-CG$1)>=-7,(G67-CG$1)<=-1), "Last Week",""))
A68: 200012838119978 | B68: 2 | C68: 109009333614035 | D68: 2 | F68: SALE | G68: 45749 | H68: 1 | I68: WM-FR-IMP-22968927-17GB5VS | J68: 460776238135 | K68: Set of 4 17 inch Gloss Black ABS Wheel Skins Wheel Covers compatible with 18-24 Chevrolet Equinox LT LS 18-21 Equinox L Impostors for 22968927 Wheel Series | L68: 2038710 | O68: IL | R68: Colona | S68: 61241 | T68: Marketplace standard | U68: 113.11 | V68: 97.63 | W68: 7.35 | X68: 7 | Y68: 104.98 | Z68: 0 | AA68: 0 | AB68: 0 | AC68: 0 | AD68: 0 | AE68: 0 | AF68: 0 | AG68: 0 | AH68: 0 | AI68: 0 | AJ68: 0 | AK68: 0 | AL68: 0 | AM68: 0 | AN68: 0 | AO68: 8.13 | AP68: 0 | AQ68: 0 | AR68: 0 | AS68: 0 | AT68: 0 | AU68: 0 | AV68: 0 | AW68: 0 | AX68: 0 | AY68: 0 | AZ68: 0 | BA68: 0 | BB68: 8.13 | BC68: Y | BG68: -10.5 | BH68: Wheels & Wheel Components | BI68: Tires & Wheels | BJ68: Automotive Wheel Covers & Hub Caps | BK68: PRO-119076-9.0 | BN68: N | BO68: Seller Fulfilled | BP68: Delivery | BQ68: New Seller Saving | BR68: 3.15 | BW68: =if(OR(F68="SALE",F68="REFUNDED"),IFERROR(Vlookup(I68,'Listing SKU - Fill SKU Mapping'!A:C,3,false),"Map"),"") -> Keystone | BX68: =IF(OR(F68="SALE",F68="REFUNDED")=TRUE,iferror(Vlookup(I68,'Listing SKU - Fill SKU Mapping'!A:B,2,false),"Map"),"") -> IMP409BLK | BY68: =IF(OR(F68="SALE",F68="REFUNDED")=TRUE,iferror(Vlookup(I68,'Listing SKU - Fill SKU Mapping'!A:D,4,false),"Map"),"") -> 50.49 | BZ68: =If(BW68="Keystone",11.5,"") -> 11.5 | CA68: =IF(ISNUMBER(BY68)=TRUE,BY68+BZ68,"") -> 61.99 | CB68: =if(F68="SALE",V68-CA68,"") -> 35.64 | CC68: =if(F68="REFUNDED",iferror(Vlookup(I68,'Listing SKU - Fill SKU Mapping'!A:B,2,false),"Map"),"") | CD68: =if(F68="REFUNDED",iferror(Vlookup(I68,'Listing SKU - Fill SKU Mapping'!A:C,3,false),"Map"),"") | CE68: =TEXT(G68,"YYYY") -> 2025 | CF68: =TEXT(G68,"MMMM") -> April | CG68: =IF(AND((G68-CG$1)>=0,(G68-CG$1)<=6), "This Week",IF(AND((G68-CG$1)>=-7,(G68-CG$1)<=-1), "Last Week",""))
A69: 200012841383047 | B69: 1 | C69: 109007662415839 | D69: 1 | F69: SALE | G69: 45733 | H69: 1 | I69: WM-FR-IMP-5712-18GB10S | J69: 460776230832 | K69: Set of 4 18 inch Gloss Black Wheel Skins Covers Compatible with 18-24 Chevrolet Equinox LS LT Premier 18-21 Equinox L 16-20 Impala Impostors for 5712 Wheel Series | L69: 2038710 | O69: IL | R69: Galesburg | S69: 61401 | T69: Marketplace standard | U69: 113.34 | V69: 96.7 | W69: 7.28 | X69: 7 | Y69: 103.98 | Z69: 0 | AA69: 0 | AB69: 0 | AC69: 0 | AD69: 0 | AE69: 0 | AF69: 0 | AG69: 0 | AH69: 0 | AI69: 0 | AJ69: 0 | AK69: 0 | AL69: 0 | AM69: 0 | AN69: 0 | AO69: 9.36 | AP69: 0 | AQ69: 0 | AR69: 0 | AS69: 0 | AT69: 0 | AU69: 0 | AV69: 0 | AW69: 0 | AX69: 0 | AY69: 0 | AZ69: 0 | BA69: 0 | BB69: 9.36 | BC69: Y | BG69: -10.4 | BH69: Wheels & Wheel Components | BI69: Tires & Wheels | BJ69: Automotive Wheel Covers & Hub Caps | BK69: PRO-119076-7.0 | BN69: N | BO69: Seller Fulfilled | BP69: Delivery | BQ69: New Seller Saving | BR69: 3.12 | BW69: =if(OR(F69="SALE",F69="REFUNDED"),IFERROR(Vlookup(I69,'Listing SKU - Fill SKU Mapping'!A:C,3,false),"Map"),"") -> Keystone | BX69: =IF(OR(F69="SALE",F69="REFUNDED")=TRUE,iferror(Vlookup(I69,'Listing SKU - Fill SKU Mapping'!A:B,2,false),"Map"),"") -> IMP407BLK | BY69: =IF(OR(F69="SALE",F69="REFUNDED")=TRUE,iferror(Vlookup(I69,'Listing SKU - Fill SKU Mapping'!A:D,4,false),"Map"),"") -> 49.71 | BZ69: =If(BW69="Keystone",11.5,"") -> 11.5 | CA69: =IF(ISNUMBER(BY69)=TRUE,BY69+BZ69,"") -> 61.21 | CB69: =if(F69="SALE",V69-CA69,"") -> 35.49 | CC69: =if(F69="REFUNDED",iferror(Vlookup(I69,'Listing SKU - Fill SKU Mapping'!A:B,2,false),"Map"),"") | CD69: =if(F69="REFUNDED",iferror(Vlookup(I69,'Listing SKU - Fill SKU Mapping'!A:C,3,false),"Map"),"") | CE69: =TEXT(G69,"YYYY") -> 2025 | CF69: =TEXT(G69,"MMMM") -> March | CG69: =IF(AND((G69-CG$1)>=0,(G69-CG$1)<=6), "This Week",IF(AND((G69-CG$1)>=-7,(G69-CG$1)<=-1), "Last Week",""))
A70: 200013477790101 | B70: 11 | C70: 109015712842855 | D70: 11 | F70: SALE | G70: 45813 | H70: 1 | I70: WM-KS-FRHC-3276-17SL | J70: 467129950768 | K70: Fuel Rider Set of 4 17 inch Silver Screw-On Hubcaps With 5 Spoke Compatible With 07-10 Pontiac G6 08-12 Chevrolet Malibu Standard Steel Wheel Covers | L70: 2038710 | O70: SC | R70: Hartsville | S70: 29550 | T70: Marketplace standard | U70: 92.86 | V70: 79.96 | W70: 6.02 | X70: 7 | Y70: 85.98 | Z70: 0 | AA70: 0 | AB70: 0 | AC70: 0 | AD70: 0 | AE70: 0 | AF70: 0 | AG70: 0 | AH70: 0 | AI70: 0 | AJ70: 0 | AK70: 0 | AL70: 0 | AM70: 0 | AN70: 0 | AO70: 6.88 | AP70: 0 | AQ70: 0 | AR70: 0 | AS70: 0 | AT70: 0 | AU70: 0 | AV70: 0 | AW70: 0 | AX70: 0 | AY70: 0 | AZ70: 0 | BA70: 0 | BB70: 6.88 | BC70: Y | BG70: -8.6 | BH70: Wheels & Wheel Components | BI70: Tires & Wheels | BJ70: Automotive Wheel Covers & Hub Caps | BK70: PRO-119076-19.0 | BN70: N | BO70: Seller Fulfilled | BP70: Delivery | BQ70: New Seller Saving | BR70: 2.58 | BW70: =if(OR(F70="SALE",F70="REFUNDED"),IFERROR(Vlookup(I70,'Listing SKU - Fill SKU Mapping'!A:C,3,false),"Map"),"") -> Keystone | BX70: =IF(OR(F70="SALE",F70="REFUNDED")=TRUE,iferror(Vlookup(I70,'Listing SKU - Fill SKU Mapping'!A:B,2,false),"Map"),"") -> 43517S | BY70: =IF(OR(F70="SALE",F70="REFUNDED")=TRUE,iferror(Vlookup(I70,'Listing SKU - Fill SKU Mapping'!A:D,4,false),"Map"),"") -> 33.53 | BZ70: =If(BW70="Keystone",11.5,"") -> 11.5 | CA70: =IF(ISNUMBER(BY70)=TRUE,BY70+BZ70,"") -> 45.03 | CB70: =if(F70="SALE",V70-CA70,"") -> 34.93 | CC70: =if(F70="REFUNDED",iferror(Vlookup(I70,'Listing SKU - Fill SKU Mapping'!A:B,2,false),"Map"),"") | CD70: =if(F70="REFUNDED",iferror(Vlookup(I70,'Listing SKU - Fill SKU Mapping'!A:C,3,false),"Map"),"") | CE70: =TEXT(G70,"YYYY") -> 2025 | CF70: =TEXT(G70,"MMMM") -> June | CG70: =IF(AND((G70-CG$1)>=0,(G70-CG$1)<=6), "This Week",IF(AND((G70-CG$1)>=-7,(G70-CG$1)<=-1), "Last Week",""))
A71: 200013370453567 | B71: 1 | C71: 109016447760929 | D71: 1 | F71: SALE | G71: 45820 | H71: 1 | I71: WM-FR-IMP-3781-17CH5SP | J71: 460776230757 | K71: Set of 4 17 inch Chrome Wheel Skins Covers compatible with 2009-2014 Ford F-150 Impostors for 3781 Wheel Series | L71: 2038710 | O71: AR | R71: Forrest City | S71: 72335 | T71: Marketplace standard | U71: 108.01 | V71: 90.19 | W71: 6.79 | X71: 7 | Y71: 96.98 | Z71: 0 | AA71: 0 | AB71: 0 | AC71: 0 | AD71: 0 | AE71: 0 | AF71: 0 | AG71: 0 | AH71: 0 | AI71: 0 | AJ71: 0 | AK71: 0 | AL71: 0 | AM71: 0 | AN71: 0 | AO71: 11.03 | AP71: 0 | AQ71: 0 | AR71: 0 | AS71: 0 | AT71: 0 | AU71: 0 | AV71: 0 | AW71: 0 | AX71: 0 | AY71: 0 | AZ71: 0 | BA71: 0 | BB71: 11.03 | BC71: Y | BG71: -9.7 | BH71: Wheels & Wheel Components | BI71: Tires & Wheels | BJ71: Automotive Wheel Covers & Hub Caps | BK71: PRO-119076-21.0 | BN71: N | BO71: Seller Fulfilled | BP71: Delivery | BQ71: New Seller Saving | BR71: 2.91 | BW71: =if(OR(F71="SALE",F71="REFUNDED"),IFERROR(Vlookup(I71,'Listing SKU - Fill SKU Mapping'!A:C,3,false),"Map"),"") -> Keystone | BX71: =IF(OR(F71="SALE",F71="REFUNDED")=TRUE,iferror(Vlookup(I71,'Listing SKU - Fill SKU Mapping'!A:B,2,false),"Map"),"") -> IMP326X | BY71: =IF(OR(F71="SALE",F71="REFUNDED")=TRUE,iferror(Vlookup(I71,'Listing SKU - Fill SKU Mapping'!A:D,4,false),"Map"),"") -> 42.21 | BZ71: =If(BW71="Keystone",11.5,"") -> 11.5 | CA71: =IF(ISNUMBER(BY71)=TRUE,BY71+BZ71,"") -> 53.71 | CB71: =if(F71="SALE",V71-CA71,"") -> 36.48 | CC71: =if(F71="REFUNDED",iferror(Vlookup(I71,'Listing SKU - Fill SKU Mapping'!A:B,2,false),"Map"),"") | CD71: =if(F71="REFUNDED",iferror(Vlookup(I71,'Listing SKU - Fill SKU Mapping'!A:C,3,false),"Map"),"") | CE71: =TEXT(G71,"YYYY") -> 2025 | CF71: =TEXT(G71,"MMMM") -> June | CG71: =IF(AND((G71-CG$1)>=0,(G71-CG$1)<=6), "This Week",IF(AND((G71-CG$1)>=-7,(G71-CG$1)<=-1), "Last Week",""))
A72: 200013369057110 | B72: 1 | C72: 109016342808965 | D72: 1 | F72: SALE | G72: 45820 | H72: 1 | I72: WM-KS-FRHC-53088-16SL | J72: 467129928224 | K72: Fuel Rider Set of 4 16 inch Silver Snap-On Hubcaps With 10 Spoke Compatible With 2013-2018 Nissan Altima Standard Steel Wheel Covers | L72: 2038710 | O72: FL | R72: Miramar | S72: 33023 | T72: Marketplace standard | U72: 72.74 | V72: 63.22 | W72: 4.76 | X72: 7 | Y72: 67.98 | Z72: 0 | AA72: 0 | AB72: 0 | AC72: 0 | AD72: 0 | AE72: 0 | AF72: 0 | AG72: 0 | AH72: 0 | AI72: 0 | AJ72: 0 | AK72: 0 | AL72: 0 | AM72: 0 | AN72: 0 | AO72: 4.76 | AP72: 0 | AQ72: 0 | AR72: 0 | AS72: 0 | AT72: 0 | AU72: 0 | AV72: 0 | AW72: 0 | AX72: 0 | AY72: 0 | AZ72: 0 | BA72: 0 | BB72: 4.76 | BC72: Y | BG72: -6.8 | BH72: Wheels & Wheel Components | BI72: Tires & Wheels | BJ72: Automotive Wheel Covers & Hub Caps | BK72: PRO-119076-20.0 | BN72: N | BO72: Seller Fulfilled | BP72: Delivery | BQ72: New Seller Saving | BR72: 2.04 | BW72: =if(OR(F72="SALE",F72="REFUNDED"),IFERROR(Vlookup(I72,'Listing SKU - Fill SKU Mapping'!A:C,3,false),"Map"),"") -> Keystone | BX72: =IF(OR(F72="SALE",F72="REFUNDED")=TRUE,iferror(Vlookup(I72,'Listing SKU - Fill SKU Mapping'!A:B,2,false),"Map"),"") -> 50516S | BY72: =IF(OR(F72="SALE",F72="REFUNDED")=TRUE,iferror(Vlookup(I72,'Listing SKU - Fill SKU Mapping'!A:D,4,false),"Map"),"") -> 22.1 | BZ72: =If(BW72="Keystone",11.5,"") -> 11.5 | CA72: =IF(ISNUMBER(BY72)=TRUE,BY72+BZ72,"") -> 33.6 | CB72: =if(F72="SALE",V72-CA72,"") -> 29.62 | CC72: =if(F72="REFUNDED",iferror(Vlookup(I72,'Listing SKU - Fill SKU Mapping'!A:B,2,false),"Map"),"") | CD72: =if(F72="REFUNDED",iferror(Vlookup(I72,'Listing SKU - Fill SKU Mapping'!A:C,3,false),"Map"),"") | CE72: =TEXT(G72,"YYYY") -> 2025 | CF72: =TEXT(G72,"MMMM") -> June | CG72: =IF(AND((G72-CG$1)>=0,(G72-CG$1)<=6), "This Week",IF(AND((G72-CG$1)>=-7,(G72-CG$1)<=-1), "Last Week",""))
A73: 200013356458819 | B73: 1 | C73: 109015712112216 | D73: 1 | F73: SALE | G73: 45813 | H73: 1 | I73: WM-KS-FRHC-3299-18SL | J73: 467129915064 | K73: Fuel Rider Set of 4 18 inch Silver Screw-On Hubcaps With 5 Spoke Compatible With 2014-2020 Chevrolet Impala Standard Steel Wheel Covers | L73: 2038710 | O73: SC | R73: Greenwood | S73: 29649 | T73: Marketplace standard | U73: 94.14 | V73: 81.82 | W73: 6.16 | X73: 7 | Y73: 87.98 | Z73: 0 | AA73: 0 | AB73: 0 | AC73: 0 | AD73: 0 | AE73: 0 | AF73: 0 | AG73: 0 | AH73: 0 | AI73: 0 | AJ73: 0 | AK73: 0 | AL73: 0 | AM73: 0 | AN73: 0 | AO73: 6.16 | AP73: 0 | AQ73: 0 | AR73: 0 | AS73: 0 | AT73: 0 | AU73: 0 | AV73: 0 | AW73: 0 | AX73: 0 | AY73: 0 | AZ73: 0 | BA73: 0 | BB73: 6.16 | BC73: Y | BG73: -8.8 | BH73: Wheels & Wheel Components | BI73: Tires & Wheels | BJ73: Automotive Wheel Covers & Hub Caps | BK73: PRO-119076-19.0 | BN73: N | BO73: Seller Fulfilled | BP73: Delivery | BQ73: New Seller Saving | BR73: 2.64 | BW73: =if(OR(F73="SALE",F73="REFUNDED"),IFERROR(Vlookup(I73,'Listing SKU - Fill SKU Mapping'!A:C,3,false),"Map"),"") -> Keystone | BX73: =IF(OR(F73="SALE",F73="REFUNDED")=TRUE,iferror(Vlookup(I73,'Listing SKU - Fill SKU Mapping'!A:B,2,false),"Map"),"") -> 47218S | BY73: =IF(OR(F73="SALE",F73="REFUNDED")=TRUE,iferror(Vlookup(I73,'Listing SKU - Fill SKU Mapping'!A:D,4,false),"Map"),"") -> 34.71 | BZ73: =If(BW73="Keystone",11.5,"") -> 11.5 | CA73: =IF(ISNUMBER(BY73)=TRUE,BY73+BZ73,"") -> 46.21 | CB73: =if(F73="SALE",V73-CA73,"") -> 35.61 | CC73: =if(F73="REFUNDED",iferror(Vlookup(I73,'Listing SKU - Fill SKU Mapping'!A:B,2,false),"Map"),"") | CD73: =if(F73="REFUNDED",iferror(Vlookup(I73,'Listing SKU - Fill SKU Mapping'!A:C,3,false),"Map"),"") | CE73: =TEXT(G73,"YYYY") -> 2025 | CF73: =TEXT(G73,"MMMM") -> June | CG73: =IF(AND((G73-CG$1)>=0,(G73-CG$1)<=6), "This Week",IF(AND((G73-CG$1)>=-7,(G73-CG$1)<=-1), "Last Week",""))
A74: 200013273890861 | B74: 1 | C74: 109015181470052 | D74: 1 | F74: SALE | G74: 45810 | H74: 1 | I74: WM-FR-IMP-75162-18GB5VS | J74: 460776241562 | K74: 18 inch Gloss Black ABS Wheel Skins Set Compatible with 2014-2019 Toyota Highlander LE XLE & Impostors for 75162 Wheel Series | L74: 2038710 | O74: IN | R74: South Bend | S74: 46614 | T74: Marketplace standard | U74: 118.75 | V74: 103.21 | W74: 7.77 | X74: 7 | Y74: 110.98 | Z74: 0 | AA74: 0 | AB74: 0 | AC74: 0 | AD74: 0 | AE74: 0 | AF74: 0 | AG74: 0 | AH74: 0 | AI74: 0 | AJ74: 0 | AK74: 0 | AL74: 0 | AM74: 0 | AN74: 0 | AO74: 7.77 | AP74: 0 | AQ74: 0 | AR74: 0 | AS74: 0 | AT74: 0 | AU74: 0 | AV74: 0 | AW74: 0 | AX74: 0 | AY74: 0 | AZ74: 0 | BA74: 0 | BB74: 7.77 | BC74: Y | BG74: -11.1 | BH74: Wheels & Wheel Components | BI74: Tires & Wheels | BJ74: Automotive Wheel Covers & Hub Caps | BK74: PRO-119076-18.0 | BN74: N | BO74: Seller Fulfilled | BP74: Delivery | BQ74: New Seller Saving | BR74: 3.33 | BW74: =if(OR(F74="SALE",F74="REFUNDED"),IFERROR(Vlookup(I74,'Listing SKU - Fill SKU Mapping'!A:C,3,false),"Map"),"") -> Keystone | BX74: =IF(OR(F74="SALE",F74="REFUNDED")=TRUE,iferror(Vlookup(I74,'Listing SKU - Fill SKU Mapping'!A:B,2,false),"Map"),"") -> IMP410BLK | BY74: =IF(OR(F74="SALE",F74="REFUNDED")=TRUE,iferror(Vlookup(I74,'Listing SKU - Fill SKU Mapping'!A:D,4,false),"Map"),"") -> 51.28 | BZ74: =If(BW74="Keystone",11.5,"") -> 11.5 | CA74: =IF(ISNUMBER(BY74)=TRUE,BY74+BZ74,"") -> 62.78 | CB74: =if(F74="SALE",V74-CA74,"") -> 40.43 | CC74: =if(F74="REFUNDED",iferror(Vlookup(I74,'Listing SKU - Fill SKU Mapping'!A:B,2,false),"Map"),"") | CD74: =if(F74="REFUNDED",iferror(Vlookup(I74,'Listing SKU - Fill SKU Mapping'!A:C,3,false),"Map"),"") | CE74: =TEXT(G74,"YYYY") -> 2025 | CF74: =TEXT(G74,"MMMM") -> June | CG74: =IF(AND((G74-CG$1)>=0,(G74-CG$1)<=6), "This Week",IF(AND((G74-CG$1)>=-7,(G74-CG$1)<=-1), "Last Week",""))
A75: 200013258011806 | B75: 1 | C75: 109016342909469 | D75: 1 | F75: SALE | G75: 45820 | H75: 1 | I75: WM-KS-FRHC-3299-18SL | J75: 467129915064 | K75: Fuel Rider Set of 4 18 inch Silver Screw-On Hubcaps With 5 Spoke Compatible With 2014-2020 Chevrolet Impala Standard Steel Wheel Covers | L75: 2038710 | O75: CO | R75: Aurora | S75: 80014 | T75: Marketplace standard | U75: 95.02 | V75: 81.82 | W75: 6.16 | X75: 7 | Y75: 87.98 | Z75: 0 | AA75: 0 | AB75: 0 | AC75: 0 | AD75: 0 | AE75: 0 | AF75: 0 | AG75: 0 | AH75: 0 | AI75: 0 | AJ75: 0 | AK75: 0 | AL75: 0 | AM75: 0 | AN75: 0 | AO75: 7.04 | AP75: 0 | AQ75: 0 | AR75: 0 | AS75: 0 | AT75: 0 | AU75: 0 | AV75: 0 | AW75: 0 | AX75: 0 | AY75: 0 | AZ75: 0 | BA75: 0 | BB75: 7.04 | BC75: Y | BG75: -8.8 | BH75: Wheels & Wheel Components | BI75: Tires & Wheels | BJ75: Automotive Wheel Covers & Hub Caps | BK75: PRO-119076-20.0 | BN75: N | BO75: Seller Fulfilled | BP75: Delivery | BQ75: New Seller Saving | BR75: 2.64 | BW75: =if(OR(F75="SALE",F75="REFUNDED"),IFERROR(Vlookup(I75,'Listing SKU - Fill SKU Mapping'!A:C,3,false),"Map"),"") -> Keystone | BX75: =IF(OR(F75="SALE",F75="REFUNDED")=TRUE,iferror(Vlookup(I75,'Listing SKU - Fill SKU Mapping'!A:B,2,false),"Map"),"") -> 47218S | BY75: =IF(OR(F75="SALE",F75="REFUNDED")=TRUE,iferror(Vlookup(I75,'Listing SKU - Fill SKU Mapping'!A:D,4,false),"Map"),"") -> 34.71 | BZ75: =If(BW75="Keystone",11.5,"") -> 11.5 | CA75: =IF(ISNUMBER(BY75)=TRUE,BY75+BZ75,"") -> 46.21 | CB75: =if(F75="SALE",V75-CA75,"") -> 35.61 | CC75: =if(F75="REFUNDED",iferror(Vlookup(I75,'Listing SKU - Fill SKU Mapping'!A:B,2,false),"Map"),"") | CD75: =if(F75="REFUNDED",iferror(Vlookup(I75,'Listing SKU - Fill SKU Mapping'!A:C,3,false),"Map"),"") | CE75: =TEXT(G75,"YYYY") -> 2025 | CF75: =TEXT(G75,"MMMM") -> June | CG75: =IF(AND((G75-CG$1)>=0,(G75-CG$1)<=6), "This Week",IF(AND((G75-CG$1)>=-7,(G75-CG$1)<=-1), "Last Week",""))
A76: 200013233213050 | B76: 1 | C76: 109015281633679 | D76: 1 | F76: SALE | G76: 45810 | H76: 1 | I76: WM-FR-IMP-68813-17CH5SP | J76: 460776237466 | K76: 17 inch Chrome ABS Wheel Skins Set Compatible with 2014-2018 Subaru Forester & Impostors for 68813 Wheel Series | L76: 2038710 | O76: PA | R76: MT Pleasant | S76: 15666 | T76: Marketplace standard | U76: 104.92 | V76: 92.05 | W76: 6.93 | X76: 7 | Y76: 98.98 | Z76: 0 | AA76: 0 | AB76: 0 | AC76: 0 | AD76: 0 | AE76: 0 | AF76: 0 | AG76: 0 | AH76: 0 | AI76: 0 | AJ76: 0 | AK76: 0 | AL76: 0 | AM76: 0 | AN76: 0 | AO76: 5.94 | AP76: 0 | AQ76: 0 | AR76: 0 | AS76: 0 | AT76: 0 | AU76: 0 | AV76: 0 | AW76: 0 | AX76: 0 | AY76: 0 | AZ76: 0 | BA76: 0 | BB76: 5.94 | BC76: Y | BG76: -9.9 | BH76: Wheels & Wheel Components | BI76: Tires & Wheels | BJ76: Automotive Wheel Covers & Hub Caps | BK76: PRO-119076-18.0 | BN76: N | BO76: Seller Fulfilled | BP76: Delivery | BQ76: New Seller Saving | BR76: 2.97 | BW76: =if(OR(F76="SALE",F76="REFUNDED"),IFERROR(Vlookup(I76,'Listing SKU - Fill SKU Mapping'!A:C,3,false),"Map"),"") -> Keystone | BX76: =IF(OR(F76="SALE",F76="REFUNDED")=TRUE,iferror(Vlookup(I76,'Listing SKU - Fill SKU Mapping'!A:B,2,false),"Map"),"") -> IMP95X | BY76: =IF(OR(F76="SALE",F76="REFUNDED")=TRUE,iferror(Vlookup(I76,'Listing SKU - Fill SKU Mapping'!A:D,4,false),"Map"),"") -> 43.39 | BZ76: =If(BW76="Keystone",11.5,"") -> 11.5 | CA76: =IF(ISNUMBER(BY76)=TRUE,BY76+BZ76,"") -> 54.89 | CB76: =if(F76="SALE",V76-CA76,"") -> 37.16 | CC76: =if(F76="REFUNDED",iferror(Vlookup(I76,'Listing SKU - Fill SKU Mapping'!A:B,2,false),"Map"),"") | CD76: =if(F76="REFUNDED",iferror(Vlookup(I76,'Listing SKU - Fill SKU Mapping'!A:C,3,false),"Map"),"") | CE76: =TEXT(G76,"YYYY") -> 2025 | CF76: =TEXT(G76,"MMMM") -> June | CG76: =IF(AND((G76-CG$1)>=0,(G76-CG$1)<=6), "This Week",IF(AND((G76-CG$1)>=-7,(G76-CG$1)<=-1), "Last Week",""))
A77: 200013204381052 | B77: 1 | C77: 109016128368712 | D77: 1 | F77: SALE | G77: 45818 | H77: 1 | I77: WM-FR-IMP-84428928-16GB5SP | J77: 460776237855 | K77: 16 inch Gloss Black ABS Wheel Skins Set Compatible with 2019-2025 Chevrolet Malibu LS & Impostors for 84428928 Wheel Series | L77: 2038710 | O77: TX | R77: Tyler | S77: 75703 | T77: Marketplace standard | U77: 119.05 | V77: 102.28 | W77: 7.7 | X77: 7 | Y77: 109.98 | Z77: 0 | AA77: 0 | AB77: 0 | AC77: 0 | AD77: 0 | AE77: 0 | AF77: 0 | AG77: 0 | AH77: 0 | AI77: 0 | AJ77: 0 | AK77: 0 | AL77: 0 | AM77: 0 | AN77: 0 | AO77: 9.07 | AP77: 0 | AQ77: 0 | AR77: 0 | AS77: 0 | AT77: 0 | AU77: 0 | AV77: 0 | AW77: 0 | AX77: 0 | AY77: 0 | AZ77: 0 | BA77: 0 | BB77: 9.07 | BC77: Y | BG77: -11 | BH77: Wheels & Wheel Components | BI77: Tires & Wheels | BJ77: Automotive Wheel Covers & Hub Caps | BK77: PRO-119076-20.0 | BN77: N | BO77: Seller Fulfilled | BP77: Delivery | BQ77: New Seller Saving | BR77: 3.3 | BW77: =if(OR(F77="SALE",F77="REFUNDED"),IFERROR(Vlookup(I77,'Listing SKU - Fill SKU Mapping'!A:C,3,false),"Map"),"") -> Keystone | BX77: =IF(OR(F77="SALE",F77="REFUNDED")=TRUE,iferror(Vlookup(I77,'Listing SKU - Fill SKU Mapping'!A:B,2,false),"Map"),"") -> IMP464BLK | BY77: =IF(OR(F77="SALE",F77="REFUNDED")=TRUE,iferror(Vlookup(I77,'Listing SKU - Fill SKU Mapping'!A:D,4,false),"Map"),"") -> 50.89 | BZ77: =If(BW77="Keystone",11.5,"") -> 11.5 | CA77: =IF(ISNUMBER(BY77)=TRUE,BY77+BZ77,"") -> 62.39 | CB77: =if(F77="SALE",V77-CA77,"") -> 39.89 | CC77: =if(F77="REFUNDED",iferror(Vlookup(I77,'Listing SKU - Fill SKU Mapping'!A:B,2,false),"Map"),"") | CD77: =if(F77="REFUNDED",iferror(Vlookup(I77,'Listing SKU - Fill SKU Mapping'!A:C,3,false),"Map"),"") | CE77: =TEXT(G77,"YYYY") -> 2025 | CF77: =TEXT(G77,"MMMM") -> June | CG77: =IF(AND((G77-CG$1)>=0,(G77-CG$1)<=6), "This Week",IF(AND((G77-CG$1)>=-7,(G77-CG$1)<=-1), "Last Week",""))
A78: 200013155973046 | B78: 1 | C78: 109015921228380 | D78: 1 | F78: SALE | G78: 45817 | H78: 1 | I78: WM-KS-FRHC-8033-16SL | J78: 467129944255 | K78: Fuel Rider Set of 4 16 inch Silver Bolt-On Hubcaps With 6 Spoke Compatible With 2008-2013 Dodge Grand Caravan Standard Steel Wheel Covers | L78: 2038710 | O78: GA | R78: Baxley | S78: 31513 | T78: Marketplace standard | U78: 88.54 | V78: 76.24 | W78: 5.74 | X78: 7 | Y78: 81.98 | Z78: 0 | AA78: 0 | AB78: 0 | AC78: 0 | AD78: 0 | AE78: 0 | AF78: 0 | AG78: 0 | AH78: 0 | AI78: 0 | AJ78: 0 | AK78: 0 | AL78: 0 | AM78: 0 | AN78: 0 | AO78: 6.56 | AP78: 0 | AQ78: 0 | AR78: 0 | AS78: 0 | AT78: 0 | AU78: 0 | AV78: 0 | AW78: 0 | AX78: 0 | AY78: 0 | AZ78: 0 | BA78: 0 | BB78: 6.56 | BC78: Y | BG78: -8.2 | BH78: Wheels & Wheel Components | BI78: Tires & Wheels | BJ78: Automotive Wheel Covers & Hub Caps | BK78: PRO-119076-20.0 | BN78: N | BO78: Seller Fulfilled | BP78: Delivery | BQ78: New Seller Saving | BR78: 2.46 | BW78: =if(OR(F78="SALE",F78="REFUNDED"),IFERROR(Vlookup(I78,'Listing SKU - Fill SKU Mapping'!A:C,3,false),"Map"),"") -> Keystone | BX78: =IF(OR(F78="SALE",F78="REFUNDED")=TRUE,iferror(Vlookup(I78,'Listing SKU - Fill SKU Mapping'!A:B,2,false),"Map"),"") -> 45116S | BY78: =IF(OR(F78="SALE",F78="REFUNDED")=TRUE,iferror(Vlookup(I78,'Listing SKU - Fill SKU Mapping'!A:D,4,false),"Map"),"") -> 30.77 | BZ78: =If(BW78="Keystone",11.5,"") -> 11.5 | CA78: =IF(ISNUMBER(BY78)=TRUE,BY78+BZ78,"") -> 42.27 | CB78: =if(F78="SALE",V78-CA78,"") -> 33.97 | CC78: =if(F78="REFUNDED",iferror(Vlookup(I78,'Listing SKU - Fill SKU Mapping'!A:B,2,false),"Map"),"") | CD78: =if(F78="REFUNDED",iferror(Vlookup(I78,'Listing SKU - Fill SKU Mapping'!A:C,3,false),"Map"),"") | CE78: =TEXT(G78,"YYYY") -> 2025 | CF78: =TEXT(G78,"MMMM") -> June | CG78: =IF(AND((G78-CG$1)>=0,(G78-CG$1)<=6), "This Week",IF(AND((G78-CG$1)>=-7,(G78-CG$1)<=-1), "Last Week",""))
A79: 200013143554738 | B79: 1 | C79: 109014348663493 | D79: 1 | F79: REFUNDED | G79: 45806 | H79: 1 | I79: WM-FR-IMP-3957-17GB5DS | J79: 460776238265 | K79: Set of 4 17 inch Gloss Black Wheel Skins Covers Compatible with 13-16 Ford Fusion Impostors for 3957 Wheel Series | L79: 2038710 | R79: Pooler | S79: 31322 | U79: -104.84 | V79: -91.12 | W79: -6.86 | X79: 0 | Y79: 0 | Z79: -97.98 | AA79: 0 | AB79: 0 | AC79: 0 | AD79: 0 | AE79: 0 | AF79: 0 | AG79: 0 | AH79: 0 | AI79: 0 | AJ79: 0 | AK79: 0 | AL79: 0 | AM79: 0 | AN79: 0 | AO79: 0 | AP79: 0 | AQ79: 0 | AR79: 0 | AS79: 0 | AT79: -6.86 | AU79: 0 | AV79: 0 | AW79: 0 | AX79: 0 | AY79: 0 | AZ79: 0 | BA79: 0 | BB79: -6.86 | BC79: Y | BD79: Return Refund | BE79: 5010 | BH79: Wheels & Wheel Components | BI79: Tires & Wheels | BL79: 1000 | BM79: No Longer Wanted | BN79: N | BO79: Seller Fulfilled | BW79: =if(OR(F79="SALE",F79="REFUNDED"),IFERROR(Vlookup(I79,'Listing SKU - Fill SKU Mapping'!A:C,3,false),"Map"),"") -> Keystone | BX79: =IF(OR(F79="SALE",F79="REFUNDED")=TRUE,iferror(Vlookup(I79,'Listing SKU - Fill SKU Mapping'!A:B,2,false),"Map"),"") -> IMP372BLKN | BY79: =IF(OR(F79="SALE",F79="REFUNDED")=TRUE,iferror(Vlookup(I79,'Listing SKU - Fill SKU Mapping'!A:D,4,false),"Map"),"") -> 45.36 | BZ79: =If(BW79="Keystone",11.5,"") -> 11.5 | CA79: =IF(ISNUMBER(BY79)=TRUE,BY79+BZ79,"") -> 56.86 | CB79: =if(F79="SALE",V79-CA79,"") | CC79: =if(F79="REFUNDED",iferror(Vlookup(I79,'Listing SKU - Fill SKU Mapping'!A:B,2,false),"Map"),"") -> IMP372BLKN | CD79: =if(F79="REFUNDED",iferror(Vlookup(I79,'Listing SKU - Fill SKU Mapping'!A:C,3,false),"Map"),"") -> Keystone | CE79: =TEXT(G79,"YYYY") -> 2025 | CF79: =TEXT(G79,"MMMM") -> May | CG79: =IF(AND((G79-CG$1)>=0,(G79-CG$1)<=6), "This Week",IF(AND((G79-CG$1)>=-7,(G79-CG$1)<=-1), "Last Week",""))
A80: 200013139259493 | B80: 1 | C80: 109012880994491 | D80: 1 | F80: REFUNDED | G80: 45813 | H80: 1 | I80: WM-FR-IMP-3943-17GB5SP | J80: 460776234854 | K80: Set of 4 17 inch Gloss Black Wheel Skins Covers Compatible with 17-19 Ford Escape SE 13-16 Ford Escape Impostors for 3943 Wheel Series | L80: 2038710 | R80: Ponte Vedra | S80: 32082 | U80: -101.15 | V80: -88.33 | W80: -6.65 | X80: 0 | Y80: 0 | Z80: -94.98 | AA80: 0 | AB80: 0 | AC80: 0 | AD80: 0 | AE80: 0 | AF80: 0 | AG80: 0 | AH80: 0 | AI80: 0 | AJ80: 0 | AK80: 0 | AL80: 0 | AM80: 0 | AN80: 0 | AO80: 0 | AP80: 0 | AQ80: 0 | AR80: 0 | AS80: 0 | AT80: -6.17 | AU80: 0 | AV80: 0 | AW80: 0 | AX80: 0 | AY80: 0 | AZ80: 0 | BA80: 0 | BB80: -6.17 | BC80: Y | BD80: Return Refund | BE80: 5010 | BH80: Wheels & Wheel Components | BI80: Tires & Wheels | BL80: 1018 | BM80: Not as described/pictured | BN80: N | BO80: Seller Fulfilled | BW80: =if(OR(F80="SALE",F80="REFUNDED"),IFERROR(Vlookup(I80,'Listing SKU - Fill SKU Mapping'!A:C,3,false),"Map"),"") -> Keystone | BX80: =IF(OR(F80="SALE",F80="REFUNDED")=TRUE,iferror(Vlookup(I80,'Listing SKU - Fill SKU Mapping'!A:B,2,false),"Map"),"") -> IMP371BLK | BY80: =IF(OR(F80="SALE",F80="REFUNDED")=TRUE,iferror(Vlookup(I80,'Listing SKU - Fill SKU Mapping'!A:D,4,false),"Map"),"") -> 43.79 | BZ80: =If(BW80="Keystone",11.5,"") -> 11.5 | CA80: =IF(ISNUMBER(BY80)=TRUE,BY80+BZ80,"") -> 55.29 | CB80: =if(F80="SALE",V80-CA80,"") | CC80: =if(F80="REFUNDED",iferror(Vlookup(I80,'Listing SKU - Fill SKU Mapping'!A:B,2,false),"Map"),"") -> IMP371BLK | CD80: =if(F80="REFUNDED",iferror(Vlookup(I80,'Listing SKU - Fill SKU Mapping'!A:C,3,false),"Map"),"") -> Keystone | CE80: =TEXT(G80,"YYYY") -> 2025 | CF80: =TEXT(G80,"MMMM") -> June | CG80: =IF(AND((G80-CG$1)>=0,(G80-CG$1)<=6), "This Week",IF(AND((G80-CG$1)>=-7,(G80-CG$1)<=-1), "Last Week",""))
A81: 200013118195642 | B81: 1 | C81: 109016342342396 | D81: 1 | F81: SALE | G81: 45820 | H81: 1 | I81: WM-KS-FRHC-70811B-16SL | J81: 466885050606 | K81: Fuel Rider Set of 4 16 inch Silver Snap-On Hubcaps with 5 Double Spoke Compatible with 2011-2017 Nissan Quest S Standard Steel Wheel Covers | L81: 2038710 | O81: MD | R81: Cambridge | S81: 21613 | T81: Marketplace standard | U81: 93.26 | V81: 81.82 | W81: 6.16 | X81: 7 | Y81: 87.98 | Z81: 0 | AA81: 0 | AB81: 0 | AC81: 0 | AD81: 0 | AE81: 0 | AF81: 0 | AG81: 0 | AH81: 0 | AI81: 0 | AJ81: 0 | AK81: 0 | AL81: 0 | AM81: 0 | AN81: 0 | AO81: 5.28 | AP81: 0 | AQ81: 0 | AR81: 0 | AS81: 0 | AT81: 0 | AU81: 0 | AV81: 0 | AW81: 0 | AX81: 0 | AY81: 0 | AZ81: 0 | BA81: 0 | BB81: 5.28 | BC81: Y | BG81: -8.8 | BH81: Wheels & Wheel Components | BI81: Tires & Wheels | BJ81: Automotive Wheel Covers & Hub Caps | BK81: PRO-119076-20.0 | BN81: N | BO81: Seller Fulfilled | BP81: Delivery | BQ81: New Seller Saving | BR81: 2.64 | BW81: =if(OR(F81="SALE",F81="REFUNDED"),IFERROR(Vlookup(I81,'Listing SKU - Fill SKU Mapping'!A:C,3,false),"Map"),"") -> Keystone | BX81: =IF(OR(F81="SALE",F81="REFUNDED")=TRUE,iferror(Vlookup(I81,'Listing SKU - Fill SKU Mapping'!A:B,2,false),"Map"),"") -> 55316S | BY81: =IF(OR(F81="SALE",F81="REFUNDED")=TRUE,iferror(Vlookup(I81,'Listing SKU - Fill SKU Mapping'!A:D,4,false),"Map"),"") -> 34.71 | BZ81: =If(BW81="Keystone",11.5,"") -> 11.5 | CA81: =IF(ISNUMBER(BY81)=TRUE,BY81+BZ81,"") -> 46.21 | CB81: =if(F81="SALE",V81-CA81,"") -> 35.61 | CC81: =if(F81="REFUNDED",iferror(Vlookup(I81,'Listing SKU - Fill SKU Mapping'!A:B,2,false),"Map"),"") | CD81: =if(F81="REFUNDED",iferror(Vlookup(I81,'Listing SKU - Fill SKU Mapping'!A:C,3,false),"Map"),"") | CE81: =TEXT(G81,"YYYY") -> 2025 | CF81: =TEXT(G81,"MMMM") -> June | CG81: =IF(AND((G81-CG$1)>=0,(G81-CG$1)<=6), "This Week",IF(AND((G81-CG$1)>=-7,(G81-CG$1)<=-1), "Last Week",""))
A82: 200013082278000 | B82: 1 | C82: 109015696721454 | D82: 1 | F82: SALE | G82: 45812 | H82: 1 | I82: WM-KS-FRHC-61175-16SL | J82: 467129941919 | K82: Fuel Rider Set of 4 16 inch Silver Snap-On Hubcaps With 10 Spoke Compatible With 2015-2017 Toyota Camry Standard Steel Wheel Covers | L82: 2038710 | O82: AL | R82: Auburn | S82: 36830 | T82: Marketplace standard | U82: 83.14 | V82: 71.59 | W82: 5.39 | X82: 7 | Y82: 76.98 | Z82: 0 | AA82: 0 | AB82: 0 | AC82: 0 | AD82: 0 | AE82: 0 | AF82: 0 | AG82: 0 | AH82: 0 | AI82: 0 | AJ82: 0 | AK82: 0 | AL82: 0 | AM82: 0 | AN82: 0 | AO82: 6.16 | AP82: 0 | AQ82: 0 | AR82: 0 | AS82: 0 | AT82: 0 | AU82: 0 | AV82: 0 | AW82: 0 | AX82: 0 | AY82: 0 | AZ82: 0 | BA82: 0 | BB82: 6.16 | BC82: Y | BG82: -7.7 | BH82: Wheels & Wheel Components | BI82: Tires & Wheels | BJ82: Automotive Wheel Covers & Hub Caps | BK82: PRO-119076-19.0 | BN82: N | BO82: Seller Fulfilled | BP82: Delivery | BQ82: New Seller Saving | BR82: 2.31 | BW82: =if(OR(F82="SALE",F82="REFUNDED"),IFERROR(Vlookup(I82,'Listing SKU - Fill SKU Mapping'!A:C,3,false),"Map"),"") -> Keystone | BX82: =IF(OR(F82="SALE",F82="REFUNDED")=TRUE,iferror(Vlookup(I82,'Listing SKU - Fill SKU Mapping'!A:B,2,false),"Map"),"") -> 51416S | BY82: =IF(OR(F82="SALE",F82="REFUNDED")=TRUE,iferror(Vlookup(I82,'Listing SKU - Fill SKU Mapping'!A:D,4,false),"Map"),"") -> 28.01 | BZ82: =If(BW82="Keystone",11.5,"") -> 11.5 | CA82: =IF(ISNUMBER(BY82)=TRUE,BY82+BZ82,"") -> 39.51 | CB82: =if(F82="SALE",V82-CA82,"") -> 32.08 | CC82: =if(F82="REFUNDED",iferror(Vlookup(I82,'Listing SKU - Fill SKU Mapping'!A:B,2,false),"Map"),"") | CD82: =if(F82="REFUNDED",iferror(Vlookup(I82,'Listing SKU - Fill SKU Mapping'!A:C,3,false),"Map"),"") | CE82: =TEXT(G82,"YYYY") -> 2025 | CF82: =TEXT(G82,"MMMM") -> June | CG82: =IF(AND((G82-CG$1)>=0,(G82-CG$1)<=6), "This Week",IF(AND((G82-CG$1)>=-7,(G82-CG$1)<=-1), "Last Week",""))
A83: 200013055732988 | B83: 1 | C83: 109015282860754 | D83: 1 | F83: SALE | G83: 45809 | H83: 1 | I83: WM-KS-FRHC-53073-15SL | J83: 469971001575 | K83: Fuel Rider Set of 4 15 inch Silver Snap-On Hubcaps With 6 Spoke Compatible With 2007-2012 Nissan Sentra Standard Steel Wheel Covers | L83: 2038710 | O83: UT | R83: Spanish Fork | S83: 84660 | T83: Marketplace standard | U83: 51.55 | V83: 44.62 | W83: 3.36 | X83: 7 | Y83: 47.98 | Z83: 0 | AA83: 0 | AB83: 0 | AC83: 0 | AD83: 0 | AE83: 0 | AF83: 0 | AG83: 0 | AH83: 0 | AI83: 0 | AJ83: 0 | AK83: 0 | AL83: 0 | AM83: 0 | AN83: 0 | AO83: 3.57 | AP83: 0 | AQ83: 0 | AR83: 0 | AS83: 0 | AT83: 0 | AU83: 0 | AV83: 0 | AW83: 0 | AX83: 0 | AY83: 0 | AZ83: 0 | BA83: 0 | BB83: 3.57 | BC83: Y | BG83: -4.8 | BH83: Wheels & Wheel Components | BI83: Tires & Wheels | BJ83: Automotive Wheel Covers & Hub Caps | BK83: PRO-119076-18.0 | BN83: N | BO83: Seller Fulfilled | BP83: Delivery | BQ83: New Seller Saving | BR83: 1.44 | BW83: =if(OR(F83="SALE",F83="REFUNDED"),IFERROR(Vlookup(I83,'Listing SKU - Fill SKU Mapping'!A:C,3,false),"Map"),"") -> Keystone | BX83: =IF(OR(F83="SALE",F83="REFUNDED")=TRUE,iferror(Vlookup(I83,'Listing SKU - Fill SKU Mapping'!A:B,2,false),"Map"),"") -> 43615S | BY83: =IF(OR(F83="SALE",F83="REFUNDED")=TRUE,iferror(Vlookup(I83,'Listing SKU - Fill SKU Mapping'!A:D,4,false),"Map"),"") -> 14.99 | BZ83: =If(BW83="Keystone",11.5,"") -> 11.5 | CA83: =IF(ISNUMBER(BY83)=TRUE,BY83+BZ83,"") -> 26.49 | CB83: =if(F83="SALE",V83-CA83,"") -> 18.13 | CC83: =if(F83="REFUNDED",iferror(Vlookup(I83,'Listing SKU - Fill SKU Mapping'!A:B,2,false),"Map"),"") | CD83: =if(F83="REFUNDED",iferror(Vlookup(I83,'Listing SKU - Fill SKU Mapping'!A:C,3,false),"Map"),"") | CE83: =TEXT(G83,"YYYY") -> 2025 | CF83: =TEXT(G83,"MMMM") -> June | CG83: =IF(AND((G83-CG$1)>=0,(G83-CG$1)<=6), "This Week",IF(AND((G83-CG$1)>=-7,(G83-CG$1)<=-1), "Last Week",""))
A84: 200013001971046 | B84: 1 | C84: 109010999475878 | D84: 1 | F84: ADJMNT | G84: 45809 | H84: 1 | I84: WM-FR-IMP-5657-17GB5SP | J84: 460776230825 | K84: Set of 4 17 inch Gloss Black Wheel Skins Covers Compatible with 15-18 Chevrolet Silverado 1500 LS Impostors for 5657 Wheel Series | L84: 2038710 | O84: PA | R84: Mount Union | S84: 17066 | T84: Marketplace standard | U84: 0 | V84: -10.81 | W84: 0 | X84: 0 | Y84: 0 | Z84: 0 | AA84: 0 | AB84: 0 | AC84: 0 | AD84: 0 | AE84: 0 | AF84: 0 | AG84: 0 | AH84: 0 | AI84: 0 | AJ84: 0 | AK84: 0 | AL84: 0 | AM84: 0 | AN84: 0 | AO84: 0 | AP84: 0 | AQ84: 0 | AR84: 0 | AS84: 0 | AT84: 0 | AU84: 0 | AV84: 0 | AW84: 0 | AX84: 0 | AY84: 0 | AZ84: 0 | BA84: 0 | BB84: 0 | BC84: Y | BD84: Walmart Return Shipping Charge | BE84: 5013 | BH84: Wheels & Wheel Components | BI84: Tires & Wheels | BN84: N | BO84: Seller Fulfilled | BW84: =if(OR(F84="SALE",F84="REFUNDED"),IFERROR(Vlookup(I84,'Listing SKU - Fill SKU Mapping'!A:C,3,false),"Map"),"") | BX84: =IF(OR(F84="SALE",F84="REFUNDED")=TRUE,iferror(Vlookup(I84,'Listing SKU - Fill SKU Mapping'!A:B,2,false),"Map"),"") | BY84: =IF(OR(F84="SALE",F84="REFUNDED")=TRUE,iferror(Vlookup(I84,'Listing SKU - Fill SKU Mapping'!A:D,4,false),"Map"),"") | BZ84: =If(BW84="Keystone",11.5,"") | CA84: =IF(ISNUMBER(BY84)=TRUE,BY84+BZ84,"") | CB84: =if(F84="SALE",V84-CA84,"") | CC84: =if(F84="REFUNDED",iferror(Vlookup(I84,'Listing SKU - Fill SKU Mapping'!A:B,2,false),"Map"),"") | CD84: =if(F84="REFUNDED",iferror(Vlookup(I84,'Listing SKU - Fill SKU Mapping'!A:C,3,false),"Map"),"") | CE84: =TEXT(G84,"YYYY") -> 2025 | CF84: =TEXT(G84,"MMMM") -> June | CG84: =IF(AND((G84-CG$1)>=0,(G84-CG$1)<=6), "This Week",IF(AND((G84-CG$1)>=-7,(G84-CG$1)<=-1), "Last Week",""))
A85: 200010000000000 | B85: 1 | C85: 109020000000000 | D85: 1 | F85: SALE | G85: 45835 | H85: 1 | I85: WM-KS-FRHC-61088-14SL | J85: 467129950058 | T85: Marketplace standard | U85: 56 | V85: 51.13 | W85: 3.85 | X85: 7 | Y85: 51.9 | Z85: 0 | AA85: 0 | AB85: 0 | AC85: 0 | AD85: 0 | AE85: 0 | AF85: 0 | AG85: 0 | AH85: 0 | AI85: 0 | AJ85: 0 | AK85: 0 | AL85: 0 | AM85: 0 | AN85: 0 | AO85: 4.1 | AP85: 0 | AQ85: 0 | AR85: 0 | AS85: 0 | AT85: 0 | AU85: 0 | AV85: 0 | AW85: 0 | AX85: 0 | AY85: 0 | AZ85: 0 | BA85: 0 | BB85: 4.1 | BC85: Y | BF85: 54.98 | BG85: -5.5 | BH85: Wheels & Wheel Components | BI85: Tires & Wheels | BJ85: Automotive Wheel Covers & Hub Caps | BK85: PRO-119076-23.0 | BN85: N | BO85: Seller Fulfilled | BP85: Delivery | BQ85: PRO | BR85: 1.65 | BT85: -3.08 | BU85: PricingIncentives | BW85: =if(OR(F85="SALE",F85="REFUNDED"),IFERROR(Vlookup(I85,'Listing SKU - Fill SKU Mapping'!A:C,3,false),"Map"),"") -> Keystone | BX85: =IF(OR(F85="SALE",F85="REFUNDED")=TRUE,iferror(Vlookup(I85,'Listing SKU - Fill SKU Mapping'!A:B,2,false),"Map"),"") -> B87714S | BY85: =IF(OR(F85="SALE",F85="REFUNDED")=TRUE,iferror(Vlookup(I85,'Listing SKU - Fill SKU Mapping'!A:D,4,false),"Map"),"") -> 14.2 | BZ85: =If(BW85="Keystone",11.5,"") -> 11.5 | CA85: =IF(ISNUMBER(BY85)=TRUE,BY85+BZ85,"") -> 25.7 | CB85: =if(F85="SALE",V85-CA85,"") -> 25.43 | CC85: =if(F85="REFUNDED",iferror(Vlookup(I85,'Listing SKU - Fill SKU Mapping'!A:B,2,false),"Map"),"") | CD85: =if(F85="REFUNDED",iferror(Vlookup(I85,'Listing SKU - Fill SKU Mapping'!A:C,3,false),"Map"),"") | CE85: =TEXT(G85,"YYYY") -> 2025 | CF85: =TEXT(G85,"MMMM") -> June | CG85: =IF(AND((G85-CG$1)>=0,(G85-CG$1)<=6), "This Week",IF(AND((G85-CG$1)>=-7,(G85-CG$1)<=-1), "Last Week",""))
A86: 200010000000000 | B86: 1 | C86: 109020000000000 | D86: 1 | F86: SALE | G86: 45831 | H86: 1 | I86: WM-KS-FRHC-3021-16SL | J86: 467129943173 | T86: Marketplace standard | U86: 80.89 | V86: 78.1 | W86: 5.88 | X86: 7 | Y86: 74.9 | Z86: 0 | AA86: 0 | AB86: 0 | AC86: 0 | AD86: 0 | AE86: 0 | AF86: 0 | AG86: 0 | AH86: 0 | AI86: 0 | AJ86: 0 | AK86: 0 | AL86: 0 | AM86: 0 | AN86: 0 | AO86: 5.99 | AP86: 0 | AQ86: 0 | AR86: 0 | AS86: 0 | AT86: 0 | AU86: 0 | AV86: 0 | AW86: 0 | AX86: 0 | AY86: 0 | AZ86: 0 | BA86: 0 | BB86: 5.99 | BC86: Y | BF86: 83.98 | BG86: -8.4 | BH86: Wheels & Wheel Components | BI86: Tires & Wheels | BJ86: Automotive Wheel Covers & Hub Caps | BK86: PRO-119076-22.0 | BN86: N | BO86: Seller Fulfilled | BP86: Delivery | BQ86: PRO | BR86: 2.52 | BT86: -9.08 | BU86: PricingIncentives | BW86: =if(OR(F86="SALE",F86="REFUNDED"),IFERROR(Vlookup(I86,'Listing SKU - Fill SKU Mapping'!A:C,3,false),"Map"),"") -> Keystone | BX86: =IF(OR(F86="SALE",F86="REFUNDED")=TRUE,iferror(Vlookup(I86,'Listing SKU - Fill SKU Mapping'!A:B,2,false),"Map"),"") -> 43116S | BY86: =IF(OR(F86="SALE",F86="REFUNDED")=TRUE,iferror(Vlookup(I86,'Listing SKU - Fill SKU Mapping'!A:D,4,false),"Map"),"") -> 32.35 | BZ86: =If(BW86="Keystone",11.5,"") -> 11.5 | CA86: =IF(ISNUMBER(BY86)=TRUE,BY86+BZ86,"") -> 43.85 | CB86: =if(F86="SALE",V86-CA86,"") -> 34.25 | CC86: =if(F86="REFUNDED",iferror(Vlookup(I86,'Listing SKU - Fill SKU Mapping'!A:B,2,false),"Map"),"") | CD86: =if(F86="REFUNDED",iferror(Vlookup(I86,'Listing SKU - Fill SKU Mapping'!A:C,3,false),"Map"),"") | CE86: =TEXT(G86,"YYYY") -> 2025 | CF86: =TEXT(G86,"MMMM") -> June | CG86: =IF(AND((G86-CG$1)>=0,(G86-CG$1)<=6), "This Week",IF(AND((G86-CG$1)>=-7,(G86-CG$1)<=-1), "Last Week",""))
A87: 200010000000000 | B87: 1 | C87: 109020000000000 | D87: 1 | F87: SALE | G87: 45828 | H87: 1 | I87: WM-FR-IMP-8069-17GB8H | J87: 460776235141 | T87: Marketplace standard | U87: 124.1 | V87: 107.86 | W87: 8.12 | X87: 7 | Y87: 115.98 | Z87: 0 | AA87: 0 | AB87: 0 | AC87: 0 | AD87: 0 | AE87: 0 | AF87: 0 | AG87: 0 | AH87: 0 | AI87: 0 | AJ87: 0 | AK87: 0 | AL87: 0 | AM87: 0 | AN87: 0 | AO87: 8.12 | AP87: 0 | AQ87: 0 | AR87: 0 | AS87: 0 | AT87: 0 | AU87: 0 | AV87: 0 | AW87: 0 | AX87: 0 | AY87: 0 | AZ87: 0 | BA87: 0 | BB87: 8.12 | BC87: Y | BG87: -11.6 | BH87: Wheels & Wheel Components | BI87: Tires & Wheels | BJ87: Automotive Wheel Covers & Hub Caps | BK87: PRO-119076-22.0 | BN87: N | BO87: Seller Fulfilled | BP87: Delivery | BQ87: New Seller Saving | BR87: 3.48 | BW87: =if(OR(F87="SALE",F87="REFUNDED"),IFERROR(Vlookup(I87,'Listing SKU - Fill SKU Mapping'!A:C,3,false),"Map"),"") -> Keystone | BX87: =IF(OR(F87="SALE",F87="REFUNDED")=TRUE,iferror(Vlookup(I87,'Listing SKU - Fill SKU Mapping'!A:B,2,false),"Map"),"") -> IMP64GBLK | BY87: =IF(OR(F87="SALE",F87="REFUNDED")=TRUE,iferror(Vlookup(I87,'Listing SKU - Fill SKU Mapping'!A:D,4,false),"Map"),"") -> 54.44 | BZ87: =If(BW87="Keystone",11.5,"") -> 11.5 | CA87: =IF(ISNUMBER(BY87)=TRUE,BY87+BZ87,"") -> 65.94 | CB87: =if(F87="SALE",V87-CA87,"") -> 41.92 | CC87: =if(F87="REFUNDED",iferror(Vlookup(I87,'Listing SKU - Fill SKU Mapping'!A:B,2,false),"Map"),"") | CD87: =if(F87="REFUNDED",iferror(Vlookup(I87,'Listing SKU - Fill SKU Mapping'!A:C,3,false),"Map"),"") | CE87: =TEXT(G87,"YYYY") -> 2025 | CF87: =TEXT(G87,"MMMM") -> June | CG87: =IF(AND((G87-CG$1)>=0,(G87-CG$1)<=6), "This Week",IF(AND((G87-CG$1)>=-7,(G87-CG$1)<=-1), "Last Week",""))
A88: 200010000000000 | B88: 1 | C88: 109020000000000 | D88: 1 | F88: SALE | G88: 45824 | H88: 1 | I88: WM-KS-FRHC-3276-17SL | J88: 467129950768 | T88: Marketplace standard | U88: 90.79 | V88: 79.96 | W88: 6.02 | X88: 7 | Y88: 85.98 | Z88: 0 | AA88: 0 | AB88: 0 | AC88: 0 | AD88: 0 | AE88: 0 | AF88: 0 | AG88: 0 | AH88: 0 | AI88: 0 | AJ88: 0 | AK88: 0 | AL88: 0 | AM88: 0 | AN88: 0 | AO88: 4.81 | AP88: 0 | AQ88: 0 | AR88: 0 | AS88: 0 | AT88: 0 | AU88: 0 | AV88: 0 | AW88: 0 | AX88: 0 | AY88: 0 | AZ88: 0 | BA88: 0 | BB88: 4.81 | BC88: Y | BG88: -8.6 | BH88: Wheels & Wheel Components | BI88: Tires & Wheels | BJ88: Automotive Wheel Covers & Hub Caps | BK88: PRO-119076-21.0 | BN88: N | BO88: Seller Fulfilled | BP88: Delivery | BQ88: New Seller Saving | BR88: 2.58 | BW88: =if(OR(F88="SALE",F88="REFUNDED"),IFERROR(Vlookup(I88,'Listing SKU - Fill SKU Mapping'!A:C,3,false),"Map"),"") -> Keystone | BX88: =IF(OR(F88="SALE",F88="REFUNDED")=TRUE,iferror(Vlookup(I88,'Listing SKU - Fill SKU Mapping'!A:B,2,false),"Map"),"") -> 43517S | BY88: =IF(OR(F88="SALE",F88="REFUNDED")=TRUE,iferror(Vlookup(I88,'Listing SKU - Fill SKU Mapping'!A:D,4,false),"Map"),"") -> 33.53 | BZ88: =If(BW88="Keystone",11.5,"") -> 11.5 | CA88: =IF(ISNUMBER(BY88)=TRUE,BY88+BZ88,"") -> 45.03 | CB88: =if(F88="SALE",V88-CA88,"") -> 34.93 | CC88: =if(F88="REFUNDED",iferror(Vlookup(I88,'Listing SKU - Fill SKU Mapping'!A:B,2,false),"Map"),"") | CD88: =if(F88="REFUNDED",iferror(Vlookup(I88,'Listing SKU - Fill SKU Mapping'!A:C,3,false),"Map"),"") | CE88: =TEXT(G88,"YYYY") -> 2025 | CF88: =TEXT(G88,"MMMM") -> June | CG88: =IF(AND((G88-CG$1)>=0,(G88-CG$1)<=6), "This Week",IF(AND((G88-CG$1)>=-7,(G88-CG$1)<=-1), "Last Week",""))
A89: 200010000000000 | B89: 1 | C89: 109020000000000 | D89: 1 | F89: SALE | G89: 45826 | H89: 1 | I89: WM-KS-FRHC-53089-16GBK | J89: 467129914746 | T89: Marketplace standard | U89: 102.34 | V89: 88.33 | W89: 6.65 | X89: 7 | Y89: 94.98 | Z89: 0 | AA89: 0 | AB89: 0 | AC89: 0 | AD89: 0 | AE89: 0 | AF89: 0 | AG89: 0 | AH89: 0 | AI89: 0 | AJ89: 0 | AK89: 0 | AL89: 0 | AM89: 0 | AN89: 0 | AO89: 7.36 | AP89: 0 | AQ89: 0 | AR89: 0 | AS89: 0 | AT89: 0 | AU89: 0 | AV89: 0 | AW89: 0 | AX89: 0 | AY89: 0 | AZ89: 0 | BA89: 0 | BB89: 7.36 | BC89: Y | BG89: -9.5 | BH89: Wheels & Wheel Components | BI89: Tires & Wheels | BJ89: Automotive Wheel Covers & Hub Caps | BK89: PRO-119076-21.0 | BN89: N | BO89: Seller Fulfilled | BP89: Delivery | BQ89: New Seller Saving | BR89: 2.85 | BW89: =if(OR(F89="SALE",F89="REFUNDED"),IFERROR(Vlookup(I89,'Listing SKU - Fill SKU Mapping'!A:C,3,false),"Map"),"") -> Keystone | BX89: =IF(OR(F89="SALE",F89="REFUNDED")=TRUE,iferror(Vlookup(I89,'Listing SKU - Fill SKU Mapping'!A:B,2,false),"Map"),"") -> 52116BLK | BY89: =IF(OR(F89="SALE",F89="REFUNDED")=TRUE,iferror(Vlookup(I89,'Listing SKU - Fill SKU Mapping'!A:D,4,false),"Map"),"") -> 39.05 | BZ89: =If(BW89="Keystone",11.5,"") -> 11.5 | CA89: =IF(ISNUMBER(BY89)=TRUE,BY89+BZ89,"") -> 50.55 | CB89: =if(F89="SALE",V89-CA89,"") -> 37.78 | CC89: =if(F89="REFUNDED",iferror(Vlookup(I89,'Listing SKU - Fill SKU Mapping'!A:B,2,false),"Map"),"") | CD89: =if(F89="REFUNDED",iferror(Vlookup(I89,'Listing SKU - Fill SKU Mapping'!A:C,3,false),"Map"),"") | CE89: =TEXT(G89,"YYYY") -> 2025 | CF89: =TEXT(G89,"MMMM") -> June | CG89: =IF(AND((G89-CG$1)>=0,(G89-CG$1)<=6), "This Week",IF(AND((G89-CG$1)>=-7,(G89-CG$1)<=-1), "Last Week",""))
A90: 200010000000000 | B90: 1 | C90: 109020000000000 | D90: 1 | F90: SALE | G90: 45827 | H90: 1 | I90: WM-KS-FRHC-53072-15SL | J90: 467129917358 | T90: Marketplace standard | U90: 60 | V90: 52.99 | W90: 3.99 | X90: 7 | Y90: 56.98 | Z90: 0 | AA90: 0 | AB90: 0 | AC90: 0 | AD90: 0 | AE90: 0 | AF90: 0 | AG90: 0 | AH90: 0 | AI90: 0 | AJ90: 0 | AK90: 0 | AL90: 0 | AM90: 0 | AN90: 0 | AO90: 3.02 | AP90: 0 | AQ90: 0 | AR90: 0 | AS90: 0 | AT90: 0 | AU90: 0 | AV90: 0 | AW90: 0 | AX90: 0 | AY90: 0 | AZ90: 0 | BA90: 0 | BB90: 3.02 | BC90: Y | BG90: -5.7 | BH90: Wheels & Wheel Components | BI90: Tires & Wheels | BJ90: Automotive Wheel Covers & Hub Caps | BK90: PRO-119076-21.0 | BN90: N | BO90: Seller Fulfilled | BP90: Delivery | BQ90: New Seller Saving | BR90: 1.71 | BW90: =if(OR(F90="SALE",F90="REFUNDED"),IFERROR(Vlookup(I90,'Listing SKU - Fill SKU Mapping'!A:C,3,false),"Map"),"") -> Keystone | BX90: =IF(OR(F90="SALE",F90="REFUNDED")=TRUE,iferror(Vlookup(I90,'Listing SKU - Fill SKU Mapping'!A:B,2,false),"Map"),"") -> 44715S | BY90: =IF(OR(F90="SALE",F90="REFUNDED")=TRUE,iferror(Vlookup(I90,'Listing SKU - Fill SKU Mapping'!A:D,4,false),"Map"),"") -> 14.99 | BZ90: =If(BW90="Keystone",11.5,"") -> 11.5 | CA90: =IF(ISNUMBER(BY90)=TRUE,BY90+BZ90,"") -> 26.49 | CB90: =if(F90="SALE",V90-CA90,"") -> 26.5 | CC90: =if(F90="REFUNDED",iferror(Vlookup(I90,'Listing SKU - Fill SKU Mapping'!A:B,2,false),"Map"),"") | CD90: =if(F90="REFUNDED",iferror(Vlookup(I90,'Listing SKU - Fill SKU Mapping'!A:C,3,false),"Map"),"") | CE90: =TEXT(G90,"YYYY") -> 2025 | CF90: =TEXT(G90,"MMMM") -> June | CG90: =IF(AND((G90-CG$1)>=0,(G90-CG$1)<=6), "This Week",IF(AND((G90-CG$1)>=-7,(G90-CG$1)<=-1), "Last Week",""))
A91: 200010000000000 | B91: 5 | C91: 109020000000000 | D91: 5 | F91: SALE | G91: 45831 | H91: 1 | I91: WM-KS-FRTR-69450-15SL | J91: 467620062434 | T91: Marketplace standard | U91: 41.12 | V91: 35.33 | W91: 2.66 | X91: 7 | Y91: 37.99 | Z91: 0 | AA91: 0 | AB91: 0 | AC91: 0 | AD91: 0 | AE91: 0 | AF91: 0 | AG91: 0 | AH91: 0 | AI91: 0 | AJ91: 0 | AK91: 0 | AL91: 0 | AM91: 0 | AN91: 0 | AO91: 3.13 | AP91: 0 | AQ91: 0 | AR91: 0 | AS91: 0 | AT91: 0 | AU91: 0 | AV91: 0 | AW91: 0 | AX91: 0 | AY91: 0 | AZ91: 0 | BA91: 0 | BB91: 3.13 | BC91: Y | BG91: -3.8 | BH91: Wheels & Wheel Components | BI91: Tires & Wheels | BJ91: Wheel Trim Rings | BK91: PRO-119076-22.0 | BN91: N | BO91: Seller Fulfilled | BP91: Delivery | BQ91: New Seller Saving | BR91: 1.14 | BW91: =if(OR(F91="SALE",F91="REFUNDED"),IFERROR(Vlookup(I91,'Listing SKU - Fill SKU Mapping'!A:C,3,false),"Map"),"") -> Keystone | BX91: =IF(OR(F91="SALE",F91="REFUNDED")=TRUE,iferror(Vlookup(I91,'Listing SKU - Fill SKU Mapping'!A:B,2,false),"Map"),"") -> 1515TP | BY91: =IF(OR(F91="SALE",F91="REFUNDED")=TRUE,iferror(Vlookup(I91,'Listing SKU - Fill SKU Mapping'!A:D,4,false),"Map"),"") -> 14.99 | BZ91: =If(BW91="Keystone",11.5,"") -> 11.5 | CA91: =IF(ISNUMBER(BY91)=TRUE,BY91+BZ91,"") -> 26.49 | CB91: =if(F91="SALE",V91-CA91,"") -> 8.84 | CC91: =if(F91="REFUNDED",iferror(Vlookup(I91,'Listing SKU - Fill SKU Mapping'!A:B,2,false),"Map"),"") | CD91: =if(F91="REFUNDED",iferror(Vlookup(I91,'Listing SKU - Fill SKU Mapping'!A:C,3,false),"Map"),"") | CE91: =TEXT(G91,"YYYY") -> 2025 | CF91: =TEXT(G91,"MMMM") -> June | CG91: =IF(AND((G91-CG$1)>=0,(G91-CG$1)<=6), "This Week",IF(AND((G91-CG$1)>=-7,(G91-CG$1)<=-1), "Last Week",""))
A92: 200010000000000 | B92: 1 | C92: 109020000000000 | D92: 1 | F92: SALE | G92: 45833 | H92: 1 | I92: WM-FR-IMP-2380-17GB5SP | J92: 460776228945 | T92: Marketplace standard | U92: 107.54 | V92: 93.91 | W92: 7.07 | X92: 7 | Y92: 100.98 | Z92: 0 | AA92: 0 | AB92: 0 | AC92: 0 | AD92: 0 | AE92: 0 | AF92: 0 | AG92: 0 | AH92: 0 | AI92: 0 | AJ92: 0 | AK92: 0 | AL92: 0 | AM92: 0 | AN92: 0 | AO92: 6.56 | AP92: 0 | AQ92: 0 | AR92: 0 | AS92: 0 | AT92: 0 | AU92: 0 | AV92: 0 | AW92: 0 | AX92: 0 | AY92: 0 | AZ92: 0 | BA92: 0 | BB92: 6.56 | BC92: Y | BG92: -10.1 | BH92: Wheels & Wheel Components | BI92: Tires & Wheels | BJ92: Automotive Wheel Covers & Hub Caps | BK92: PRO-119076-22.0 | BN92: N | BO92: Seller Fulfilled | BP92: Delivery | BQ92: New Seller Saving | BR92: 3.03 | BW92: =if(OR(F92="SALE",F92="REFUNDED"),IFERROR(Vlookup(I92,'Listing SKU - Fill SKU Mapping'!A:C,3,false),"Map"),"") -> Keystone | BX92: =IF(OR(F92="SALE",F92="REFUNDED")=TRUE,iferror(Vlookup(I92,'Listing SKU - Fill SKU Mapping'!A:B,2,false),"Map"),"") -> IMP373BLK | BY92: =IF(OR(F92="SALE",F92="REFUNDED")=TRUE,iferror(Vlookup(I92,'Listing SKU - Fill SKU Mapping'!A:D,4,false),"Map"),"") -> 44.97 | BZ92: =If(BW92="Keystone",11.5,"") -> 11.5 | CA92: =IF(ISNUMBER(BY92)=TRUE,BY92+BZ92,"") -> 56.47 | CB92: =if(F92="SALE",V92-CA92,"") -> 37.44 | CC92: =if(F92="REFUNDED",iferror(Vlookup(I92,'Listing SKU - Fill SKU Mapping'!A:B,2,false),"Map"),"") | CD92: =if(F92="REFUNDED",iferror(Vlookup(I92,'Listing SKU - Fill SKU Mapping'!A:C,3,false),"Map"),"") | CE92: =TEXT(G92,"YYYY") -> 2025 | CF92: =TEXT(G92,"MMMM") -> June | CG92: =IF(AND((G92-CG$1)>=0,(G92-CG$1)<=6), "This Week",IF(AND((G92-CG$1)>=-7,(G92-CG$1)<=-1), "Last Week",""))
A93: 200010000000000 | B93: 1 | C93: 109020000000000 | D93: 1 | F93: SALE | G93: 45824 | H93: 1 | I93: WM-KS-FRHC-53088-16CH | J93: 467129945405 | T93: Marketplace standard | U93: 94.93 | V93: 92.05 | W93: 6.93 | X93: 7 | Y93: 87.9 | Z93: 0 | AA93: 0 | AB93: 0 | AC93: 0 | AD93: 0 | AE93: 0 | AF93: 0 | AG93: 0 | AH93: 0 | AI93: 0 | AJ93: 0 | AK93: 0 | AL93: 0 | AM93: 0 | AN93: 0 | AO93: 7.03 | AP93: 0 | AQ93: 0 | AR93: 0 | AS93: 0 | AT93: 0 | AU93: 0 | AV93: 0 | AW93: 0 | AX93: 0 | AY93: 0 | AZ93: 0 | BA93: 0 | BB93: 7.03 | BC93: Y | BF93: 98.98 | BG93: -9.9 | BH93: Wheels & Wheel Components | BI93: Tires & Wheels | BJ93: Automotive Wheel Covers & Hub Caps | BK93: PRO-119076-21.0 | BN93: N | BO93: Seller Fulfilled | BP93: Delivery | BQ93: PRO | BR93: 2.97 | BT93: -11.08 | BU93: PricingIncentives | BW93: =if(OR(F93="SALE",F93="REFUNDED"),IFERROR(Vlookup(I93,'Listing SKU - Fill SKU Mapping'!A:C,3,false),"Map"),"") -> Keystone | BX93: =IF(OR(F93="SALE",F93="REFUNDED")=TRUE,iferror(Vlookup(I93,'Listing SKU - Fill SKU Mapping'!A:B,2,false),"Map"),"") -> 50516C | BY93: =IF(OR(F93="SALE",F93="REFUNDED")=TRUE,iferror(Vlookup(I93,'Listing SKU - Fill SKU Mapping'!A:D,4,false),"Map"),"") -> 41.42 | BZ93: =If(BW93="Keystone",11.5,"") -> 11.5 | CA93: =IF(ISNUMBER(BY93)=TRUE,BY93+BZ93,"") -> 52.92 | CB93: =if(F93="SALE",V93-CA93,"") -> 39.13 | CC93: =if(F93="REFUNDED",iferror(Vlookup(I93,'Listing SKU - Fill SKU Mapping'!A:B,2,false),"Map"),"") | CD93: =if(F93="REFUNDED",iferror(Vlookup(I93,'Listing SKU - Fill SKU Mapping'!A:C,3,false),"Map"),"") | CE93: =TEXT(G93,"YYYY") -> 2025 | CF93: =TEXT(G93,"MMMM") -> June | CG93: =IF(AND((G93-CG$1)>=0,(G93-CG$1)<=6), "This Week",IF(AND((G93-CG$1)>=-7,(G93-CG$1)<=-1), "Last Week",""))
A94: 200010000000000 | B94: 1 | C94: 109020000000000 | D94: 1 | F94: SALE | G94: 45835 | H94: 1 | I94: WM-KS-FRHC-61173-16SL | J94: 467129950621 | T94: Marketplace standard | U94: 75.98 | V94: 76.24 | W94: 5.74 | X94: 7 | Y94: 72.9 | Z94: 0 | AA94: 0 | AB94: 0 | AC94: 0 | AD94: 0 | AE94: 0 | AF94: 0 | AG94: 0 | AH94: 0 | AI94: 0 | AJ94: 0 | AK94: 0 | AL94: 0 | AM94: 0 | AN94: 0 | AO94: 3.08 | AP94: 0 | AQ94: 0 | AR94: 0 | AS94: 0 | AT94: 0 | AU94: 0 | AV94: 0 | AW94: 0 | AX94: 0 | AY94: 0 | AZ94: 0 | BA94: 0 | BB94: 3.08 | BC94: Y | BF94: 81.98 | BG94: -8.2 | BH94: Wheels & Wheel Components | BI94: Tires & Wheels | BJ94: Automotive Wheel Covers & Hub Caps | BK94: PRO-119076-22.0 | BN94: N | BO94: Seller Fulfilled | BP94: Delivery | BQ94: PRO | BR94: 2.46 | BT94: -9.08 | BU94: PricingIncentives | BW94: =if(OR(F94="SALE",F94="REFUNDED"),IFERROR(Vlookup(I94,'Listing SKU - Fill SKU Mapping'!A:C,3,false),"Map"),"") -> Keystone | BX94: =IF(OR(F94="SALE",F94="REFUNDED")=TRUE,iferror(Vlookup(I94,'Listing SKU - Fill SKU Mapping'!A:B,2,false),"Map"),"") -> 52316S | BY94: =IF(OR(F94="SALE",F94="REFUNDED")=TRUE,iferror(Vlookup(I94,'Listing SKU - Fill SKU Mapping'!A:D,4,false),"Map"),"") -> 30.77 | BZ94: =If(BW94="Keystone",11.5,"") -> 11.5 | CA94: =IF(ISNUMBER(BY94)=TRUE,BY94+BZ94,"") -> 42.27 | CB94: =if(F94="SALE",V94-CA94,"") -> 33.97 | CC94: =if(F94="REFUNDED",iferror(Vlookup(I94,'Listing SKU - Fill SKU Mapping'!A:B,2,false),"Map"),"") | CD94: =if(F94="REFUNDED",iferror(Vlookup(I94,'Listing SKU - Fill SKU Mapping'!A:C,3,false),"Map"),"") | CE94: =TEXT(G94,"YYYY") -> 2025 | CF94: =TEXT(G94,"MMMM") -> June | CG94: =IF(AND((G94-CG$1)>=0,(G94-CG$1)<=6), "This Week",IF(AND((G94-CG$1)>=-7,(G94-CG$1)<=-1), "Last Week",""))
A95: 200010000000000 | B95: 1 | C95: 109020000000000 | D95: 1 | F95: SALE | G95: 45831 | H95: 1 | I95: WM-KS-FRHC-61173-16SL | J95: 467129950621 | T95: Marketplace standard | U95: 78.91 | V95: 76.24 | W95: 5.74 | X95: 7 | Y95: 72.9 | Z95: 0 | AA95: 0 | AB95: 0 | AC95: 0 | AD95: 0 | AE95: 0 | AF95: 0 | AG95: 0 | AH95: 0 | AI95: 0 | AJ95: 0 | AK95: 0 | AL95: 0 | AM95: 0 | AN95: 0 | AO95: 6.01 | AP95: 0 | AQ95: 0 | AR95: 0 | AS95: 0 | AT95: 0 | AU95: 0 | AV95: 0 | AW95: 0 | AX95: 0 | AY95: 0 | AZ95: 0 | BA95: 0 | BB95: 6.01 | BC95: Y | BF95: 81.98 | BG95: -8.2 | BH95: Wheels & Wheel Components | BI95: Tires & Wheels | BJ95: Automotive Wheel Covers & Hub Caps | BK95: PRO-119076-22.0 | BN95: N | BO95: Seller Fulfilled | BP95: Delivery | BQ95: PRO | BR95: 2.46 | BT95: -9.08 | BU95: PricingIncentives | BW95: =if(OR(F95="SALE",F95="REFUNDED"),IFERROR(Vlookup(I95,'Listing SKU - Fill SKU Mapping'!A:C,3,false),"Map"),"") -> Keystone | BX95: =IF(OR(F95="SALE",F95="REFUNDED")=TRUE,iferror(Vlookup(I95,'Listing SKU - Fill SKU Mapping'!A:B,2,false),"Map"),"") -> 52316S | BY95: =IF(OR(F95="SALE",F95="REFUNDED")=TRUE,iferror(Vlookup(I95,'Listing SKU - Fill SKU Mapping'!A:D,4,false),"Map"),"") -> 30.77 | BZ95: =If(BW95="Keystone",11.5,"") -> 11.5 | CA95: =IF(ISNUMBER(BY95)=TRUE,BY95+BZ95,"") -> 42.27 | CB95: =if(F95="SALE",V95-CA95,"") -> 33.97 | CC95: =if(F95="REFUNDED",iferror(Vlookup(I95,'Listing SKU - Fill SKU Mapping'!A:B,2,false),"Map"),"") | CD95: =if(F95="REFUNDED",iferror(Vlookup(I95,'Listing SKU - Fill SKU Mapping'!A:C,3,false),"Map"),"") | CE95: =TEXT(G95,"YYYY") -> 2025 | CF95: =TEXT(G95,"MMMM") -> June | CG95: =IF(AND((G95-CG$1)>=0,(G95-CG$1)<=6), "This Week",IF(AND((G95-CG$1)>=-7,(G95-CG$1)<=-1), "Last Week",""))
A96: 200010000000000 | B96: 1 | C96: 109020000000000 | D96: 1 | F96: SALE | G96: 45834 | H96: 1 | I96: WM-KS-FRCC-799-CH | J96: 468102659623 | T96: Marketplace standard | U96: 70.32 | V96: 61.33 | W96: 4.62 | X96: 7 | Y96: 65.95 | Z96: 0 | AA96: 0 | AB96: 0 | AC96: 0 | AD96: 0 | AE96: 0 | AF96: 0 | AG96: 0 | AH96: 0 | AI96: 0 | AJ96: 0 | AK96: 0 | AL96: 0 | AM96: 0 | AN96: 0 | AO96: 4.37 | AP96: 0 | AQ96: 0 | AR96: 0 | AS96: 0 | AT96: 0 | AU96: 0 | AV96: 0 | AW96: 0 | AX96: 0 | AY96: 0 | AZ96: 0 | BA96: 0 | BB96: 4.37 | BC96: Y | BG96: -6.6 | BH96: Wheels & Wheel Components | BI96: Tires & Wheels | BJ96: Automotive Wheel Covers & Hub Caps | BK96: PRO-119076-22.0 | BN96: N | BO96: Seller Fulfilled | BP96: Delivery | BQ96: New Seller Saving | BR96: 1.98 | BW96: =if(OR(F96="SALE",F96="REFUNDED"),IFERROR(Vlookup(I96,'Listing SKU - Fill SKU Mapping'!A:C,3,false),"Map"),"") -> Keystone | BX96: =IF(OR(F96="SALE",F96="REFUNDED")=TRUE,iferror(Vlookup(I96,'Listing SKU - Fill SKU Mapping'!A:B,2,false),"Map"),"") -> C2030 | BY96: =IF(OR(F96="SALE",F96="REFUNDED")=TRUE,iferror(Vlookup(I96,'Listing SKU - Fill SKU Mapping'!A:D,4,false),"Map"),"") -> 28.4 | BZ96: =If(BW96="Keystone",11.5,"") -> 11.5 | CA96: =IF(ISNUMBER(BY96)=TRUE,BY96+BZ96,"") -> 39.9 | CB96: =if(F96="SALE",V96-CA96,"") -> 21.43 | CC96: =if(F96="REFUNDED",iferror(Vlookup(I96,'Listing SKU - Fill SKU Mapping'!A:B,2,false),"Map"),"") | CD96: =if(F96="REFUNDED",iferror(Vlookup(I96,'Listing SKU - Fill SKU Mapping'!A:C,3,false),"Map"),"") | CE96: =TEXT(G96,"YYYY") -> 2025 | CF96: =TEXT(G96,"MMMM") -> June | CG96: =IF(AND((G96-CG$1)>=0,(G96-CG$1)<=6), "This Week",IF(AND((G96-CG$1)>=-7,(G96-CG$1)<=-1), "Last Week",""))
A97: 200010000000000 | B97: 1 | C97: 109020000000000 | D97: 1 | F97: SALE | G97: 45825 | H97: 1 | I97: WM-KS-FRHC-61179-17SBK | J97: 467129958757 | T97: Marketplace standard | U97: 89.07 | V97: 85.54 | W97: 6.44 | X97: 7 | Y97: 81.9 | Z97: 0 | AA97: 0 | AB97: 0 | AC97: 0 | AD97: 0 | AE97: 0 | AF97: 0 | AG97: 0 | AH97: 0 | AI97: 0 | AJ97: 0 | AK97: 0 | AL97: 0 | AM97: 0 | AN97: 0 | AO97: 7.17 | AP97: 0 | AQ97: 0 | AR97: 0 | AS97: 0 | AT97: 0 | AU97: 0 | AV97: 0 | AW97: 0 | AX97: 0 | AY97: 0 | AZ97: 0 | BA97: 0 | BB97: 7.17 | BC97: Y | BF97: 91.98 | BG97: -9.2 | BH97: Wheels & Wheel Components | BI97: Tires & Wheels | BJ97: Automotive Wheel Covers & Hub Caps | BK97: PRO-119076-21.0 | BN97: N | BO97: Seller Fulfilled | BP97: Delivery | BQ97: PRO | BR97: 2.76 | BT97: -10.08 | BU97: PricingIncentives | BW97: =if(OR(F97="SALE",F97="REFUNDED"),IFERROR(Vlookup(I97,'Listing SKU - Fill SKU Mapping'!A:C,3,false),"Map"),"") -> Keystone | BX97: =IF(OR(F97="SALE",F97="REFUNDED")=TRUE,iferror(Vlookup(I97,'Listing SKU - Fill SKU Mapping'!A:B,2,false),"Map"),"") -> 51817SB | BY97: =IF(OR(F97="SALE",F97="REFUNDED")=TRUE,iferror(Vlookup(I97,'Listing SKU - Fill SKU Mapping'!A:D,4,false),"Map"),"") -> 37.08 | BZ97: =If(BW97="Keystone",11.5,"") -> 11.5 | CA97: =IF(ISNUMBER(BY97)=TRUE,BY97+BZ97,"") -> 48.58 | CB97: =if(F97="SALE",V97-CA97,"") -> 36.96 | CC97: =if(F97="REFUNDED",iferror(Vlookup(I97,'Listing SKU - Fill SKU Mapping'!A:B,2,false),"Map"),"") | CD97: =if(F97="REFUNDED",iferror(Vlookup(I97,'Listing SKU - Fill SKU Mapping'!A:C,3,false),"Map"),"") | CE97: =TEXT(G97,"YYYY") -> 2025 | CF97: =TEXT(G97,"MMMM") -> June | CG97: =IF(AND((G97-CG$1)>=0,(G97-CG$1)<=6), "This Week",IF(AND((G97-CG$1)>=-7,(G97-CG$1)<=-1), "Last Week",""))
A98: 200010000000000 | B98: 1 | C98: 109020000000000 | D98: 1 | F98: SALE | G98: 45827 | H98: 1 | I98: WM-KS-FRHC-8038-17SL | J98: 467129941643 | T98: Marketplace standard | U98: 104.25 | V98: 90.19 | W98: 6.79 | X98: 7 | Y98: 96.98 | Z98: 0 | AA98: 0 | AB98: 0 | AC98: 0 | AD98: 0 | AE98: 0 | AF98: 0 | AG98: 0 | AH98: 0 | AI98: 0 | AJ98: 0 | AK98: 0 | AL98: 0 | AM98: 0 | AN98: 0 | AO98: 7.27 | AP98: 0 | AQ98: 0 | AR98: 0 | AS98: 0 | AT98: 0 | AU98: 0 | AV98: 0 | AW98: 0 | AX98: 0 | AY98: 0 | AZ98: 0 | BA98: 0 | BB98: 7.27 | BC98: Y | BG98: -9.7 | BH98: Wheels & Wheel Components | BI98: Tires & Wheels | BJ98: Automotive Wheel Covers & Hub Caps | BK98: PRO-119076-21.0 | BN98: N | BO98: Seller Fulfilled | BP98: Delivery | BQ98: New Seller Saving | BR98: 2.91 | BW98: =if(OR(F98="SALE",F98="REFUNDED"),IFERROR(Vlookup(I98,'Listing SKU - Fill SKU Mapping'!A:C,3,false),"Map"),"") -> Keystone | BX98: =IF(OR(F98="SALE",F98="REFUNDED")=TRUE,iferror(Vlookup(I98,'Listing SKU - Fill SKU Mapping'!A:B,2,false),"Map"),"") -> 46817S | BY98: =IF(OR(F98="SALE",F98="REFUNDED")=TRUE,iferror(Vlookup(I98,'Listing SKU - Fill SKU Mapping'!A:D,4,false),"Map"),"") -> 39.84 | BZ98: =If(BW98="Keystone",11.5,"") -> 11.5 | CA98: =IF(ISNUMBER(BY98)=TRUE,BY98+BZ98,"") -> 51.34 | CB98: =if(F98="SALE",V98-CA98,"") -> 38.85 | CC98: =if(F98="REFUNDED",iferror(Vlookup(I98,'Listing SKU - Fill SKU Mapping'!A:B,2,false),"Map"),"") | CD98: =if(F98="REFUNDED",iferror(Vlookup(I98,'Listing SKU - Fill SKU Mapping'!A:C,3,false),"Map"),"") | CE98: =TEXT(G98,"YYYY") -> 2025 | CF98: =TEXT(G98,"MMMM") -> June | CG98: =IF(AND((G98-CG$1)>=0,(G98-CG$1)<=6), "This Week",IF(AND((G98-CG$1)>=-7,(G98-CG$1)<=-1), "Last Week",""))
A99: 200010000000000 | B99: 1 | C99: 109020000000000 | D99: 1 | F99: SALE | G99: 45824 | H99: 1 | I99: WM-FR-IMP-ML3Z-1007-A-17GB6S | J99: 465595357029 | T99: Marketplace standard | U99: 77.38 | V99: 66.94 | W99: 5.04 | X99: 7 | Y99: 71.98 | Z99: 0 | AA99: 0 | AB99: 0 | AC99: 0 | AD99: 0 | AE99: 0 | AF99: 0 | AG99: 0 | AH99: 0 | AI99: 0 | AJ99: 0 | AK99: 0 | AL99: 0 | AM99: 0 | AN99: 0 | AO99: 5.4 | AP99: 0 | AQ99: 0 | AR99: 0 | AS99: 0 | AT99: 0 | AU99: 0 | AV99: 0 | AW99: 0 | AX99: 0 | AY99: 0 | AZ99: 0 | BA99: 0 | BB99: 5.4 | BC99: Y | BG99: -7.2 | BH99: Wheels & Wheel Components | BI99: Tires & Wheels | BJ99: Automotive Wheel Covers & Hub Caps | BK99: PRO-119076-21.0 | BN99: N | BO99: Seller Fulfilled | BP99: Delivery | BQ99: New Seller Saving | BR99: 2.16 | BW99: =if(OR(F99="SALE",F99="REFUNDED"),IFERROR(Vlookup(I99,'Listing SKU - Fill SKU Mapping'!A:C,3,false),"Map"),"") -> Keystone | BX99: =IF(OR(F99="SALE",F99="REFUNDED")=TRUE,iferror(Vlookup(I99,'Listing SKU - Fill SKU Mapping'!A:B,2,false),"Map"),"") -> IMP477BLK | BY99: =IF(OR(F99="SALE",F99="REFUNDED")=TRUE,iferror(Vlookup(I99,'Listing SKU - Fill SKU Mapping'!A:D,4,false),"Map"),"") -> 48.13 | BZ99: =If(BW99="Keystone",11.5,"") -> 11.5 | CA99: =IF(ISNUMBER(BY99)=TRUE,BY99+BZ99,"") -> 59.63 | CB99: =if(F99="SALE",V99-CA99,"") -> 7.31 | CC99: =if(F99="REFUNDED",iferror(Vlookup(I99,'Listing SKU - Fill SKU Mapping'!A:B,2,false),"Map"),"") | CD99: =if(F99="REFUNDED",iferror(Vlookup(I99,'Listing SKU - Fill SKU Mapping'!A:C,3,false),"Map"),"") | CE99: =TEXT(G99,"YYYY") -> 2025 | CF99: =TEXT(G99,"MMMM") -> June | CG99: =IF(AND((G99-CG$1)>=0,(G99-CG$1)<=6), "This Week",IF(AND((G99-CG$1)>=-7,(G99-CG$1)<=-1), "Last Week",""))
A100: 200010000000000 | B100: 1 | C100: 109020000000000 | D100: 1 | F100: SALE | G100: 45832 | H100: 1 | I100: WM-KS-FRHC-53094-17SL | J100: 467129945498 | T100: Marketplace standard | U100: 72.82 | V100: 70.66 | W100: 5.32 | X100: 7 | Y100: 67.9 | Z100: 0 | AA100: 0 | AB100: 0 | AC100: 0 | AD100: 0 | AE100: 0 | AF100: 0 | AG100: 0 | AH100: 0 | AI100: 0 | AJ100: 0 | AK100: 0 | AL100: 0 | AM100: 0 | AN100: 0 | AO100: 4.92 | AP100: 0 | AQ100: 0 | AR100: 0 | AS100: 0 | AT100: 0 | AU100: 0 | AV100: 0 | AW100: 0 | AX100: 0 | AY100: 0 | AZ100: 0 | BA100: 0 | BB100: 4.92 | BC100: Y | BF100: 75.98 | BG100: -7.6 | BH100: Wheels & Wheel Components | BI100: Tires & Wheels | BJ100: Automotive Wheel Covers & Hub Caps | BK100: PRO-119071-7.0 | BN100: N | BO100: Seller Fulfilled | BP100: Delivery | BQ100: PRO | BR100: 2.28 | BT100: -8.08 | BU100: PricingIncentives | BW100: =if(OR(F100="SALE",F100="REFUNDED"),IFERROR(Vlookup(I100,'Listing SKU - Fill SKU Mapping'!A:C,3,false),"Map"),"") -> Keystone | BX100: =IF(OR(F100="SALE",F100="REFUNDED")=TRUE,iferror(Vlookup(I100,'Listing SKU - Fill SKU Mapping'!A:B,2,false),"Map"),"") -> 51917S | BY100: =IF(OR(F100="SALE",F100="REFUNDED")=TRUE,iferror(Vlookup(I100,'Listing SKU - Fill SKU Mapping'!A:D,4,false),"Map"),"") -> 27.22 | BZ100: =If(BW100="Keystone",11.5,"") -> 11.5 | CA100: =IF(ISNUMBER(BY100)=TRUE,BY100+BZ100,"") -> 38.72 | CB100: =if(F100="SALE",V100-CA100,"") -> 31.94 | CC100: =if(F100="REFUNDED",iferror(Vlookup(I100,'Listing SKU - Fill SKU Mapping'!A:B,2,false),"Map"),"") | CD100: =if(F100="REFUNDED",iferror(Vlookup(I100,'Listing SKU - Fill SKU Mapping'!A:C,3,false),"Map"),"") | CE100: =TEXT(G100,"YYYY") -> 2025 | CF100: =TEXT(G100,"MMMM") -> June | CG100: =IF(AND((G100-CG$1)>=0,(G100-CG$1)<=6), "This Week",IF(AND((G100-CG$1)>=-7,(G100-CG$1)<=-1), "Last Week",""))
...

Sheet Listing SKU - Fill SKU Mapping
A1: Listing SKU | B1: Part Number | C1: Vendor
A2: WM-KS-FRHC-SWUNWSPK-15CH | B2: 1215 | C2: Keystone | D2: 62.76
A3: WM-KS-FRHC-SWUN5SPK-15SL | B3: 102815S | C3: Keystone | D3: 22.88
A4: WM-KS-FRHC-SWUN5SPK-16SL | B4: 102816S | C4: Keystone | D4: 25.25
A5: WM-KS-FRHC-56554-16GBK | B5: 103216BLK | C5: Keystone | D5: 27.22
A6: WM-KS-FRHC-56554-16SL | B6: 103216S | C6: Keystone | D6: 25.25
A7: WM-KS-FRHC-61163-15GBK | B7: 103715BLK | C7: Keystone | D7: 24.85
A8: WM-KS-FRHC-61163-15SL | B8: 103715S | C8: Keystone | D8: 22.88
A9: WM-KS-FRHC-61163-16GBK | B9: 103716BLK | C9: Keystone | D9: 27.22
A10: WM-KS-FRHC-61163-16SL | B10: 103716S | C10: Keystone | D10: 25.25
A11: WM-KS-FRHC-61159-16GBK | B11: 103816BLK | C11: Keystone | D11: 27.22
